Workbook

Sheet KPI Review
D1: ZZEM | J1: 사주 | P1: Speaking
A2: sql과 맞는 Metric | B2: sql과 맞는 Metric | C2: 지표 | D2: W-2 | E2: W-1 | F2: 변화 | G2: M-1 | H2: M0 | I2: 변화 | J2: W-2 | K2: W-1 | L2: 변화 | M2: M-1 | N2: M0 | O2: 변화 | P2: W-2 | Q2: W-1 | R2: 변화 | S2: M-1 | T2: M0 | U2: 변화
A3: Paid_Cohort_Retention | B3: Paid_Cohort_Retention | C3: Paid Cohort Retention | D3: {=LET(val, IFERROR(INDEX('Weekly 쨈 raw'!$A:$AAQ, MATCH(TODAY() - WEEKDAY(TODAY(), 2) - 20, 'Weekly 쨈 raw'!$A:$A, 0), MATCH($A3, 'Weekly 쨈 raw'!$1:$1, 0)), ""), IF(val=0, "", val))} -> 0.46276596 | E3: {=LET(val, IFERROR(INDEX('Weekly 쨈 raw'!$A:$AAQ, MATCH(TODAY() - WEEKDAY(TODAY(), 2) - 13, 'Weekly 쨈 raw'!$A:$A, 0), MATCH($A3, 'Weekly 쨈 raw'!$1:$1, 0)), ""), IF(val=0, "", val))} -> 0.49603175 | F3: =LET(val, IF(OR(E3="", D3=""), "", IFERROR((E3 - D3) / D3, "")), IF(val=0, "", val)) -> 0.071884693 | G3: {=LET(val, IFERROR(INDEX('Monthly 쨈 M raw'!$A:$AAQ, MATCH(EOMONTH(TODAY(), -2) + 1, 'Monthly 쨈 M raw'!$A:$A, 0), MATCH($B3, 'Monthly 쨈 M raw'!$1:$1, 0)), 0), IF(val=0, "", val))} -> 0.60796545 | H3: {=LET(val, IFERROR(INDEX('Monthly 쨈 M raw'!$A:$AAQ, MATCH(EOMONTH(TODAY(), -1) + 1, 'Monthly 쨈 M raw'!$A:$A, 0), MATCH($B3, 'Monthly 쨈 M raw'!$1:$1, 0)), 0), IF(val=0, "", val))} -> 0.48663102 | I3: =LET(val, IF(OR(G3="", H3=""), "", IFERROR((H3 - G3) / G3, "")), IF(val=0, "", val)) -> -0.19957456 | J3: {=LET(val, IFERROR(INDEX('Weekly 사주 raw'!$A:$AAQ, MATCH(TODAY() - WEEKDAY(TODAY(), 2) - 20, 'Weekly 사주 raw'!$A:$A, 0), MATCH($A3, 'Weekly 사주 raw'!$1:$1, 0)), ""), IF(val=0, "", val))} -> 0.36363636 | K3: {=LET(val, IFERROR(INDEX('Weekly 사주 raw'!$A:$AAQ, MATCH(TODAY() - WEEKDAY(TODAY(), 2) - 13, 'Weekly 사주 raw'!$A:$A, 0), MATCH($A3, 'Weekly 사주 raw'!$1:$1, 0)), ""), IF(val=0, "", val))} -> 0.38970588 | L3: =LET(val, IF(OR(K3="", J3=""), "", IFERROR((K3 - J3) / J3, "")), IF(val=0, "", val)) -> 0.071691176 | M3: {=LET(val, IFERROR(INDEX('Monthly 사주 M raw'!$A:$AAQ, MATCH(EOMONTH(TODAY(), -2) + 1, 'Monthly 사주 M raw'!$A:$A, 0), MATCH($B3, 'Monthly 사주 M raw'!$1:$1, 0)), ""), IF(val=0, "", val))} -> 0.41691843 | N3: {=LET(val, IFERROR(INDEX('Monthly 사주 M raw'!$A:$AAQ, MATCH(EOMONTH(TODAY(), -1) + 1, 'Monthly 사주 M raw'!$A:$A, 0), MATCH($B3, 'Monthly 사주 M raw'!$1:$1, 0)), ""), IF(val=0, "", val))} -> 0.44333333 | O3: =LET(val, IF(OR(M3="", N3=""), "", IFERROR((N3 - M3) / M3, "")), IF(val=0, "", val)) -> 0.063357488 | P3: {=LET(val, IFERROR(INDEX('Weekly 스피킹 raw'!$A:$AAQ, MATCH(TODAY() - WEEKDAY(TODAY(), 2) - 20, 'Weekly 스피킹 raw'!$A:$A, 0), MATCH($A3, 'Weekly 스피킹 raw'!$1:$1, 0)), ""), IF(val=0, "", val))} -> 0.89189189 | Q3: {=LET(val, IFERROR(INDEX('Weekly 스피킹 raw'!$A:$AAQ, MATCH(TODAY() - WEEKDAY(TODAY(), 2) - 13, 'Weekly 스피킹 raw'!$A:$A, 0), MATCH($A3, 'Weekly 스피킹 raw'!$1:$1, 0)), ""), IF(val=0, "", val))} -> 0.9 | R3: =LET(val, IFERROR((Q3 - P3) / P3, ""), IF(val=0, "", val)) -> 0.0090909091 | S3: {=LET(val, IFERROR(INDEX('Monthly 스피킹 M raw'!$A:$AAQ, MATCH(EOMONTH(TODAY(), -2) + 1, 'Monthly 스피킹 M raw'!$A:$A, 0), MATCH($B3, 'Monthly 스피킹 M raw'!$1:$1, 0)), ""), IF(val=0, "", val))} -> 0.85365854 | T3: {=LET(val, IFERROR(INDEX('Monthly 스피킹 M raw'!$A:$AAQ, MATCH(EOMONTH(TODAY(), -1) + 1, 'Monthly 스피킹 M raw'!$A:$A, 0), MATCH($B3, 'Monthly 스피킹 M raw'!$1:$1, 0)), ""), IF(val=0, "", val))} -> 0.82914573 | U3: =LET(val, IF(OR(S3="", T3=""), "", IFERROR((T3 - S3) / S3, "")), IF(val=0, "", val)) -> -0.028715004
A4: W1_Any_Event_User | B4: M1_Any_Event_User | C4: ㄴ x0 Any Event User | D4: {=LET(val, IFERROR(INDEX('Weekly 쨈 raw'!$A:$AAQ, MATCH(TODAY() - WEEKDAY(TODAY(), 2) - 20, 'Weekly 쨈 raw'!$A:$A, 0), MATCH($A4, 'Weekly 쨈 raw'!$1:$1, 0)), ""), IF(val=0, "", val))} -> 87 | E4: {=LET(val, IFERROR(INDEX('Weekly 쨈 raw'!$A:$AAQ, MATCH(TODAY() - WEEKDAY(TODAY(), 2) - 13, 'Weekly 쨈 raw'!$A:$A, 0), MATCH($A4, 'Weekly 쨈 raw'!$1:$1, 0)), ""), IF(val=0, "", val))} -> 125 | F4: =LET(val, IF(OR(E4="", D4=""), "", IFERROR((E4 - D4) / D4, "")), IF(val=0, "", val)) -> 0.43678161 | G4: {=LET(val, IFERROR(INDEX('Monthly 쨈 M raw'!$A:$AAQ, MATCH(EOMONTH(TODAY(), -2) + 1, 'Monthly 쨈 M raw'!$A:$A, 0), MATCH($B4, 'Monthly 쨈 M raw'!$1:$1, 0)), 0), IF(val=0, "", val))} -> 1267 | H4: {=LET(val, IFERROR(INDEX('Monthly 쨈 M raw'!$A:$AAQ, MATCH(EOMONTH(TODAY(), -1) + 1, 'Monthly 쨈 M raw'!$A:$A, 0), MATCH($B4, 'Monthly 쨈 M raw'!$1:$1, 0)), 0), IF(val=0, "", val))} -> 637 | I4: =LET(val, IF(OR(G4="", H4=""), "", IFERROR((H4 - G4) / G4, "")), IF(val=0, "", val)) -> -0.49723757 | J4: {=LET(val, IFERROR(INDEX('Weekly 사주 raw'!$A:$AAQ, MATCH(TODAY() - WEEKDAY(TODAY(), 2) - 20, 'Weekly 사주 raw'!$A:$A, 0), MATCH($A4, 'Weekly 사주 raw'!$1:$1, 0)), ""), IF(val=0, "", val))} -> 88 | K4: {=LET(val, IFERROR(INDEX('Weekly 사주 raw'!$A:$AAQ, MATCH(TODAY() - WEEKDAY(TODAY(), 2) - 13, 'Weekly 사주 raw'!$A:$A, 0), MATCH($A4, 'Weekly 사주 raw'!$1:$1, 0)), ""), IF(val=0, "", val))} -> 53 | L4: =LET(val, IF(OR(K4="", J4=""), "", IFERROR((K4 - J4) / J4, "")), IF(val=0, "", val)) -> -0.39772727 | M4: {=LET(val, IFERROR(INDEX('Monthly 사주 M raw'!$A:$AAQ, MATCH(EOMONTH(TODAY(), -2) + 1, 'Monthly 사주 M raw'!$A:$A, 0), MATCH($B4, 'Monthly 사주 M raw'!$1:$1, 0)), ""), IF(val=0, "", val))} -> 138 | N4: {=LET(val, IFERROR(INDEX('Monthly 사주 M raw'!$A:$AAQ, MATCH(EOMONTH(TODAY(), -1) + 1, 'Monthly 사주 M raw'!$A:$A, 0), MATCH($B4, 'Monthly 사주 M raw'!$1:$1, 0)), ""), IF(val=0, "", val))} -> 532 | O4: =LET(val, IF(OR(M4="", N4=""), "", IFERROR((N4 - M4) / M4, "")), IF(val=0, "", val)) -> 2.8550725 | P4: {=LET(val, IFERROR(INDEX('Weekly 스피킹 raw'!$A:$AAQ, MATCH(TODAY() - WEEKDAY(TODAY(), 2) - 20, 'Weekly 스피킹 raw'!$A:$A, 0), MATCH($A4, 'Weekly 스피킹 raw'!$1:$1, 0)), ""), IF(val=0, "", val))} -> 33 | Q4: {=LET(val, IFERROR(INDEX('Weekly 스피킹 raw'!$A:$AAQ, MATCH(TODAY() - WEEKDAY(TODAY(), 2) - 13, 'Weekly 스피킹 raw'!$A:$A, 0), MATCH($A4, 'Weekly 스피킹 raw'!$1:$1, 0)), ""), IF(val=0, "", val))} -> 18 | R4: =LET(val, IFERROR((Q4 - P4) / P4, ""), IF(val=0, "", val)) -> -0.45454545 | S4: {=LET(val, IFERROR(INDEX('Monthly 스피킹 M raw'!$A:$AAQ, MATCH(EOMONTH(TODAY(), -2) + 1, 'Monthly 스피킹 M raw'!$A:$A, 0), MATCH($B4, 'Monthly 스피킹 M raw'!$1:$1, 0)), ""), IF(val=0, "", val))} -> 35 | T4: {=LET(val, IFERROR(INDEX('Monthly 스피킹 M raw'!$A:$AAQ, MATCH(EOMONTH(TODAY(), -1) + 1, 'Monthly 스피킹 M raw'!$A:$A, 0), MATCH($B4, 'Monthly 스피킹 M raw'!$1:$1, 0)), ""), IF(val=0, "", val))} -> 165 | U4: =LET(val, IF(OR(S4="", T4=""), "", IFERROR((T4 - S4) / S4, "")), IF(val=0, "", val)) -> 3.7142857
A5: W0_Purchase_Done_User | B5: M0_Purchase_Done_User | C5: ㄴ x-1 Purchase Done User | D5: {=LET(val, IFERROR(INDEX('Weekly 쨈 raw'!$A:$AAQ, MATCH(TODAY() - WEEKDAY(TODAY(), 2) - 20, 'Weekly 쨈 raw'!$A:$A, 0), MATCH($A5, 'Weekly 쨈 raw'!$1:$1, 0)), ""), IF(val=0, "", val))} -> 188 | E5: {=LET(val, IFERROR(INDEX('Weekly 쨈 raw'!$A:$AAQ, MATCH(TODAY() - WEEKDAY(TODAY(), 2) - 13, 'Weekly 쨈 raw'!$A:$A, 0), MATCH($A5, 'Weekly 쨈 raw'!$1:$1, 0)), ""), IF(val=0, "", val))} -> 252 | F5: =LET(val, IFERROR((E5 - D5) / D5, ""), IF(val=0, "", val)) -> 0.34042553 | G5: {=LET(val, IFERROR(INDEX('Monthly 쨈 M raw'!$A:$AAQ, MATCH(EOMONTH(TODAY(), -2) + 1, 'Monthly 쨈 M raw'!$A:$A, 0), MATCH($B5, 'Monthly 쨈 M raw'!$1:$1, 0)), 0), IF(val=0, "", val))} -> 2084 | H5: {=LET(val, IFERROR(INDEX('Monthly 쨈 M raw'!$A:$AAQ, MATCH(EOMONTH(TODAY(), -1) + 1, 'Monthly 쨈 M raw'!$A:$A, 0), MATCH($B5, 'Monthly 쨈 M raw'!$1:$1, 0)), 0), IF(val=0, "", val))} -> 1309 | I5: =LET(val, IF(OR(G5="", H5=""), "", IFERROR((H5 - G5) / G5, "")), IF(val=0, "", val)) -> -0.371881 | J5: {=LET(val, IFERROR(INDEX('Weekly 사주 raw'!$A:$AAQ, MATCH(TODAY() - WEEKDAY(TODAY(), 2) - 20, 'Weekly 사주 raw'!$A:$A, 0), MATCH($A5, 'Weekly 사주 raw'!$1:$1, 0)), ""), IF(val=0, "", val))} -> 242 | K5: {=LET(val, IFERROR(INDEX('Weekly 사주 raw'!$A:$AAQ, MATCH(TODAY() - WEEKDAY(TODAY(), 2) - 13, 'Weekly 사주 raw'!$A:$A, 0), MATCH($A5, 'Weekly 사주 raw'!$1:$1, 0)), ""), IF(val=0, "", val))} -> 136 | L5: =LET(val, IFERROR((K5 - J5) / J5, ""), IF(val=0, "", val)) -> -0.43801653 | M5: {=LET(val, IFERROR(INDEX('Monthly 사주 M raw'!$A:$AAQ, MATCH(EOMONTH(TODAY(), -2) + 1, 'Monthly 사주 M raw'!$A:$A, 0), MATCH($B5, 'Monthly 사주 M raw'!$1:$1, 0)), ""), IF(val=0, "", val))} -> 331 | N5: {=LET(val, IFERROR(INDEX('Monthly 사주 M raw'!$A:$AAQ, MATCH(EOMONTH(TODAY(), -1) + 1, 'Monthly 사주 M raw'!$A:$A, 0), MATCH($B5, 'Monthly 사주 M raw'!$1:$1, 0)), ""), IF(val=0, "", val))} -> 1200 | O5: =LET(val, IF(OR(M5="", N5=""), "", IFERROR((N5 - M5) / M5, "")), IF(val=0, "", val)) -> 2.6253776 | P5: {=LET(val, IFERROR(INDEX('Weekly 스피킹 raw'!$A:$AAQ, MATCH(TODAY() - WEEKDAY(TODAY(), 2) - 20, 'Weekly 스피킹 raw'!$A:$A, 0), MATCH($A5, 'Weekly 스피킹 raw'!$1:$1, 0)), ""), IF(val=0, "", val))} -> 37 | Q5: {=LET(val, IFERROR(INDEX('Weekly 스피킹 raw'!$A:$AAQ, MATCH(TODAY() - WEEKDAY(TODAY(), 2) - 13, 'Weekly 스피킹 raw'!$A:$A, 0), MATCH($A5, 'Weekly 스피킹 raw'!$1:$1, 0)), ""), IF(val=0, "", val))} -> 20 | R5: =LET(val, IFERROR((Q5 - P5) / P5, ""), IF(val=0, "", val)) -> -0.45945946 | S5: {=LET(val, IFERROR(INDEX('Monthly 스피킹 M raw'!$A:$AAQ, MATCH(EOMONTH(TODAY(), -2) + 1, 'Monthly 스피킹 M raw'!$A:$A, 0), MATCH($B5, 'Monthly 스피킹 M raw'!$1:$1, 0)), ""), IF(val=0, "", val))} -> 41 | T5: {=LET(val, IFERROR(INDEX('Monthly 스피킹 M raw'!$A:$AAQ, MATCH(EOMONTH(TODAY(), -1) + 1, 'Monthly 스피킹 M raw'!$A:$A, 0), MATCH($B5, 'Monthly 스피킹 M raw'!$1:$1, 0)), ""), IF(val=0, "", val))} -> 199 | U5: =LET(val, IF(OR(S5="", T5=""), "", IFERROR((T5 - S5) / S5, "")), IF(val=0, "", val)) -> 3.8536585
A7: CVR | B7: CVR | C7: CVR | D7: {=LET(val, IFERROR(INDEX('Weekly 쨈 raw'!$A:$AAQ, MATCH(TODAY() - WEEKDAY(TODAY(), 2) - 13, 'Weekly 쨈 raw'!$A:$A, 0), MATCH($A7, 'Weekly 쨈 raw'!$1:$1, 0)), ""), IF(val=0, "", val))} -> 0.1596474 | E7: {=LET(val, IFERROR(INDEX('Weekly 쨈 raw'!$A:$AAQ, MATCH(TODAY() - WEEKDAY(TODAY(), 2) - 6, 'Weekly 쨈 raw'!$A:$A, 0), MATCH($A7, 'Weekly 쨈 raw'!$1:$1, 0)), ""), IF(val=0, "", val))} -> 0.20490072 | F7: =LET(val, IFERROR((E7 - D7) / D7, ""), IF(val=0, "", val)) -> 0.28345787 | G7: {=LET(val, IFERROR(INDEX('Monthly 쨈 M raw'!$A:$AAQ, MATCH(EOMONTH(TODAY(), -2) + 1, 'Monthly 쨈 M raw'!$A:$A, 0), MATCH($B7, 'Monthly 쨈 M raw'!$1:$1, 0)), 0), IF(val=0, "", val))} -> 0.17133465 | H7: {=LET(val, IFERROR(INDEX('Monthly 쨈 M raw'!$A:$AAQ, MATCH(EOMONTH(TODAY(), -1) + 1, 'Monthly 쨈 M raw'!$A:$A, 0), MATCH($B7, 'Monthly 쨈 M raw'!$1:$1, 0)), ""), IF(val=0, "", val))} -> 0.16825397 | I7: =LET(val, IF(OR(G7="", H7=""), "", IFERROR((H7 - G7) / G7, "")), IF(val=0, "", val)) -> -0.017980485 | J7: {=LET(val, IFERROR(INDEX('Weekly 사주 raw'!$A:$AAQ, MATCH(TODAY() - WEEKDAY(TODAY(), 2) - 13, 'Weekly 사주 raw'!$A:$A, 0), MATCH($A7, 'Weekly 사주 raw'!$1:$1, 0)), ""), IF(val=0, "", val))} -> 0.13826607 | K7: {=LET(val, IFERROR(INDEX('Weekly 사주 raw'!$A:$AAQ, MATCH(TODAY() - WEEKDAY(TODAY(), 2) - 6, 'Weekly 사주 raw'!$A:$A, 0), MATCH($A7, 'Weekly 사주 raw'!$1:$1, 0)), ""), IF(val=0, "", val))} -> 0.16679657 | L7: =LET(val, IFERROR((K7 - J7) / J7, ""), IF(val=0, "", val)) -> 0.20634493 | M7: {=LET(val, IFERROR(INDEX('Monthly 사주 M raw'!$A:$AAQ, MATCH(EOMONTH(TODAY(), -2) + 1, 'Monthly 사주 M raw'!$A:$A, 0), MATCH($B7, 'Monthly 사주 M raw'!$1:$1, 0)), ""), IF(val=0, "", val))} -> 0.11255141 | N7: {=LET(val, IFERROR(INDEX('Monthly 사주 M raw'!$A:$AAQ, MATCH(EOMONTH(TODAY(), -1) + 1, 'Monthly 사주 M raw'!$A:$A, 0), MATCH($B7, 'Monthly 사주 M raw'!$1:$1, 0)), ""), IF(val=0, "", val))} -> 0.15896151 | O7: =LET(val, IF(OR(M7="", N7=""), "", IFERROR((N7 - M7) / M7, "")), IF(val=0, "", val)) -> 0.41234575 | P7: {=LET(val, IFERROR(INDEX('Weekly 스피킹 raw'!$A:$AAQ, MATCH(TODAY() - WEEKDAY(TODAY(), 2) - 13, 'Weekly 스피킹 raw'!$A:$A, 0), MATCH($A7, 'Weekly 스피킹 raw'!$1:$1, 0)), ""), IF(val=0, "", val))} -> 0.0029631143 | Q7: {=LET(val, IFERROR(INDEX('Weekly 스피킹 raw'!$A:$AAQ, MATCH(TODAY() - WEEKDAY(TODAY(), 2) - 6, 'Weekly 스피킹 raw'!$A:$A, 0), MATCH($A7, 'Weekly 스피킹 raw'!$1:$1, 0)), ""), IF(val=0, "", val))} -> 0.0034466366 | R7: =LET(val, IFERROR((Q7 - P7) / P7, ""), IF(val=0, "", val)) -> 0.16318041 | S7: {=LET(val, IFERROR(INDEX('Monthly 스피킹 M raw'!$A:$AAQ, MATCH(EOMONTH(TODAY(), -2) + 1, 'Monthly 스피킹 M raw'!$A:$A, 0), MATCH($B7, 'Monthly 스피킹 M raw'!$1:$1, 0)), ""), IF(val=0, "", val))} -> 0.0050385479 | T7: {=LET(val, IFERROR(INDEX('Monthly 스피킹 raw'!$A:$AAQ, MATCH(EOMONTH(TODAY(), -1) + 1, 'Monthly 스피킹 raw'!$A:$A, 0), MATCH($B7, 'Monthly 스피킹 raw'!$1:$1, 0)), ""), IF(val=0, "", val))} -> 0.0051045538 | U7: =LET(val, IF(OR(S7="", T7=""), "", IFERROR((T7 - S7) / S7, "")), IF(val=0, "", val)) -> 0.013100178
A8: Purchase_Done_User_CVR | B8: Purchase_Done_User_CVR | C8: ㄴ Purchase Done User | D8: {=LET(val, IFERROR(INDEX('Weekly 쨈 raw'!$A:$AAQ, MATCH(TODAY() - WEEKDAY(TODAY(), 2) - 13, 'Weekly 쨈 raw'!$A:$A, 0), MATCH($A8, 'Weekly 쨈 raw'!$1:$1, 0)), ""), IF(val=0, "", val))} -> 326 | E8: {=LET(val, IFERROR(INDEX('Weekly 쨈 raw'!$A:$AAQ, MATCH(TODAY() - WEEKDAY(TODAY(), 2) - 6, 'Weekly 쨈 raw'!$A:$A, 0), MATCH($A8, 'Weekly 쨈 raw'!$1:$1, 0)), ""), IF(val=0, "", val))} -> 485 | F8: =LET(val, IFERROR((E8 - D8) / D8, ""), IF(val=0, "", val)) -> 0.48773006 | G8: {=LET(val, IFERROR(INDEX('Monthly 쨈 M raw'!$A:$AAQ, MATCH(EOMONTH(TODAY(), -2) + 1, 'Monthly 쨈 M raw'!$A:$A, 0), MATCH($B8, 'Monthly 쨈 M raw'!$1:$1, 0)), ""), IF(val=0, "", val))} -> 1303 | H8: {=LET(val, IFERROR(INDEX('Monthly 쨈 M raw'!$A:$AAQ, MATCH(EOMONTH(TODAY(), -1) + 1, 'Monthly 쨈 M raw'!$A:$A, 0), MATCH($B8, 'Monthly 쨈 M raw'!$1:$1, 0)), ""), IF(val=0, "", val))} -> 1060 | I8: =LET(val, IF(OR(G8="", H8=""), "", IFERROR((H8 - G8) / G8, "")), IF(val=0, "", val)) -> -0.18649271 | J8: {=LET(val, IFERROR(INDEX('Weekly 사주 raw'!$A:$AAQ, MATCH(TODAY() - WEEKDAY(TODAY(), 2) - 13, 'Weekly 사주 raw'!$A:$A, 0), MATCH($A8, 'Weekly 사주 raw'!$1:$1, 0)), ""), IF(val=0, "", val))} -> 185 | K8: {=LET(val, IFERROR(INDEX('Weekly 사주 raw'!$A:$AAQ, MATCH(TODAY() - WEEKDAY(TODAY(), 2) - 6, 'Weekly 사주 raw'!$A:$A, 0), MATCH($A8, 'Weekly 사주 raw'!$1:$1, 0)), ""), IF(val=0, "", val))} -> 214 | L8: =LET(val, IFERROR((K8 - J8) / J8, ""), IF(val=0, "", val)) -> 0.15675676 | M8: {=LET(val, IFERROR(INDEX('Monthly 사주 M raw'!$A:$AAQ, MATCH(EOMONTH(TODAY(), -2) + 1, 'Monthly 사주 M raw'!$A:$A, 0), MATCH($B8, 'Monthly 사주 M raw'!$1:$1, 0)), ""), IF(val=0, "", val))} -> 903 | N8: {=LET(val, IFERROR(INDEX('Monthly 사주 M raw'!$A:$AAQ, MATCH(EOMONTH(TODAY(), -1) + 1, 'Monthly 사주 M raw'!$A:$A, 0), MATCH($B8, 'Monthly 사주 M raw'!$1:$1, 0)), ""), IF(val=0, "", val))} -> 698 | O8: =LET(val, IF(OR(M8="", N8=""), "", IFERROR((N8 - M8) / M8, "")), IF(val=0, "", val)) -> -0.22702104 | P8: {=LET(val, IFERROR(INDEX('Weekly 스피킹 raw'!$A:$AAQ, MATCH(TODAY() - WEEKDAY(TODAY(), 2) - 13, 'Weekly 스피킹 raw'!$A:$A, 0), MATCH($A8, 'Weekly 스피킹 raw'!$1:$1, 0)), ""), IF(val=0, "", val))} -> 29 | Q8: {=LET(val, IFERROR(INDEX('Weekly 스피킹 raw'!$A:$AAQ, MATCH(TODAY() - WEEKDAY(TODAY(), 2) - 6, 'Weekly 스피킹 raw'!$A:$A, 0), MATCH($A8, 'Weekly 스피킹 raw'!$1:$1, 0)), ""), IF(val=0, "", val))} -> 29 | R8: =LET(val, IFERROR((Q8 - P8) / P8, ""), IF(val=0, "", val)) | S8: {=LET(val, IFERROR(INDEX('Monthly 스피킹 M raw'!$A:$AAQ, MATCH(EOMONTH(TODAY(), -2) + 1, 'Monthly 스피킹 M raw'!$A:$A, 0), MATCH($B8, 'Monthly 스피킹 M raw'!$1:$1, 0)), ""), IF(val=0, "", val))} -> 166 | T8: {=LET(val, IFERROR(INDEX('Monthly 스피킹 raw'!$A:$AAQ, MATCH(EOMONTH(TODAY(), -1) + 1, 'Monthly 스피킹 raw'!$A:$A, 0), MATCH($B8, 'Monthly 스피킹 raw'!$1:$1, 0)), ""), IF(val=0, "", val))} -> 114 | U8: =LET(val, IF(OR(S8="", T8=""), "", IFERROR((T8 - S8) / S8, "")), IF(val=0, "", val)) -> -0.31325301
A9: Gen_Done_User | B9: Gen_Done_User | C9: ㄴ Gen Done User | D9: {=LET(val, IFERROR(INDEX('Weekly 쨈 raw'!$A:$AAQ, MATCH(TODAY() - WEEKDAY(TODAY(), 2) - 13, 'Weekly 쨈 raw'!$A:$A, 0), MATCH($A9, 'Weekly 쨈 raw'!$1:$1, 0)), ""), IF(val=0, "", val))} -> 2042 | E9: {=LET(val, IFERROR(INDEX('Weekly 쨈 raw'!$A:$AAQ, MATCH(TODAY() - WEEKDAY(TODAY(), 2) - 6, 'Weekly 쨈 raw'!$A:$A, 0), MATCH($A9, 'Weekly 쨈 raw'!$1:$1, 0)), ""), IF(val=0, "", val))} -> 2367 | F9: =LET(val, IFERROR((E9 - D9) / D9, ""), IF(val=0, "", val)) -> 0.15915769 | G9: {=LET(val, IFERROR(INDEX('Monthly 쨈 M raw'!$A:$AAQ, MATCH(EOMONTH(TODAY(), -2) + 1, 'Monthly 쨈 M raw'!$A:$A, 0), MATCH($B9, 'Monthly 쨈 M raw'!$1:$1, 0)), ""), IF(val=0, "", val))} -> 7605 | H9: {=LET(val, IFERROR(INDEX('Monthly 쨈 M raw'!$A:$AAQ, MATCH(EOMONTH(TODAY(), -1) + 1, 'Monthly 쨈 M raw'!$A:$A, 0), MATCH($B9, 'Monthly 쨈 M raw'!$1:$1, 0)), ""), IF(val=0, "", val))} -> 6300 | I9: =LET(val, IF(OR(G9="", H9=""), "", IFERROR((H9 - G9) / G9, "")), IF(val=0, "", val)) -> -0.17159763 | J9: {=LET(val, IFERROR(INDEX('Weekly 사주 raw'!$A:$AAQ, MATCH(TODAY() - WEEKDAY(TODAY(), 2) - 13, 'Weekly 사주 raw'!$A:$A, 0), MATCH($A9, 'Weekly 사주 raw'!$1:$1, 0)), ""), IF(val=0, "", val))} -> 1338 | K9: {=LET(val, IFERROR(INDEX('Weekly 사주 raw'!$A:$AAQ, MATCH(TODAY() - WEEKDAY(TODAY(), 2) - 6, 'Weekly 사주 raw'!$A:$A, 0), MATCH($A9, 'Weekly 사주 raw'!$1:$1, 0)), ""), IF(val=0, "", val))} -> 1283 | L9: =LET(val, IFERROR((K9 - J9) / J9, ""), IF(val=0, "", val)) -> -0.041106129 | M9: {=LET(val, IFERROR(INDEX('Monthly 사주 M raw'!$A:$AAQ, MATCH(EOMONTH(TODAY(), -2) + 1, 'Monthly 사주 M raw'!$A:$A, 0), MATCH($B9, 'Monthly 사주 M raw'!$1:$1, 0)), ""), IF(val=0, "", val))} -> 8023 | N9: {=LET(val, IFERROR(INDEX('Monthly 사주 M raw'!$A:$AAQ, MATCH(EOMONTH(TODAY(), -1) + 1, 'Monthly 사주 M raw'!$A:$A, 0), MATCH($B9, 'Monthly 사주 M raw'!$1:$1, 0)), ""), IF(val=0, "", val))} -> 4391 | O9: =LET(val, IF(OR(M9="", N9=""), "", IFERROR((N9 - M9) / M9, "")), IF(val=0, "", val)) -> -0.45269849 | P9: {=LET(val, IFERROR(INDEX('Weekly 스피킹 raw'!$A:$AAQ, MATCH(TODAY() - WEEKDAY(TODAY(), 2) - 13, 'Weekly 스피킹 raw'!$A:$A, 0), MATCH($A9, 'Weekly 스피킹 raw'!$1:$1, 0)), ""), IF(val=0, "", val))} -> 9787 | Q9: {=LET(val, IFERROR(INDEX('Weekly 스피킹 raw'!$A:$AAQ, MATCH(TODAY() - WEEKDAY(TODAY(), 2) - 6, 'Weekly 스피킹 raw'!$A:$A, 0), MATCH($A9, 'Weekly 스피킹 raw'!$1:$1, 0)), ""), IF(val=0, "", val))} -> 8414 | R9: =LET(val, IFERROR((Q9 - P9) / P9, ""), IF(val=0, "", val)) -> -0.14028814 | S9: {=LET(val, IFERROR(INDEX('Monthly 스피킹 M raw'!$A:$AAQ, MATCH(EOMONTH(TODAY(), -2) + 1, 'Monthly 스피킹 M raw'!$A:$A, 0), MATCH($B9, 'Monthly 스피킹 M raw'!$1:$1, 0)), ""), IF(val=0, "", val))} -> 32946 | T9: {=LET(val, IFERROR(INDEX('Monthly 스피킹 raw'!$A:$AAQ, MATCH(EOMONTH(TODAY(), -1) + 1, 'Monthly 스피킹 raw'!$A:$A, 0), MATCH($B9, 'Monthly 스피킹 raw'!$1:$1, 0)), ""), IF(val=0, "", val))} -> 22333 | U9: =LET(val, IF(OR(S9="", T9=""), "", IFERROR((T9 - S9) / S9, "")), IF(val=0, "", val)) -> -0.32213319
A10: Gen_Done_Count | B10: Gen_Done_Count | C10: ㄴ Gen Done Count | D10: {=LET(val, IFERROR(INDEX('Weekly 쨈 raw'!$A:$AAQ, MATCH(TODAY() - WEEKDAY(TODAY(), 2) - 13, 'Weekly 쨈 raw'!$A:$A, 0), MATCH($A10, 'Weekly 쨈 raw'!$1:$1, 0)), ""), IF(val=0, "", val))} -> 7739 | E10: {=LET(val, IFERROR(INDEX('Weekly 쨈 raw'!$A:$AAQ, MATCH(TODAY() - WEEKDAY(TODAY(), 2) - 6, 'Weekly 쨈 raw'!$A:$A, 0), MATCH($A10, 'Weekly 쨈 raw'!$1:$1, 0)), ""), IF(val=0, "", val))} -> 8951 | F10: =LET(val, IFERROR((E10 - D10) / D10, ""), IF(val=0, "", val)) -> 0.15660938 | G10: {=LET(val, IFERROR(INDEX('Monthly 쨈 M raw'!$A:$AAQ, MATCH(EOMONTH(TODAY(), -2) + 1, 'Monthly 쨈 M raw'!$A:$A, 0), MATCH($B10, 'Monthly 쨈 M raw'!$1:$1, 0)), ""), IF(val=0, "", val))} -> 29720 | H10: {=LET(val, IFERROR(INDEX('Monthly 쨈 M raw'!$A:$AAQ, MATCH(EOMONTH(TODAY(), -1) + 1, 'Monthly 쨈 M raw'!$A:$A, 0), MATCH($B10, 'Monthly 쨈 M raw'!$1:$1, 0)), ""), IF(val=0, "", val))} -> 26580 | I10: =LET(val, IF(OR(G10="", H10=""), "", IFERROR((H10 - G10) / G10, "")), IF(val=0, "", val)) -> -0.10565276 | J10: {=LET(val, IFERROR(INDEX('Weekly 사주 raw'!$A:$AAQ, MATCH(TODAY() - WEEKDAY(TODAY(), 2) - 13, 'Weekly 사주 raw'!$A:$A, 0), MATCH($A10, 'Weekly 사주 raw'!$1:$1, 0)), ""), IF(val=0, "", val))} -> 3348 | K10: {=LET(val, IFERROR(INDEX('Weekly 사주 raw'!$A:$AAQ, MATCH(TODAY() - WEEKDAY(TODAY(), 2) - 6, 'Weekly 사주 raw'!$A:$A, 0), MATCH($A10, 'Weekly 사주 raw'!$1:$1, 0)), ""), IF(val=0, "", val))} -> 3239 | L10: =LET(val, IFERROR((K10 - J10) / J10, ""), IF(val=0, "", val)) -> -0.03255675 | M10: {=LET(val, IFERROR(INDEX('Monthly 사주 M raw'!$A:$AAQ, MATCH(EOMONTH(TODAY(), -2) + 1, 'Monthly 사주 M raw'!$A:$A, 0), MATCH($B10, 'Monthly 사주 M raw'!$1:$1, 0)), ""), IF(val=0, "", val))} -> 25804 | N10: {=LET(val, IFERROR(INDEX('Monthly 사주 M raw'!$A:$AAQ, MATCH(EOMONTH(TODAY(), -1) + 1, 'Monthly 사주 M raw'!$A:$A, 0), MATCH($B10, 'Monthly 사주 M raw'!$1:$1, 0)), ""), IF(val=0, "", val))} -> 11965 | O10: =LET(val, IF(OR(M10="", N10=""), "", IFERROR((N10 - M10) / M10, "")), IF(val=0, "", val)) -> -0.5363122 | P10: {=LET(val, IFERROR(INDEX('Weekly 스피킹 raw'!$A:$AAQ, MATCH(TODAY() - WEEKDAY(TODAY(), 2) - 13, 'Weekly 스피킹 raw'!$A:$A, 0), MATCH($A10, 'Weekly 스피킹 raw'!$1:$1, 0)), ""), IF(val=0, "", val))} -> 88753 | Q10: {=LET(val, IFERROR(INDEX('Weekly 스피킹 raw'!$A:$AAQ, MATCH(TODAY() - WEEKDAY(TODAY(), 2) - 6, 'Weekly 스피킹 raw'!$A:$A, 0), MATCH($A10, 'Weekly 스피킹 raw'!$1:$1, 0)), ""), IF(val=0, "", val))} -> 67528 | R10: =LET(val, IFERROR((Q10 - P10) / P10, ""), IF(val=0, "", val)) -> -0.23914685 | S10: {=LET(val, IFERROR(INDEX('Monthly 스피킹 M raw'!$A:$AAQ, MATCH(EOMONTH(TODAY(), -2) + 1, 'Monthly 스피킹 M raw'!$A:$A, 0), MATCH($B10, 'Monthly 스피킹 M raw'!$1:$1, 0)), ""), IF(val=0, "", val))} -> 634217 | T10: {=LET(val, IFERROR(INDEX('Monthly 스피킹 raw'!$A:$AAQ, MATCH(EOMONTH(TODAY(), -1) + 1, 'Monthly 스피킹 raw'!$A:$A, 0), MATCH($B10, 'Monthly 스피킹 raw'!$1:$1, 0)), ""), IF(val=0, "", val))} -> 293658 | U10: =LET(val, IF(OR(S10="", T10=""), "", IFERROR((T10 - S10) / S10, "")), IF(val=0, "", val)) -> -0.53697551
A12: ARPPU | B12: ARPPU | C12: ARPPU | D12: {=LET(val, IFERROR(INDEX('Weekly 쨈 raw'!$A:$AAQ, MATCH(TODAY() - WEEKDAY(TODAY(), 2) - 13, 'Weekly 쨈 raw'!$A:$A, 0), MATCH($A12, 'Weekly 쨈 raw'!$1:$1, 0)), ""), IF(val=0, "", val))} -> 18170.552 | E12: {=LET(val, IFERROR(INDEX('Weekly 쨈 raw'!$A:$AAQ, MATCH(TODAY() - WEEKDAY(TODAY(), 2) - 6, 'Weekly 쨈 raw'!$A:$A, 0), MATCH($A12, 'Weekly 쨈 raw'!$1:$1, 0)), ""), IF(val=0, "", val))} -> 17841.237 | F12: =LET(val, IFERROR((E12 - D12) / D12, ""), IF(val=0, "", val)) -> -0.018123557 | G12: {=LET(val, IFERROR(INDEX('Monthly 쨈 M raw'!$A:$AAQ, MATCH(EOMONTH(TODAY(), -2) + 1, 'Monthly 쨈 M raw'!$A:$A, 0), MATCH($B12, 'Monthly 쨈 M raw'!$1:$1, 0)), 0), IF(val=0, "", val))} -> 8511.2817 | H12: {=LET(val, IFERROR(INDEX('Monthly 쨈 M raw'!$A:$AAQ, MATCH(EOMONTH(TODAY(), -1) + 1, 'Monthly 쨈 M raw'!$A:$A, 0), MATCH($B12, 'Monthly 쨈 M raw'!$1:$1, 0)), ""), IF(val=0, "", val))} -> 18036.132 | I12: =LET(val, IF(OR(G12="", H12=""), "", IFERROR((H12 - G12) / G12, "")), IF(val=0, "", val)) -> 1.1190853 | J12: {=LET(val, IFERROR(INDEX('Weekly 사주 raw'!$A:$AAQ, MATCH(TODAY() - WEEKDAY(TODAY(), 2) - 13, 'Weekly 사주 raw'!$A:$A, 0), MATCH($A12, 'Weekly 사주 raw'!$1:$1, 0)), ""), IF(val=0, "", val))} -> 24025.405 | K12: {=LET(val, IFERROR(INDEX('Weekly 사주 raw'!$A:$AAQ, MATCH(TODAY() - WEEKDAY(TODAY(), 2) - 6, 'Weekly 사주 raw'!$A:$A, 0), MATCH($A12, 'Weekly 사주 raw'!$1:$1, 0)), ""), IF(val=0, "", val))} -> 24415.421 | L12: =LET(val, IFERROR((K12 - J12) / J12, ""), IF(val=0, "", val)) -> 0.016233447 | M12: {=LET(val, IFERROR(INDEX('Monthly 사주 M raw'!$A:$AAQ, MATCH(EOMONTH(TODAY(), -2) + 1, 'Monthly 사주 M raw'!$A:$A, 0), MATCH($B12, 'Monthly 사주 M raw'!$1:$1, 0)), ""), IF(val=0, "", val))} -> 23157.918 | N12: {=LET(val, IFERROR(INDEX('Monthly 사주 M raw'!$A:$AAQ, MATCH(EOMONTH(TODAY(), -1) + 1, 'Monthly 사주 M raw'!$A:$A, 0), MATCH($B12, 'Monthly 사주 M raw'!$1:$1, 0)), ""), IF(val=0, "", val))} -> 24889.398 | O12: =LET(val, IF(OR(M12="", N12=""), "", IFERROR((N12 - M12) / M12, "")), IF(val=0, "", val)) -> 0.074768389 | P12: {=LET(val, IFERROR(INDEX('Weekly 스피킹 raw'!$A:$AAQ, MATCH(TODAY() - WEEKDAY(TODAY(), 2) - 13, 'Weekly 스피킹 raw'!$A:$A, 0), MATCH($A12, 'Weekly 스피킹 raw'!$1:$1, 0)), ""), IF(val=0, "", val))} -> 59034.483 | Q12: {=LET(val, IFERROR(INDEX('Weekly 스피킹 raw'!$A:$AAQ, MATCH(TODAY() - WEEKDAY(TODAY(), 2) - 6, 'Weekly 스피킹 raw'!$A:$A, 0), MATCH($A12, 'Weekly 스피킹 raw'!$1:$1, 0)), ""), IF(val=0, "", val))} -> 76275.862 | R12: =LET(val, IFERROR((Q12 - P12) / P12, ""), IF(val=0, "", val)) -> 0.29205607 | S12: {=LET(val, IFERROR(INDEX('Monthly 스피킹 M raw'!$A:$AAQ, MATCH(EOMONTH(TODAY(), -2) + 1, 'Monthly 스피킹 M raw'!$A:$A, 0), MATCH($B12, 'Monthly 스피킹 M raw'!$1:$1, 0)), ""), IF(val=0, "", val))} -> 83102.41 | T12: {=LET(val, IFERROR(INDEX('Monthly 스피킹 raw'!$A:$AAQ, MATCH(EOMONTH(TODAY(), -1) + 1, 'Monthly 스피킹 raw'!$A:$A, 0), MATCH($B12, 'Monthly 스피킹 raw'!$1:$1, 0)), ""), IF(val=0, "", val))} -> 72833.333 | U12: =LET(val, IF(OR(S12="", T12=""), "", IFERROR((T12 - S12) / S12, "")), IF(val=0, "", val)) -> -0.12357134
A13: Revenue | B13: Revenue | C13: ㄴ Revenue | D13: {=LET(val, IFERROR(INDEX('Weekly 쨈 raw'!$A:$AAQ, MATCH(TODAY() - WEEKDAY(TODAY(), 2) - 13, 'Weekly 쨈 raw'!$A:$A, 0), MATCH($A13, 'Weekly 쨈 raw'!$1:$1, 0)), ""), IF(val=0, "", val))} -> 5923600 | E13: {=LET(val, IFERROR(INDEX('Weekly 쨈 raw'!$A:$AAQ, MATCH(TODAY() - WEEKDAY(TODAY(), 2) - 6, 'Weekly 쨈 raw'!$A:$A, 0), MATCH($A13, 'Weekly 쨈 raw'!$1:$1, 0)), ""), IF(val=0, "", val))} -> 8653000 | F13: =LET(val, IFERROR((E13 - D13) / D13, ""), IF(val=0, "", val)) -> 0.4607671 | G13: {=LET(val, IFERROR(INDEX('Monthly 쨈 M raw'!$A:$AAQ, MATCH(EOMONTH(TODAY(), -2) + 1, 'Monthly 쨈 M raw'!$A:$A, 0), MATCH($B13, 'Monthly 쨈 M raw'!$1:$1, 0)), 0), IF(val=0, "", val))} -> 11090200 | H13: {=LET(val, IFERROR(INDEX('Monthly 쨈 M raw'!$A:$AAQ, MATCH(EOMONTH(TODAY(), -1) + 1, 'Monthly 쨈 M raw'!$A:$A, 0), MATCH($B13, 'Monthly 쨈 M raw'!$1:$1, 0)), ""), IF(val=0, "", val))} -> 19118300 | I13: =LET(val, IF(OR(G13="", H13=""), "", IFERROR((H13 - G13) / G13, "")), IF(val=0, "", val)) -> 0.72389136 | J13: {=LET(val, IFERROR(INDEX('Weekly 사주 raw'!$A:$AAQ, MATCH(TODAY() - WEEKDAY(TODAY(), 2) - 13, 'Weekly 사주 raw'!$A:$A, 0), MATCH($A13, 'Weekly 사주 raw'!$1:$1, 0)), ""), IF(val=0, "", val))} -> 4444700 | K13: {=LET(val, IFERROR(INDEX('Weekly 사주 raw'!$A:$AAQ, MATCH(TODAY() - WEEKDAY(TODAY(), 2) - 6, 'Weekly 사주 raw'!$A:$A, 0), MATCH($A13, 'Weekly 사주 raw'!$1:$1, 0)), ""), IF(val=0, "", val))} -> 5224900 | L13: =LET(val, IFERROR((K13 - J13) / J13, ""), IF(val=0, "", val)) -> 0.17553491 | M13: {=LET(val, IFERROR(INDEX('Monthly 사주 M raw'!$A:$AAQ, MATCH(EOMONTH(TODAY(), -2) + 1, 'Monthly 사주 M raw'!$A:$A, 0), MATCH($B13, 'Monthly 사주 M raw'!$1:$1, 0)), ""), IF(val=0, "", val))} -> 20911600 | N13: {=LET(val, IFERROR(INDEX('Monthly 사주 M raw'!$A:$AAQ, MATCH(EOMONTH(TODAY(), -1) + 1, 'Monthly 사주 M raw'!$A:$A, 0), MATCH($B13, 'Monthly 사주 M raw'!$1:$1, 0)), ""), IF(val=0, "", val))} -> 17372800 | O13: =LET(val, IF(OR(M13="", N13=""), "", IFERROR((N13 - M13) / M13, "")), IF(val=0, "", val)) -> -0.16922665 | P13: {=LET(val, IFERROR(INDEX('Weekly 스피킹 raw'!$A:$AAQ, MATCH(TODAY() - WEEKDAY(TODAY(), 2) - 13, 'Weekly 스피킹 raw'!$A:$A, 0), MATCH($A13, 'Weekly 스피킹 raw'!$1:$1, 0)), ""), IF(val=0, "", val))} -> 1712000 | Q13: {=LET(val, IFERROR(INDEX('Weekly 스피킹 raw'!$A:$AAQ, MATCH(TODAY() - WEEKDAY(TODAY(), 2) - 6, 'Weekly 스피킹 raw'!$A:$A, 0), MATCH($A13, 'Weekly 스피킹 raw'!$1:$1, 0)), ""), IF(val=0, "", val))} -> 2212000 | R13: =LET(val, IFERROR((Q13 - P13) / P13, ""), IF(val=0, "", val)) -> 0.29205607 | S13: {=LET(val, IFERROR(INDEX('Monthly 스피킹 M raw'!$A:$AAQ, MATCH(EOMONTH(TODAY(), -2) + 1, 'Monthly 스피킹 M raw'!$A:$A, 0), MATCH($B13, 'Monthly 스피킹 M raw'!$1:$1, 0)), ""), IF(val=0, "", val))} -> 13795000 | T13: {=LET(val, IFERROR(INDEX('Monthly 스피킹 raw'!$A:$AAQ, MATCH(EOMONTH(TODAY(), -1) + 1, 'Monthly 스피킹 raw'!$A:$A, 0), MATCH($B13, 'Monthly 스피킹 raw'!$1:$1, 0)), ""), IF(val=0, "", val))} -> 8303000 | U13: =LET(val, IF(OR(S13="", T13=""), "", IFERROR((T13 - S13) / S13, "")), IF(val=0, "", val)) -> -0.39811526
A14: Purchase_Done_User_ARPPU | B14: Purchase_Done_User_ARPPU | C14: ㄴ Purchase Done User | D14: {=LET(val, IFERROR(INDEX('Weekly 쨈 raw'!$A:$AAQ, MATCH(TODAY() - WEEKDAY(TODAY(), 2) - 13, 'Weekly 쨈 raw'!$A:$A, 0), MATCH($A14, 'Weekly 쨈 raw'!$1:$1, 0)), ""), IF(val=0, "", val))} -> 326 | E14: {=LET(val, IFERROR(INDEX('Weekly 쨈 raw'!$A:$AAQ, MATCH(TODAY() - WEEKDAY(TODAY(), 2) - 6, 'Weekly 쨈 raw'!$A:$A, 0), MATCH($A14, 'Weekly 쨈 raw'!$1:$1, 0)), ""), IF(val=0, "", val))} -> 485 | F14: =LET(val, IFERROR((E14 - D14) / D14, ""), IF(val=0, "", val)) -> 0.48773006 | G14: {=LET(val, IFERROR(INDEX('Monthly 쨈 M raw'!$A:$AAQ, MATCH(EOMONTH(TODAY(), -2) + 1, 'Monthly 쨈 M raw'!$A:$A, 0), MATCH($B14, 'Monthly 쨈 M raw'!$1:$1, 0)), 0), IF(val=0, "", val))} -> 1303 | H14: {=LET(val, IFERROR(INDEX('Monthly 쨈 M raw'!$A:$AAQ, MATCH(EOMONTH(TODAY(), -1) + 1, 'Monthly 쨈 M raw'!$A:$A, 0), MATCH($B14, 'Monthly 쨈 M raw'!$1:$1, 0)), ""), IF(val=0, "", val))} -> 1060 | I14: =LET(val, IF(OR(G14="", H14=""), "", IFERROR((H14 - G14) / G14, "")), IF(val=0, "", val)) -> -0.18649271 | J14: {=LET(val, IFERROR(INDEX('Weekly 사주 raw'!$A:$AAQ, MATCH(TODAY() - WEEKDAY(TODAY(), 2) - 13, 'Weekly 사주 raw'!$A:$A, 0), MATCH($A14, 'Weekly 사주 raw'!$1:$1, 0)), ""), IF(val=0, "", val))} -> 185 | K14: {=LET(val, IFERROR(INDEX('Weekly 사주 raw'!$A:$AAQ, MATCH(TODAY() - WEEKDAY(TODAY(), 2) - 6, 'Weekly 사주 raw'!$A:$A, 0), MATCH($A14, 'Weekly 사주 raw'!$1:$1, 0)), ""), IF(val=0, "", val))} -> 214 | L14: =LET(val, IFERROR((K14 - J14) / J14, ""), IF(val=0, "", val)) -> 0.15675676 | M14: {=LET(val, IFERROR(INDEX('Monthly 사주 M raw'!$A:$AAQ, MATCH(EOMONTH(TODAY(), -2) + 1, 'Monthly 사주 M raw'!$A:$A, 0), MATCH($B14, 'Monthly 사주 M raw'!$1:$1, 0)), ""), IF(val=0, "", val))} -> 903 | N14: {=LET(val, IFERROR(INDEX('Monthly 사주 M raw'!$A:$AAQ, MATCH(EOMONTH(TODAY(), -1) + 1, 'Monthly 사주 M raw'!$A:$A, 0), MATCH($B14, 'Monthly 사주 M raw'!$1:$1, 0)), ""), IF(val=0, "", val))} -> 698 | O14: =LET(val, IF(OR(M14="", N14=""), "", IFERROR((N14 - M14) / M14, "")), IF(val=0, "", val)) -> -0.22702104 | P14: {=LET(val, IFERROR(INDEX('Weekly 스피킹 raw'!$A:$AAQ, MATCH(TODAY() - WEEKDAY(TODAY(), 2) - 13, 'Weekly 스피킹 raw'!$A:$A, 0), MATCH($A14, 'Weekly 스피킹 raw'!$1:$1, 0)), ""), IF(val=0, "", val))} -> 29 | Q14: {=LET(val, IFERROR(INDEX('Weekly 스피킹 raw'!$A:$AAQ, MATCH(TODAY() - WEEKDAY(TODAY(), 2) - 6, 'Weekly 스피킹 raw'!$A:$A, 0), MATCH($A14, 'Weekly 스피킹 raw'!$1:$1, 0)), ""), IF(val=0, "", val))} -> 29 | R14: =LET(val, IFERROR((Q14 - P14) / P14, ""), IF(val=0, "", val)) | S14: {=LET(val, IFERROR(INDEX('Monthly 스피킹 M raw'!$A:$AAQ, MATCH(EOMONTH(TODAY(), -2) + 1, 'Monthly 스피킹 M raw'!$A:$A, 0), MATCH($B14, 'Monthly 스피킹 M raw'!$1:$1, 0)), ""), IF(val=0, "", val))} -> 166 | T14: {=LET(val, IFERROR(INDEX('Monthly 스피킹 raw'!$A:$AAQ, MATCH(EOMONTH(TODAY(), -1) + 1, 'Monthly 스피킹 raw'!$A:$A, 0), MATCH($B14, 'Monthly 스피킹 raw'!$1:$1, 0)), ""), IF(val=0, "", val))} -> 114 | U14: =LET(val, IF(OR(S14="", T14=""), "", IFERROR((T14 - S14) / S14, "")), IF(val=0, "", val)) -> -0.31325301
A15: Purchase_Done_Count | B15: Purchase_Done_Count | C15: ㄴ Purchase Done Count | D15: {=LET(val, IFERROR(INDEX('Weekly 쨈 raw'!$A:$AAQ, MATCH(TODAY() - WEEKDAY(TODAY(), 2) - 13, 'Weekly 쨈 raw'!$A:$A, 0), MATCH($A15, 'Weekly 쨈 raw'!$1:$1, 0)), ""), IF(val=0, "", val))} -> 401 | E15: {=LET(val, IFERROR(INDEX('Weekly 쨈 raw'!$A:$AAQ, MATCH(TODAY() - WEEKDAY(TODAY(), 2) - 6, 'Weekly 쨈 raw'!$A:$A, 0), MATCH($A15, 'Weekly 쨈 raw'!$1:$1, 0)), ""), IF(val=0, "", val))} -> 621 | F15: =LET(val, IFERROR((E15 - D15) / D15, ""), IF(val=0, "", val)) -> 0.54862843 | G15: {=LET(val, IFERROR(INDEX('Monthly 쨈 M raw'!$A:$AAQ, MATCH(EOMONTH(TODAY(), -2) + 1, 'Monthly 쨈 M raw'!$A:$A, 0), MATCH($B15, 'Monthly 쨈 M raw'!$1:$1, 0)), 0), IF(val=0, "", val))} -> 1700 | H15: {=LET(val, IFERROR(INDEX('Monthly 쨈 M raw'!$A:$AAQ, MATCH(EOMONTH(TODAY(), -1) + 1, 'Monthly 쨈 M raw'!$A:$A, 0), MATCH($B15, 'Monthly 쨈 M raw'!$1:$1, 0)), ""), IF(val=0, "", val))} -> 1460 | I15: =LET(val, IF(OR(G15="", H15=""), "", IFERROR((H15 - G15) / G15, "")), IF(val=0, "", val)) -> -0.14117647 | J15: {=LET(val, IFERROR(INDEX('Weekly 사주 raw'!$A:$AAQ, MATCH(TODAY() - WEEKDAY(TODAY(), 2) - 13, 'Weekly 사주 raw'!$A:$A, 0), MATCH($A15, 'Weekly 사주 raw'!$1:$1, 0)), ""), IF(val=0, "", val))} -> 227 | K15: {=LET(val, IFERROR(INDEX('Weekly 사주 raw'!$A:$AAQ, MATCH(TODAY() - WEEKDAY(TODAY(), 2) - 6, 'Weekly 사주 raw'!$A:$A, 0), MATCH($A15, 'Weekly 사주 raw'!$1:$1, 0)), ""), IF(val=0, "", val))} -> 265 | L15: =LET(val, IFERROR((K15 - J15) / J15, ""), IF(val=0, "", val)) -> 0.16740088 | M15: {=LET(val, IFERROR(INDEX('Monthly 사주 M raw'!$A:$AAQ, MATCH(EOMONTH(TODAY(), -2) + 1, 'Monthly 사주 M raw'!$A:$A, 0), MATCH($B15, 'Monthly 사주 M raw'!$1:$1, 0)), ""), IF(val=0, "", val))} -> 1242 | N15: {=LET(val, IFERROR(INDEX('Monthly 사주 M raw'!$A:$AAQ, MATCH(EOMONTH(TODAY(), -1) + 1, 'Monthly 사주 M raw'!$A:$A, 0), MATCH($B15, 'Monthly 사주 M raw'!$1:$1, 0)), ""), IF(val=0, "", val))} -> 1028 | O15: =LET(val, IF(OR(M15="", N15=""), "", IFERROR((N15 - M15) / M15, "")), IF(val=0, "", val)) -> -0.17230274 | P15: {=LET(val, IFERROR(INDEX('Weekly 스피킹 raw'!$A:$AAQ, MATCH(TODAY() - WEEKDAY(TODAY(), 2) - 13, 'Weekly 스피킹 raw'!$A:$A, 0), MATCH($A15, 'Weekly 스피킹 raw'!$1:$1, 0)), ""), IF(val=0, "", val))} -> 29 | Q15: {=LET(val, IFERROR(INDEX('Weekly 스피킹 raw'!$A:$AAQ, MATCH(TODAY() - WEEKDAY(TODAY(), 2) - 6, 'Weekly 스피킹 raw'!$A:$A, 0), MATCH($A15, 'Weekly 스피킹 raw'!$1:$1, 0)), ""), IF(val=0, "", val))} -> 29 | R15: =LET(val, IFERROR((Q15 - P15) / P15, ""), IF(val=0, "", val)) | S15: {=LET(val, IFERROR(INDEX('Monthly 스피킹 M raw'!$A:$AAQ, MATCH(EOMONTH(TODAY(), -2) + 1, 'Monthly 스피킹 M raw'!$A:$A, 0), MATCH($B15, 'Monthly 스피킹 M raw'!$1:$1, 0)), ""), IF(val=0, "", val))} -> 167 | T15: {=LET(val, IFERROR(INDEX('Monthly 스피킹 raw'!$A:$AAQ, MATCH(EOMONTH(TODAY(), -1) + 1, 'Monthly 스피킹 raw'!$A:$A, 0), MATCH($B15, 'Monthly 스피킹 raw'!$1:$1, 0)), ""), IF(val=0, "", val))} -> 115 | U15: =LET(val, IF(OR(S15="", T15=""), "", IFERROR((T15 - S15) / S15, "")), IF(val=0, "", val)) -> -0.31137725
A17: Margin_Rate | B17: Margin_Rate | C17: 마진율 | D17: {=LET(val, IFERROR(INDEX('Weekly 쨈 raw'!$A:$AAQ, MATCH(TODAY() - WEEKDAY(TODAY(), 2) - 13, 'Weekly 쨈 raw'!$A:$A, 0), MATCH($A17, 'Weekly 쨈 raw'!$1:$1, 0)), ""), IF(val=0, "", val))} -> 0.31341969 | E17: {=LET(val, IFERROR(INDEX('Weekly 쨈 raw'!$A:$AAQ, MATCH(TODAY() - WEEKDAY(TODAY(), 2) - 6, 'Weekly 쨈 raw'!$A:$A, 0), MATCH($A17, 'Weekly 쨈 raw'!$1:$1, 0)), ""), IF(val=0, "", val))} -> 0.3147599 | F17: =LET(val, IFERROR((E17 - D17) / ABS(D17), ""), IF(val=0, "", val)) -> 0.0042760689 | G17: {=LET(val, IFERROR(INDEX('Monthly 쨈 M raw'!$A:$AAQ, MATCH(EOMONTH(TODAY(), -2) + 1, 'Monthly 쨈 M raw'!$A:$A, 0), MATCH($B17, 'Monthly 쨈 M raw'!$1:$1, 0)), 0), IF(val=0, "", val))} -> 0.11811167 | H17: {=LET(val, IFERROR(INDEX('Monthly 쨈 M raw'!$A:$AAQ, MATCH(EOMONTH(TODAY(), -1) + 1, 'Monthly 쨈 M raw'!$A:$A, 0), MATCH($B17, 'Monthly 쨈 M raw'!$1:$1, 0)), ""), IF(val=0, "", val))} -> 0.2965746 | I17: =LET(val, IF(OR(G17="", H17=""), "", IFERROR((H17 - G17) / ABS(G17), "")), IF(val=0, "", val)) -> 1.5109678 | J17: {=LET(val, IFERROR(INDEX('Weekly 사주 raw'!$A:$AAQ, MATCH(TODAY() - WEEKDAY(TODAY(), 2) - 13, 'Weekly 사주 raw'!$A:$A, 0), MATCH($A17, 'Weekly 사주 raw'!$1:$1, 0)), ""), IF(val=0, "", val))} -> 0.73759789 | K17: {=LET(val, IFERROR(INDEX('Weekly 사주 raw'!$A:$AAQ, MATCH(TODAY() - WEEKDAY(TODAY(), 2) - 6, 'Weekly 사주 raw'!$A:$A, 0), MATCH($A17, 'Weekly 사주 raw'!$1:$1, 0)), ""), IF(val=0, "", val))} -> 0.72691942 | L17: =LET(val, IF(OR(K17="", J17=""), "", IFERROR((K17 - J17) / ABS(J17), "")), IF(val=0, "", val)) -> -0.014477359 | M17: {=LET(val, IFERROR(INDEX('Monthly 사주 M raw'!$A:$AAQ, MATCH(EOMONTH(TODAY(), -2) + 1, 'Monthly 사주 M raw'!$A:$A, 0), MATCH($B17, 'Monthly 사주 M raw'!$1:$1, 0)), ""), IF(val=0, "", val))} -> 0.75190571 | N17: {=LET(val, IFERROR(INDEX('Monthly 사주 M raw'!$A:$AAQ, MATCH(EOMONTH(TODAY(), -1) + 1, 'Monthly 사주 M raw'!$A:$A, 0), MATCH($B17, 'Monthly 사주 M raw'!$1:$1, 0)), ""), IF(val=0, "", val))} -> 0.72349896 | O17: =LET(val, IF(OR(M17="", N17=""), "", IFERROR((N17 - M17) / ABS(M17), "")), IF(val=0, "", val)) -> -0.037779674 | P17: {=LET(val, IFERROR(INDEX('Weekly 스피킹'!$A:$AAQ, MATCH($A17, 'Weekly 스피킹'!$A:$A, 0), MATCH(TODAY() - WEEKDAY(TODAY(), 2) - 13, 'Weekly 스피킹'!$2:$2, 0)), ""), IF(val=0, "", val))} -> 0.31683995 | Q17: {=LET(val, IFERROR(INDEX('Weekly 스피킹'!$A:$AAQ, MATCH($A17, 'Weekly 스피킹'!$A:$A, 0), MATCH(TODAY() - WEEKDAY(TODAY(), 2) - 6, 'Weekly 스피킹'!$2:$2, 0)), ""), IF(val=0, "", val))} | R17: =LET(val, IF(OR(Q17="", P17=""), "", IFERROR((Q17 - P17) / ABS(P17), "")), IF(val=0, "", val)) | S17: =(S19 - S18) / S19 -> -0.012982011 | T17: =(T19 - T18) / T19 -> 0.50253884 | U17: =LET(val, IF(OR(T17="", S17=""), "", IFERROR((T17 - S17) / ABS(S17), "")), IF(val=0, "", val)) -> 39.710399
A18: Cost | B18: Cost | C18: ㄴ Cost | D18: {=LET(val, IFERROR(INDEX('Weekly 쨈 raw'!$A:$AAQ, MATCH(TODAY() - WEEKDAY(TODAY(), 2) - 13, 'Weekly 쨈 raw'!$A:$A, 0), MATCH($A18, 'Weekly 쨈 raw'!$1:$1, 0)), ""), IF(val=0, "", val))} -> 4067027.1 | E18: {=LET(val, IFERROR(INDEX('Weekly 쨈 raw'!$A:$AAQ, MATCH(TODAY() - WEEKDAY(TODAY(), 2) - 6, 'Weekly 쨈 raw'!$A:$A, 0), MATCH($A18, 'Weekly 쨈 raw'!$1:$1, 0)), ""), IF(val=0, "", val))} -> 5929382.6 | F18: =LET(val, IFERROR((E18 - D18) / D18, ""), IF(val=0, "", val)) -> 0.45791568 | G18: {=LET(val, IFERROR(INDEX('Monthly 쨈 M raw'!$A:$AAQ, MATCH(EOMONTH(TODAY(), -2) + 1, 'Monthly 쨈 M raw'!$A:$A, 0), MATCH($B18, 'Monthly 쨈 M raw'!$1:$1, 0)), ""), IF(val=0, "", val))} -> 9780318 | H18: {=LET(val, IFERROR(INDEX('Monthly 쨈 M raw'!$A:$AAQ, MATCH(EOMONTH(TODAY(), -1) + 1, 'Monthly 쨈 M raw'!$A:$A, 0), MATCH($B18, 'Monthly 쨈 M raw'!$1:$1, 0)), ""), IF(val=0, "", val))} -> 13448298 | I18: =LET(val, IF(OR(G18="", H18=""), "", IFERROR((H18 - G18) / G18, "")), IF(val=0, "", val)) -> 0.37503688 | J18: {=LET(val, IFERROR(INDEX('Weekly 사주 raw'!$A:$AAQ, MATCH(TODAY() - WEEKDAY(TODAY(), 2) - 13, 'Weekly 사주 raw'!$A:$A, 0), MATCH($A18, 'Weekly 사주 raw'!$1:$1, 0)), ""), IF(val=0, "", val))} -> 1166298.7 | K18: {=LET(val, IFERROR(INDEX('Weekly 사주 raw'!$A:$AAQ, MATCH(TODAY() - WEEKDAY(TODAY(), 2) - 6, 'Weekly 사주 raw'!$A:$A, 0), MATCH($A18, 'Weekly 사주 raw'!$1:$1, 0)), ""), IF(val=0, "", val))} -> 1426818.7 | L18: =LET(val, IFERROR((K18 - J18) / J18, ""), IF(val=0, "", val)) -> 0.22337337 | M18: {=LET(val, IFERROR(INDEX('Monthly 사주 M raw'!$A:$AAQ, MATCH(EOMONTH(TODAY(), -2) + 1, 'Monthly 사주 M raw'!$A:$A, 0), MATCH($B18, 'Monthly 사주 M raw'!$1:$1, 0)), ""), IF(val=0, "", val))} -> 5188048.5 | N18: {=LET(val, IFERROR(INDEX('Monthly 사주 M raw'!$A:$AAQ, MATCH(EOMONTH(TODAY(), -1) + 1, 'Monthly 사주 M raw'!$A:$A, 0), MATCH($B18, 'Monthly 사주 M raw'!$1:$1, 0)), ""), IF(val=0, "", val))} -> 4803597.3 | O18: =LET(val, IF(OR(M18="", N18=""), "", IFERROR((N18 - M18) / M18, "")), IF(val=0, "", val)) -> -0.074103247 | P18: {=LET(val, IFERROR(INDEX('Weekly 스피킹'!$A:$AAQ, MATCH($A18, 'Weekly 스피킹'!$A:$A, 0), MATCH(TODAY() - WEEKDAY(TODAY(), 2) - 13, 'Weekly 스피킹'!$2:$2, 0)), ""), IF(val=0, "", val))} -> 1169570 | Q18: {=LET(val, IFERROR(INDEX('Weekly 스피킹'!$A:$AAQ, MATCH($A18, 'Weekly 스피킹'!$A:$A, 0), MATCH(TODAY() - WEEKDAY(TODAY(), 2) - 6, 'Weekly 스피킹'!$2:$2, 0)), ""), IF(val=0, "", val))} | R18: =LET(val, IFERROR((Q18 - P18) / P18, ""), IF(val=0, "", val)) -> -1 | S18: {=SUM( INDEX('Daily 스피킹'!15:15, MATCH(EDATE(DATE(YEAR(TODAY()), MONTH(TODAY()), 1), -1), 'Daily 스피킹'!2:2, 0)) : INDEX('Daily 스피킹'!15:15, MATCH(EDATE(TODAY(), -1), 'Daily 스피킹'!2:2, 0)) )} -> 13974087 | T18: {=SUM( INDEX('Daily 스피킹'!15:15, MATCH(DATE(YEAR(TODAY()), MONTH(TODAY()), 1), 'Daily 스피킹'!2:2, 0)) : INDEX('Daily 스피킹'!15:15, MATCH(TODAY(), 'Daily 스피킹'!2:2, 0)) )} -> 4130420 | U18: =LET(val, IF(OR(S18="", T18=""), "", IFERROR((T18 - S18) / S18, "")), IF(val=0, "", val)) -> -0.7044229
A19: Revenue_ | B19: Revenue_ | C19: ㄴ Revenue | D19: {=LET(val, IFERROR(INDEX('Weekly 쨈 raw'!$A:$AAQ, MATCH(TODAY() - WEEKDAY(TODAY(), 2) - 13, 'Weekly 쨈 raw'!$A:$A, 0), MATCH($A19, 'Weekly 쨈 raw'!$1:$1, 0)), ""), IF(val=0, "", val))} -> 5923600 | E19: {=LET(val, IFERROR(INDEX('Weekly 쨈 raw'!$A:$AAQ, MATCH(TODAY() - WEEKDAY(TODAY(), 2) - 6, 'Weekly 쨈 raw'!$A:$A, 0), MATCH($A19, 'Weekly 쨈 raw'!$1:$1, 0)), ""), IF(val=0, "", val))} -> 8653000 | F19: =LET(val, IFERROR((E19 - D19) / D19, ""), IF(val=0, "", val)) -> 0.4607671 | G19: {=LET(val, IFERROR(INDEX('Monthly 쨈 M raw'!$A:$AAQ, MATCH(EOMONTH(TODAY(), -2) + 1, 'Monthly 쨈 M raw'!$A:$A, 0), MATCH($B19, 'Monthly 쨈 M raw'!$1:$1, 0)), 0), IF(val=0, "", val))} -> 11090200 | H19: {=LET(val, IFERROR(INDEX('Monthly 쨈 M raw'!$A:$AAQ, MATCH(EOMONTH(TODAY(), -1) + 1, 'Monthly 쨈 M raw'!$A:$A, 0), MATCH($B19, 'Monthly 쨈 M raw'!$1:$1, 0)), ""), IF(val=0, "", val))} -> 19118300 | I19: =LET(val, IF(OR(G19="", H19=""), "", IFERROR((H19 - G19) / G19, "")), IF(val=0, "", val)) -> 0.72389136 | J19: {=LET(val, IFERROR(INDEX('Weekly 사주 raw'!$A:$AAQ, MATCH(TODAY() - WEEKDAY(TODAY(), 2) - 13, 'Weekly 사주 raw'!$A:$A, 0), MATCH($A19, 'Weekly 사주 raw'!$1:$1, 0)), ""), IF(val=0, "", val))} -> 4444700 | K19: {=LET(val, IFERROR(INDEX('Weekly 사주 raw'!$A:$AAQ, MATCH(TODAY() - WEEKDAY(TODAY(), 2) - 6, 'Weekly 사주 raw'!$A:$A, 0), MATCH($A19, 'Weekly 사주 raw'!$1:$1, 0)), ""), IF(val=0, "", val))} -> 5224900 | L19: =LET(val, IFERROR((K19 - J19) / J19, ""), IF(val=0, "", val)) -> 0.17553491 | M19: {=LET(val, IFERROR(INDEX('Monthly 사주 M raw'!$A:$AAQ, MATCH(EOMONTH(TODAY(), -2) + 1, 'Monthly 사주 M raw'!$A:$A, 0), MATCH($B19, 'Monthly 사주 M raw'!$1:$1, 0)), ""), IF(val=0, "", val))} -> 20911600 | N19: {=LET(val, IFERROR(INDEX('Monthly 사주 M raw'!$A:$AAQ, MATCH(EOMONTH(TODAY(), -1) + 1, 'Monthly 사주 M raw'!$A:$A, 0), MATCH($B19, 'Monthly 사주 M raw'!$1:$1, 0)), ""), IF(val=0, "", val))} -> 17372800 | O19: =LET(val, IF(OR(M19="", N19=""), "", IFERROR((N19 - M19) / M19, "")), IF(val=0, "", val)) -> -0.16922665 | P19: {=LET(val, IFERROR(INDEX('Weekly 스피킹 raw'!$A:$AAQ, MATCH(TODAY() - WEEKDAY(TODAY(), 2) - 13, 'Weekly 스피킹 raw'!$A:$A, 0), MATCH($A19, 'Weekly 스피킹 raw'!$1:$1, 0)), ""), IF(val=0, "", val))} -> 1712000 | Q19: {=LET(val, IFERROR(INDEX('Weekly 스피킹 raw'!$A:$AAQ, MATCH(TODAY() - WEEKDAY(TODAY(), 2) - 6, 'Weekly 스피킹 raw'!$A:$A, 0), MATCH($A19, 'Weekly 스피킹 raw'!$1:$1, 0)), ""), IF(val=0, "", val))} -> 2212000 | R19: =LET(val, IFERROR((Q19 - P19) / P19, ""), IF(val=0, "", val)) -> 0.29205607 | S19: {=LET(val, IFERROR(INDEX('Monthly 스피킹 M raw'!$A:$AAQ, MATCH(EOMONTH(TODAY(), -2) + 1, 'Monthly 스피킹 M raw'!$A:$A, 0), MATCH($B19, 'Monthly 스피킹 M raw'!$1:$1, 0)), ""), IF(val=0, "", val))} -> 13795000 | T19: {=LET(val, IFERROR(INDEX('Monthly 스피킹 raw'!$A:$AAQ, MATCH(EOMONTH(TODAY(), -1) + 1, 'Monthly 스피킹 raw'!$A:$A, 0), MATCH($B19, 'Monthly 스피킹 raw'!$1:$1, 0)), ""), IF(val=0, "", val))} -> 8303000 | U19: =LET(val, IF(OR(S19="", T19=""), "", IFERROR((T19 - S19) / S19, "")), IF(val=0, "", val)) -> -0.39811526
C21: 퍼널 (신규) | D21: {=LET(val, IFERROR(INDEX('Weekly 쨈 raw'!$A:$AAQ, MATCH(TODAY() - WEEKDAY(TODAY(), 2) - 13, 'Weekly 쨈 raw'!$A:$A, 0), MATCH($A21, 'Weekly 쨈 raw'!$1:$1, 0)), ""), IF(val=0, "", val))} | E21: {=LET(val, IFERROR(INDEX('Weekly 쨈 raw'!$A:$AAQ, MATCH(TODAY() - WEEKDAY(TODAY(), 2) - 6, 'Weekly 쨈 raw'!$A:$A, 0), MATCH($A21, 'Weekly 쨈 raw'!$1:$1, 0)), ""), IF(val=0, "", val))} | F21: =LET(val, IFERROR((E21 - D21) / D21, ""), IF(val=0, "", val)) | G21: {=LET(val, IFERROR(INDEX('Monthly 쨈 M raw'!$A:$AAQ, MATCH(EOMONTH(TODAY(), -2) + 1, 'Monthly 쨈 M raw'!$A:$A, 0), MATCH($B21, 'Monthly 쨈 M raw'!$1:$1, 0)), 0), IF(val=0, "", val))} | H21: {=LET(val, IFERROR(INDEX('Monthly 쨈 M raw'!$A:$AAQ, MATCH(EOMONTH(TODAY(), -1) + 1, 'Monthly 쨈 M raw'!$A:$A, 0), MATCH($B21, 'Monthly 쨈 M raw'!$1:$1, 0)), ""), IF(val=0, "", val))} | I21: =LET(val, IF(OR(G21="", H21=""), "", IFERROR((H21 - G21) / G21, "")), IF(val=0, "", val)) | J21: {=LET(val, IFERROR(INDEX('Weekly 사주 raw'!$A:$AAQ, MATCH(TODAY() - WEEKDAY(TODAY(), 2) - 13, 'Weekly 사주 raw'!$A:$A, 0), MATCH($A21, 'Weekly 사주 raw'!$1:$1, 0)), ""), IF(val=0, "", val))} | K21: {=LET(val, IFERROR(INDEX('Weekly 사주 raw'!$A:$AAQ, MATCH(TODAY() - WEEKDAY(TODAY(), 2) - 6, 'Weekly 사주 raw'!$A:$A, 0), MATCH($A21, 'Weekly 사주 raw'!$1:$1, 0)), ""), IF(val=0, "", val))} | L21: =LET(val, IFERROR((K21 - J21) / J21, ""), IF(val=0, "", val)) | M21: {=LET(val, IFERROR(INDEX('Monthly 사주 raw'!$A:$AAQ, MATCH(EOMONTH(TODAY(), -2) + 1, 'Monthly 사주 raw'!$A:$A, 0), MATCH($B21, 'Monthly 사주 raw'!$1:$1, 0)), ""), IF(val=0, "", val))} | N21: {=LET(val, IFERROR(INDEX('Monthly 사주 M raw'!$A:$AAQ, MATCH(EOMONTH(TODAY(), -1) + 1, 'Monthly 사주 M raw'!$A:$A, 0), MATCH($B21, 'Monthly 사주 M raw'!$1:$1, 0)), ""), IF(val=0, "", val))} | O21: =LET(val, IF(OR(M21="", N21=""), "", IFERROR((N21 - M21) / M21, "")), IF(val=0, "", val)) | P21: {=LET(val, IFERROR(INDEX('Weekly 스피킹 raw'!$A:$AAQ, MATCH(TODAY() - WEEKDAY(TODAY(), 2) - 13, 'Weekly 스피킹 raw'!$A:$A, 0), MATCH($A21, 'Weekly 스피킹 raw'!$1:$1, 0)), ""), IF(val=0, "", val))} | Q21: {=LET(val, IFERROR(INDEX('Weekly 스피킹 raw'!$A:$AAQ, MATCH(TODAY() - WEEKDAY(TODAY(), 2) - 6, 'Weekly 스피킹 raw'!$A:$A, 0), MATCH($A21, 'Weekly 스피킹 raw'!$1:$1, 0)), ""), IF(val=0, "", val))} | R21: =LET(val, IFERROR((Q21 - P21) / P21, ""), IF(val=0, "", val)) | S21: {=LET(val, IFERROR(INDEX('Monthly 스피킹 M raw'!$A:$AAQ, MATCH(EOMONTH(TODAY(), -2) + 1, 'Monthly 스피킹 M raw'!$A:$A, 0), MATCH($B21, 'Monthly 스피킹 M raw'!$1:$1, 0)), ""), IF(val=0, "", val))} | T21: {=LET(val, IFERROR(INDEX('Monthly 스피킹 raw'!$A:$AAQ, MATCH(EOMONTH(TODAY(), -1) + 1, 'Monthly 스피킹 raw'!$A:$A, 0), MATCH($B21, 'Monthly 스피킹 raw'!$1:$1, 0)), ""), IF(val=0, "", val))} | U21: =LET(val, IF(OR(S21="", T21=""), "", IFERROR((T21 - S21) / S21, "")), IF(val=0, "", val))
A22: Install_User_New | B22: Install_User_New | C22: ㄴ Install User | D22: {=LET(val, IFERROR(INDEX('Weekly 쨈 raw'!$A:$AAQ, MATCH(TODAY() - WEEKDAY(TODAY(), 2) - 13, 'Weekly 쨈 raw'!$A:$A, 0), MATCH($A22, 'Weekly 쨈 raw'!$1:$1, 0)), ""), IF(val=0, "", val))} | E22: {=LET(val, IFERROR(INDEX('Weekly 쨈 raw'!$A:$AAQ, MATCH(TODAY() - WEEKDAY(TODAY(), 2) - 6, 'Weekly 쨈 raw'!$A:$A, 0), MATCH($A22, 'Weekly 쨈 raw'!$1:$1, 0)), ""), IF(val=0, "", val))} | F22: =LET(val, IFERROR((E22 - D22) / D22, ""), IF(val=0, "", val)) | G22: {=LET(val, IFERROR(INDEX('Monthly 쨈 M raw'!$A:$AAQ, MATCH(EOMONTH(TODAY(), -2) + 1, 'Monthly 쨈 M raw'!$A:$A, 0), MATCH($B22, 'Monthly 쨈 M raw'!$1:$1, 0)), 0), IF(val=0, "", val))} | H22: {=LET(val, IFERROR(INDEX('Monthly 쨈 M raw'!$A:$AAQ, MATCH(EOMONTH(TODAY(), -1) + 1, 'Monthly 쨈 M raw'!$A:$A, 0), MATCH($B22, 'Monthly 쨈 M raw'!$1:$1, 0)), ""), IF(val=0, "", val))} | I22: =LET(val, IF(OR(G22="", H22=""), "", IFERROR((H22 - G22) / G22, "")), IF(val=0, "", val)) | J22: {=LET(val, IFERROR(INDEX('Weekly 사주 raw'!$A:$AAQ, MATCH(TODAY() - WEEKDAY(TODAY(), 2) - 13, 'Weekly 사주 raw'!$A:$A, 0), MATCH($A22, 'Weekly 사주 raw'!$1:$1, 0)), ""), IF(val=0, "", val))} | K22: {=LET(val, IFERROR(INDEX('Weekly 사주 raw'!$A:$AAQ, MATCH(TODAY() - WEEKDAY(TODAY(), 2) - 6, 'Weekly 사주 raw'!$A:$A, 0), MATCH($A22, 'Weekly 사주 raw'!$1:$1, 0)), ""), IF(val=0, "", val))} | L22: =LET(val, IFERROR((K22 - J22) / J22, ""), IF(val=0, "", val)) | M22: {=LET(val, IFERROR(INDEX('Monthly 사주 raw'!$A:$AAQ, MATCH(EOMONTH(TODAY(), -2) + 1, 'Monthly 사주 raw'!$A:$A, 0), MATCH($B22, 'Monthly 사주 raw'!$1:$1, 0)), ""), IF(val=0, "", val))} | N22: {=LET(val, IFERROR(INDEX('Monthly 사주 M raw'!$A:$AAQ, MATCH(EOMONTH(TODAY(), -1) + 1, 'Monthly 사주 M raw'!$A:$A, 0), MATCH($B22, 'Monthly 사주 M raw'!$1:$1, 0)), ""), IF(val=0, "", val))} | O22: =LET(val, IF(OR(M22="", N22=""), "", IFERROR((N22 - M22) / M22, "")), IF(val=0, "", val)) | P22: {=LET(val, IFERROR(INDEX('Weekly 스피킹 raw'!$A:$AAQ, MATCH(TODAY() - WEEKDAY(TODAY(), 2) - 13, 'Weekly 스피킹 raw'!$A:$A, 0), MATCH($A22, 'Weekly 스피킹 raw'!$1:$1, 0)), ""), IF(val=0, "", val))} | Q22: {=LET(val, IFERROR(INDEX('Weekly 스피킹 raw'!$A:$AAQ, MATCH(TODAY() - WEEKDAY(TODAY(), 2) - 6, 'Weekly 스피킹 raw'!$A:$A, 0), MATCH($A22, 'Weekly 스피킹 raw'!$1:$1, 0)), ""), IF(val=0, "", val))} | R22: =LET(val, IFERROR((Q22 - P22) / P22, ""), IF(val=0, "", val)) | S22: {=LET(val, IFERROR(INDEX('Monthly 스피킹 M raw'!$A:$AAQ, MATCH(EOMONTH(TODAY(), -2) + 1, 'Monthly 스피킹 M raw'!$A:$A, 0), MATCH($B22, 'Monthly 스피킹 M raw'!$1:$1, 0)), ""), IF(val=0, "", val))} | T22: {=LET(val, IFERROR(INDEX('Monthly 스피킹 raw'!$A:$AAQ, MATCH(EOMONTH(TODAY(), -1) + 1, 'Monthly 스피킹 raw'!$A:$A, 0), MATCH($B22, 'Monthly 스피킹 raw'!$1:$1, 0)), ""), IF(val=0, "", val))} | U22: =LET(val, IF(OR(S22="", T22=""), "", IFERROR((T22 - S22) / S22, "")), IF(val=0, "", val))
A23: Sign_Up_User_New | B23: Sign_Up_User_New | C23: ㄴ Sign Up User | D23: {=LET(val, IFERROR(INDEX('Weekly 쨈 raw'!$A:$AAQ, MATCH(TODAY() - WEEKDAY(TODAY(), 2) - 13, 'Weekly 쨈 raw'!$A:$A, 0), MATCH($A23, 'Weekly 쨈 raw'!$1:$1, 0)), ""), IF(val=0, "", val))} | E23: {=LET(val, IFERROR(INDEX('Weekly 쨈 raw'!$A:$AAQ, MATCH(TODAY() - WEEKDAY(TODAY(), 2) - 6, 'Weekly 쨈 raw'!$A:$A, 0), MATCH($A23, 'Weekly 쨈 raw'!$1:$1, 0)), ""), IF(val=0, "", val))} | F23: =LET(val, IFERROR((E23 - D23) / D23, ""), IF(val=0, "", val)) | G23: {=LET(val, IFERROR(INDEX('Monthly 쨈 M raw'!$A:$AAQ, MATCH(EOMONTH(TODAY(), -2) + 1, 'Monthly 쨈 M raw'!$A:$A, 0), MATCH($B23, 'Monthly 쨈 M raw'!$1:$1, 0)), 0), IF(val=0, "", val))} | H23: {=LET(val, IFERROR(INDEX('Monthly 쨈 M raw'!$A:$AAQ, MATCH(EOMONTH(TODAY(), -1) + 1, 'Monthly 쨈 M raw'!$A:$A, 0), MATCH($B23, 'Monthly 쨈 M raw'!$1:$1, 0)), ""), IF(val=0, "", val))} | I23: =LET(val, IF(OR(G23="", H23=""), "", IFERROR((H23 - G23) / G23, "")), IF(val=0, "", val)) | J23: {=LET(val, IFERROR(INDEX('Weekly 사주 raw'!$A:$AAQ, MATCH(TODAY() - WEEKDAY(TODAY(), 2) - 13, 'Weekly 사주 raw'!$A:$A, 0), MATCH($A23, 'Weekly 사주 raw'!$1:$1, 0)), ""), IF(val=0, "", val))} | K23: {=LET(val, IFERROR(INDEX('Weekly 사주 raw'!$A:$AAQ, MATCH(TODAY() - WEEKDAY(TODAY(), 2) - 6, 'Weekly 사주 raw'!$A:$A, 0), MATCH($A23, 'Weekly 사주 raw'!$1:$1, 0)), ""), IF(val=0, "", val))} | L23: =LET(val, IFERROR((K23 - J23) / J23, ""), IF(val=0, "", val)) | M23: {=LET(val, IFERROR(INDEX('Monthly 사주 raw'!$A:$AAQ, MATCH(EOMONTH(TODAY(), -2) + 1, 'Monthly 사주 raw'!$A:$A, 0), MATCH($B23, 'Monthly 사주 raw'!$1:$1, 0)), ""), IF(val=0, "", val))} | N23: {=LET(val, IFERROR(INDEX('Monthly 사주 M raw'!$A:$AAQ, MATCH(EOMONTH(TODAY(), -1) + 1, 'Monthly 사주 M raw'!$A:$A, 0), MATCH($B23, 'Monthly 사주 M raw'!$1:$1, 0)), ""), IF(val=0, "", val))} | O23: =LET(val, IF(OR(M23="", N23=""), "", IFERROR((N23 - M23) / M23, "")), IF(val=0, "", val)) | P23: {=LET(val, IFERROR(INDEX('Weekly 스피킹 raw'!$A:$AAQ, MATCH(TODAY() - WEEKDAY(TODAY(), 2) - 13, 'Weekly 스피킹 raw'!$A:$A, 0), MATCH($A23, 'Weekly 스피킹 raw'!$1:$1, 0)), ""), IF(val=0, "", val))} | Q23: {=LET(val, IFERROR(INDEX('Weekly 스피킹 raw'!$A:$AAQ, MATCH(TODAY() - WEEKDAY(TODAY(), 2) - 6, 'Weekly 스피킹 raw'!$A:$A, 0), MATCH($A23, 'Weekly 스피킹 raw'!$1:$1, 0)), ""), IF(val=0, "", val))} | R23: =LET(val, IFERROR((Q23 - P23) / P23, ""), IF(val=0, "", val)) | S23: {=LET(val, IFERROR(INDEX('Monthly 스피킹 M raw'!$A:$AAQ, MATCH(EOMONTH(TODAY(), -2) + 1, 'Monthly 스피킹 M raw'!$A:$A, 0), MATCH($B23, 'Monthly 스피킹 M raw'!$1:$1, 0)), ""), IF(val=0, "", val))} | T23: {=LET(val, IFERROR(INDEX('Monthly 스피킹 raw'!$A:$AAQ, MATCH(EOMONTH(TODAY(), -1) + 1, 'Monthly 스피킹 raw'!$A:$A, 0), MATCH($B23, 'Monthly 스피킹 raw'!$1:$1, 0)), ""), IF(val=0, "", val))} | U23: =LET(val, IF(OR(S23="", T23=""), "", IFERROR((T23 - S23) / S23, "")), IF(val=0, "", val))
A24: Main_View_User_New | B24: Main_View_User_New | C24: ㄴ Main View User | D24: {=LET(val, IFERROR(INDEX('Weekly 쨈 raw'!$A:$AAQ, MATCH(TODAY() - WEEKDAY(TODAY(), 2) - 13, 'Weekly 쨈 raw'!$A:$A, 0), MATCH($A24, 'Weekly 쨈 raw'!$1:$1, 0)), ""), IF(val=0, "", val))} -> 4308 | E24: {=LET(val, IFERROR(INDEX('Weekly 쨈 raw'!$A:$AAQ, MATCH(TODAY() - WEEKDAY(TODAY(), 2) - 6, 'Weekly 쨈 raw'!$A:$A, 0), MATCH($A24, 'Weekly 쨈 raw'!$1:$1, 0)), ""), IF(val=0, "", val))} -> 4426 | F24: =LET(val, IFERROR((E24 - D24) / D24, ""), IF(val=0, "", val)) -> 0.027390901 | G24: {=LET(val, IFERROR(INDEX('Monthly 쨈 M raw'!$A:$AAQ, MATCH(EOMONTH(TODAY(), -2) + 1, 'Monthly 쨈 M raw'!$A:$A, 0), MATCH($B24, 'Monthly 쨈 M raw'!$1:$1, 0)), 0), IF(val=0, "", val))} -> 11015 | H24: {=LET(val, IFERROR(INDEX('Monthly 쨈 M raw'!$A:$AAQ, MATCH(EOMONTH(TODAY(), -1) + 1, 'Monthly 쨈 M raw'!$A:$A, 0), MATCH($B24, 'Monthly 쨈 M raw'!$1:$1, 0)), ""), IF(val=0, "", val))} -> 13278 | I24: =LET(val, IF(OR(G24="", H24=""), "", IFERROR((H24 - G24) / G24, "")), IF(val=0, "", val)) -> 0.20544712 | J24: {=LET(val, IFERROR(INDEX('Weekly 사주 raw'!$A:$AAQ, MATCH(TODAY() - WEEKDAY(TODAY(), 2) - 13, 'Weekly 사주 raw'!$A:$A, 0), MATCH($A24, 'Weekly 사주 raw'!$1:$1, 0)), ""), IF(val=0, "", val))} -> 3912 | K24: {=LET(val, IFERROR(INDEX('Weekly 사주 raw'!$A:$AAQ, MATCH(TODAY() - WEEKDAY(TODAY(), 2) - 6, 'Weekly 사주 raw'!$A:$A, 0), MATCH($A24, 'Weekly 사주 raw'!$1:$1, 0)), ""), IF(val=0, "", val))} -> 1845 | L24: =LET(val, IFERROR((K24 - J24) / J24, ""), IF(val=0, "", val)) -> -0.52837423 | M24: {=LET(val, IFERROR(INDEX('Monthly 사주 M raw'!$A:$AAQ, MATCH(EOMONTH(TODAY(), -2) + 1, 'Monthly 사주 M raw'!$A:$A, 0), MATCH($B24, 'Monthly 사주 M raw'!$1:$1, 0)), ""), IF(val=0, "", val))} -> 14126 | N24: {=LET(val, IFERROR(INDEX('Monthly 사주 M raw'!$A:$AAQ, MATCH(EOMONTH(TODAY(), -1) + 1, 'Monthly 사주 M raw'!$A:$A, 0), MATCH($B24, 'Monthly 사주 M raw'!$1:$1, 0)), ""), IF(val=0, "", val))} -> 13219 | O24: =LET(val, IF(OR(M24="", N24=""), "", IFERROR((N24 - M24) / M24, "")), IF(val=0, "", val)) -> -0.064207844 | P24: {=LET(val, IFERROR(INDEX('Weekly 스피킹 raw'!$A:$AAQ, MATCH(TODAY() - WEEKDAY(TODAY(), 2) - 13, 'Weekly 스피킹 raw'!$A:$A, 0), MATCH($A24, 'Weekly 스피킹 raw'!$1:$1, 0)), ""), IF(val=0, "", val))} -> 3452 | Q24: {=LET(val, IFERROR(INDEX('Weekly 스피킹 raw'!$A:$AAQ, MATCH(TODAY() - WEEKDAY(TODAY(), 2) - 6, 'Weekly 스피킹 raw'!$A:$A, 0), MATCH($A24, 'Weekly 스피킹 raw'!$1:$1, 0)), ""), IF(val=0, "", val))} -> 1453 | R24: =LET(val, IFERROR((Q24 - P24) / P24, ""), IF(val=0, "", val)) -> -0.57908459 | S24: {=LET(val, IFERROR(INDEX('Monthly 스피킹 M raw'!$A:$AAQ, MATCH(EOMONTH(TODAY(), -2) + 1, 'Monthly 스피킹 M raw'!$A:$A, 0), MATCH($B24, 'Monthly 스피킹 M raw'!$1:$1, 0)), ""), IF(val=0, "", val))} -> 10369 | T24: {=LET(val, IFERROR(INDEX('Monthly 스피킹 raw'!$A:$AAQ, MATCH(EOMONTH(TODAY(), -1) + 1, 'Monthly 스피킹 raw'!$A:$A, 0), MATCH($B24, 'Monthly 스피킹 raw'!$1:$1, 0)), ""), IF(val=0, "", val))} -> 10502 | U24: =LET(val, IF(OR(S24="", T24=""), "", IFERROR((T24 - S24) / S24, "")), IF(val=0, "", val)) -> 0.012826695
A25: Product_View_User_New | B25: Product_View_User_New | C25: ㄴ Product View User | D25: {=LET(val, IFERROR(INDEX('Weekly 쨈 raw'!$A:$AAQ, MATCH(TODAY() - WEEKDAY(TODAY(), 2) - 13, 'Weekly 쨈 raw'!$A:$A, 0), MATCH($A25, 'Weekly 쨈 raw'!$1:$1, 0)), ""), IF(val=0, "", val))} -> 2886 | E25: {=LET(val, IFERROR(INDEX('Weekly 쨈 raw'!$A:$AAQ, MATCH(TODAY() - WEEKDAY(TODAY(), 2) - 6, 'Weekly 쨈 raw'!$A:$A, 0), MATCH($A25, 'Weekly 쨈 raw'!$1:$1, 0)), ""), IF(val=0, "", val))} -> 3496 | F25: =LET(val, IFERROR((E25 - D25) / D25, ""), IF(val=0, "", val)) -> 0.21136521 | G25: {=LET(val, IFERROR(INDEX('Monthly 쨈 M raw'!$A:$AAQ, MATCH(EOMONTH(TODAY(), -2) + 1, 'Monthly 쨈 M raw'!$A:$A, 0), MATCH($B25, 'Monthly 쨈 M raw'!$1:$1, 0)), 0), IF(val=0, "", val))} -> 3611 | H25: {=LET(val, IFERROR(INDEX('Monthly 쨈 M raw'!$A:$AAQ, MATCH(EOMONTH(TODAY(), -1) + 1, 'Monthly 쨈 M raw'!$A:$A, 0), MATCH($B25, 'Monthly 쨈 M raw'!$1:$1, 0)), ""), IF(val=0, "", val))} -> 8504 | I25: =LET(val, IF(OR(G25="", H25=""), "", IFERROR((H25 - G25) / G25, "")), IF(val=0, "", val)) -> 1.3550263 | J25: {=LET(val, IFERROR(INDEX('Weekly 사주 raw'!$A:$AAQ, MATCH(TODAY() - WEEKDAY(TODAY(), 2) - 13, 'Weekly 사주 raw'!$A:$A, 0), MATCH($A25, 'Weekly 사주 raw'!$1:$1, 0)), ""), IF(val=0, "", val))} -> 1249 | K25: {=LET(val, IFERROR(INDEX('Weekly 사주 raw'!$A:$AAQ, MATCH(TODAY() - WEEKDAY(TODAY(), 2) - 6, 'Weekly 사주 raw'!$A:$A, 0), MATCH($A25, 'Weekly 사주 raw'!$1:$1, 0)), ""), IF(val=0, "", val))} -> 870 | L25: =LET(val, IFERROR((K25 - J25) / J25, ""), IF(val=0, "", val)) -> -0.30344275 | M25: {=LET(val, IFERROR(INDEX('Monthly 사주 M raw'!$A:$AAQ, MATCH(EOMONTH(TODAY(), -2) + 1, 'Monthly 사주 M raw'!$A:$A, 0), MATCH($B25, 'Monthly 사주 M raw'!$1:$1, 0)), ""), IF(val=0, "", val))} -> 7312 | N25: {=LET(val, IFERROR(INDEX('Monthly 사주 M raw'!$A:$AAQ, MATCH(EOMONTH(TODAY(), -1) + 1, 'Monthly 사주 M raw'!$A:$A, 0), MATCH($B25, 'Monthly 사주 M raw'!$1:$1, 0)), ""), IF(val=0, "", val))} -> 4487 | O25: =LET(val, IF(OR(M25="", N25=""), "", IFERROR((N25 - M25) / M25, "")), IF(val=0, "", val)) -> -0.3863512 | P25: {=LET(val, IFERROR(INDEX('Weekly 스피킹 raw'!$A:$AAQ, MATCH(TODAY() - WEEKDAY(TODAY(), 2) - 13, 'Weekly 스피킹 raw'!$A:$A, 0), MATCH($A25, 'Weekly 스피킹 raw'!$1:$1, 0)), ""), IF(val=0, "", val))} -> 925 | Q25: {=LET(val, IFERROR(INDEX('Weekly 스피킹 raw'!$A:$AAQ, MATCH(TODAY() - WEEKDAY(TODAY(), 2) - 6, 'Weekly 스피킹 raw'!$A:$A, 0), MATCH($A25, 'Weekly 스피킹 raw'!$1:$1, 0)), ""), IF(val=0, "", val))} -> 498 | R25: =LET(val, IFERROR((Q25 - P25) / P25, ""), IF(val=0, "", val)) -> -0.46162162 | S25: {=LET(val, IFERROR(INDEX('Monthly 스피킹 M raw'!$A:$AAQ, MATCH(EOMONTH(TODAY(), -2) + 1, 'Monthly 스피킹 M raw'!$A:$A, 0), MATCH($B25, 'Monthly 스피킹 M raw'!$1:$1, 0)), ""), IF(val=0, "", val))} -> 3789 | T25: {=LET(val, IFERROR(INDEX('Monthly 스피킹 raw'!$A:$AAQ, MATCH(EOMONTH(TODAY(), -1) + 1, 'Monthly 스피킹 raw'!$A:$A, 0), MATCH($B25, 'Monthly 스피킹 raw'!$1:$1, 0)), ""), IF(val=0, "", val))} -> 2975 | U25: =LET(val, IF(OR(S25="", T25=""), "", IFERROR((T25 - S25) / S25, "")), IF(val=0, "", val)) -> -0.21483241
A26: Gen_Done_User_New | B26: Gen_Done_User_New | C26: ㄴ Gen Done User | D26: {=LET(val, IFERROR(INDEX('Weekly 쨈 raw'!$A:$AAQ, MATCH(TODAY() - WEEKDAY(TODAY(), 2) - 13, 'Weekly 쨈 raw'!$A:$A, 0), MATCH($A26, 'Weekly 쨈 raw'!$1:$1, 0)), ""), IF(val=0, "", val))} -> 1587 | E26: {=LET(val, IFERROR(INDEX('Weekly 쨈 raw'!$A:$AAQ, MATCH(TODAY() - WEEKDAY(TODAY(), 2) - 6, 'Weekly 쨈 raw'!$A:$A, 0), MATCH($A26, 'Weekly 쨈 raw'!$1:$1, 0)), ""), IF(val=0, "", val))} -> 1566 | F26: =LET(val, IFERROR((E26 - D26) / D26, ""), IF(val=0, "", val)) -> -0.013232514 | G26: {=LET(val, IFERROR(INDEX('Monthly 쨈 M raw'!$A:$AAQ, MATCH(EOMONTH(TODAY(), -2) + 1, 'Monthly 쨈 M raw'!$A:$A, 0), MATCH($B26, 'Monthly 쨈 M raw'!$1:$1, 0)), 0), IF(val=0, "", val))} -> 618 | H26: {=LET(val, IFERROR(INDEX('Monthly 쨈 M raw'!$A:$AAQ, MATCH(EOMONTH(TODAY(), -1) + 1, 'Monthly 쨈 M raw'!$A:$A, 0), MATCH($B26, 'Monthly 쨈 M raw'!$1:$1, 0)), ""), IF(val=0, "", val))} -> 4011 | I26: =LET(val, IF(OR(G26="", H26=""), "", IFERROR((H26 - G26) / G26, "")), IF(val=0, "", val)) -> 5.4902913 | J26: {=LET(val, IFERROR(INDEX('Weekly 사주 raw'!$A:$AAQ, MATCH(TODAY() - WEEKDAY(TODAY(), 2) - 13, 'Weekly 사주 raw'!$A:$A, 0), MATCH($A26, 'Weekly 사주 raw'!$1:$1, 0)), ""), IF(val=0, "", val))} -> 207 | K26: {=LET(val, IFERROR(INDEX('Weekly 사주 raw'!$A:$AAQ, MATCH(TODAY() - WEEKDAY(TODAY(), 2) - 6, 'Weekly 사주 raw'!$A:$A, 0), MATCH($A26, 'Weekly 사주 raw'!$1:$1, 0)), ""), IF(val=0, "", val))} -> 150 | L26: =LET(val, IFERROR((K26 - J26) / J26, ""), IF(val=0, "", val)) -> -0.27536232 | M26: {=LET(val, IFERROR(INDEX('Monthly 사주 M raw'!$A:$AAQ, MATCH(EOMONTH(TODAY(), -2) + 1, 'Monthly 사주 M raw'!$A:$A, 0), MATCH($B26, 'Monthly 사주 M raw'!$1:$1, 0)), ""), IF(val=0, "", val))} -> 1196 | N26: {=LET(val, IFERROR(INDEX('Monthly 사주 M raw'!$A:$AAQ, MATCH(EOMONTH(TODAY(), -1) + 1, 'Monthly 사주 M raw'!$A:$A, 0), MATCH($B26, 'Monthly 사주 M raw'!$1:$1, 0)), ""), IF(val=0, "", val))} -> 825 | O26: =LET(val, IF(OR(M26="", N26=""), "", IFERROR((N26 - M26) / M26, "")), IF(val=0, "", val)) -> -0.31020067 | P26: {=LET(val, IFERROR(INDEX('Weekly 스피킹 raw'!$A:$AAQ, MATCH(TODAY() - WEEKDAY(TODAY(), 2) - 13, 'Weekly 스피킹 raw'!$A:$A, 0), MATCH($A26, 'Weekly 스피킹 raw'!$1:$1, 0)), ""), IF(val=0, "", val))} -> 874 | Q26: {=LET(val, IFERROR(INDEX('Weekly 스피킹 raw'!$A:$AAQ, MATCH(TODAY() - WEEKDAY(TODAY(), 2) - 6, 'Weekly 스피킹 raw'!$A:$A, 0), MATCH($A26, 'Weekly 스피킹 raw'!$1:$1, 0)), ""), IF(val=0, "", val))} -> 467 | R26: =LET(val, IFERROR((Q26 - P26) / P26, ""), IF(val=0, "", val)) -> -0.46567506 | S26: {=LET(val, IFERROR(INDEX('Monthly 스피킹 M raw'!$A:$AAQ, MATCH(EOMONTH(TODAY(), -2) + 1, 'Monthly 스피킹 M raw'!$A:$A, 0), MATCH($B26, 'Monthly 스피킹 M raw'!$1:$1, 0)), ""), IF(val=0, "", val))} -> 3614 | T26: {=LET(val, IFERROR(INDEX('Monthly 스피킹 raw'!$A:$AAQ, MATCH(EOMONTH(TODAY(), -1) + 1, 'Monthly 스피킹 raw'!$A:$A, 0), MATCH($B26, 'Monthly 스피킹 raw'!$1:$1, 0)), ""), IF(val=0, "", val))} -> 2847 | U26: =LET(val, IF(OR(S26="", T26=""), "", IFERROR((T26 - S26) / S26, "")), IF(val=0, "", val)) -> -0.21223022
A27: Paywall_View_User_New | B27: Paywall_View_User_New | C27: ㄴ Paywall View User | D27: {=LET(val, IFERROR(INDEX('Weekly 쨈 raw'!$A:$AAQ, MATCH(TODAY() - WEEKDAY(TODAY(), 2) - 13, 'Weekly 쨈 raw'!$A:$A, 0), MATCH($A27, 'Weekly 쨈 raw'!$1:$1, 0)), ""), IF(val=0, "", val))} -> 1602 | E27: {=LET(val, IFERROR(INDEX('Weekly 쨈 raw'!$A:$AAQ, MATCH(TODAY() - WEEKDAY(TODAY(), 2) - 6, 'Weekly 쨈 raw'!$A:$A, 0), MATCH($A27, 'Weekly 쨈 raw'!$1:$1, 0)), ""), IF(val=0, "", val))} -> 1947 | F27: =LET(val, IFERROR((E27 - D27) / D27, ""), IF(val=0, "", val)) -> 0.21535581 | G27: {=LET(val, IFERROR(INDEX('Monthly 쨈 M raw'!$A:$AAQ, MATCH(EOMONTH(TODAY(), -2) + 1, 'Monthly 쨈 M raw'!$A:$A, 0), MATCH($B27, 'Monthly 쨈 M raw'!$1:$1, 0)), 0), IF(val=0, "", val))} -> 902 | H27: {=LET(val, IFERROR(INDEX('Monthly 쨈 M raw'!$A:$AAQ, MATCH(EOMONTH(TODAY(), -1) + 1, 'Monthly 쨈 M raw'!$A:$A, 0), MATCH($B27, 'Monthly 쨈 M raw'!$1:$1, 0)), ""), IF(val=0, "", val))} -> 4475 | I27: =LET(val, IF(OR(G27="", H27=""), "", IFERROR((H27 - G27) / G27, "")), IF(val=0, "", val)) -> 3.9611973 | J27: {=LET(val, IFERROR(INDEX('Weekly 사주 raw'!$A:$AAQ, MATCH(TODAY() - WEEKDAY(TODAY(), 2) - 13, 'Weekly 사주 raw'!$A:$A, 0), MATCH($A27, 'Weekly 사주 raw'!$1:$1, 0)), ""), IF(val=0, "", val))} -> 756 | K27: {=LET(val, IFERROR(INDEX('Weekly 사주 raw'!$A:$AAQ, MATCH(TODAY() - WEEKDAY(TODAY(), 2) - 6, 'Weekly 사주 raw'!$A:$A, 0), MATCH($A27, 'Weekly 사주 raw'!$1:$1, 0)), ""), IF(val=0, "", val))} -> 385 | L27: =LET(val, IFERROR((K27 - J27) / J27, ""), IF(val=0, "", val)) -> -0.49074074 | M27: {=LET(val, IFERROR(INDEX('Monthly 사주 M raw'!$A:$AAQ, MATCH(EOMONTH(TODAY(), -2) + 1, 'Monthly 사주 M raw'!$A:$A, 0), MATCH($B27, 'Monthly 사주 M raw'!$1:$1, 0)), ""), IF(val=0, "", val))} -> 2517 | N27: {=LET(val, IFERROR(INDEX('Monthly 사주 M raw'!$A:$AAQ, MATCH(EOMONTH(TODAY(), -1) + 1, 'Monthly 사주 M raw'!$A:$A, 0), MATCH($B27, 'Monthly 사주 M raw'!$1:$1, 0)), ""), IF(val=0, "", val))} -> 2699 | O27: =LET(val, IF(OR(M27="", N27=""), "", IFERROR((N27 - M27) / M27, "")), IF(val=0, "", val)) -> 0.072308304 | P27: {=LET(val, IFERROR(INDEX('Weekly 스피킹 raw'!$A:$AAQ, MATCH(TODAY() - WEEKDAY(TODAY(), 2) - 13, 'Weekly 스피킹 raw'!$A:$A, 0), MATCH($A27, 'Weekly 스피킹 raw'!$1:$1, 0)), ""), IF(val=0, "", val))} -> 576 | Q27: {=LET(val, IFERROR(INDEX('Weekly 스피킹 raw'!$A:$AAQ, MATCH(TODAY() - WEEKDAY(TODAY(), 2) - 6, 'Weekly 스피킹 raw'!$A:$A, 0), MATCH($A27, 'Weekly 스피킹 raw'!$1:$1, 0)), ""), IF(val=0, "", val))} -> 347 | R27: =LET(val, IFERROR((Q27 - P27) / P27, ""), IF(val=0, "", val)) -> -0.39756944 | S27: {=LET(val, IFERROR(INDEX('Monthly 스피킹 M raw'!$A:$AAQ, MATCH(EOMONTH(TODAY(), -2) + 1, 'Monthly 스피킹 M raw'!$A:$A, 0), MATCH($B27, 'Monthly 스피킹 M raw'!$1:$1, 0)), ""), IF(val=0, "", val))} -> 2478 | T27: {=LET(val, IFERROR(INDEX('Monthly 스피킹 raw'!$A:$AAQ, MATCH(EOMONTH(TODAY(), -1) + 1, 'Monthly 스피킹 raw'!$A:$A, 0), MATCH($B27, 'Monthly 스피킹 raw'!$1:$1, 0)), ""), IF(val=0, "", val))} -> 1931 | U27: =LET(val, IF(OR(S27="", T27=""), "", IFERROR((T27 - S27) / S27, "")), IF(val=0, "", val)) -> -0.22074253
A28: Purchase_Done_User_New | B28: Purchase_Done_User_New | C28: ㄴ Purchase Done User | D28: {=LET(val, IFERROR(INDEX('Weekly 쨈 raw'!$A:$AAQ, MATCH(TODAY() - WEEKDAY(TODAY(), 2) - 13, 'Weekly 쨈 raw'!$A:$A, 0), MATCH($A28, 'Weekly 쨈 raw'!$1:$1, 0)), ""), IF(val=0, "", val))} -> 260 | E28: {=LET(val, IFERROR(INDEX('Weekly 쨈 raw'!$A:$AAQ, MATCH(TODAY() - WEEKDAY(TODAY(), 2) - 6, 'Weekly 쨈 raw'!$A:$A, 0), MATCH($A28, 'Weekly 쨈 raw'!$1:$1, 0)), ""), IF(val=0, "", val))} -> 371 | F28: =LET(val, IFERROR((E28 - D28) / D28, ""), IF(val=0, "", val)) -> 0.42692308 | G28: {=LET(val, IFERROR(INDEX('Monthly 쨈 M raw'!$A:$AAQ, MATCH(EOMONTH(TODAY(), -2) + 1, 'Monthly 쨈 M raw'!$A:$A, 0), MATCH($B28, 'Monthly 쨈 M raw'!$1:$1, 0)), 0), IF(val=0, "", val))} -> 141 | H28: {=LET(val, IFERROR(INDEX('Monthly 쨈 M raw'!$A:$AAQ, MATCH(EOMONTH(TODAY(), -1) + 1, 'Monthly 쨈 M raw'!$A:$A, 0), MATCH($B28, 'Monthly 쨈 M raw'!$1:$1, 0)), ""), IF(val=0, "", val))} -> 840 | I28: =LET(val, IF(OR(G28="", H28=""), "", IFERROR((H28 - G28) / G28, "")), IF(val=0, "", val)) -> 4.9574468 | J28: {=LET(val, IFERROR(INDEX('Weekly 사주 raw'!$A:$AAQ, MATCH(TODAY() - WEEKDAY(TODAY(), 2) - 13, 'Weekly 사주 raw'!$A:$A, 0), MATCH($A28, 'Weekly 사주 raw'!$1:$1, 0)), ""), IF(val=0, "", val))} -> 33 | K28: {=LET(val, IFERROR(INDEX('Weekly 사주 raw'!$A:$AAQ, MATCH(TODAY() - WEEKDAY(TODAY(), 2) - 6, 'Weekly 사주 raw'!$A:$A, 0), MATCH($A28, 'Weekly 사주 raw'!$1:$1, 0)), ""), IF(val=0, "", val))} -> 16 | L28: =LET(val, IFERROR((K28 - J28) / J28, ""), IF(val=0, "", val)) -> -0.51515152 | M28: {=LET(val, IFERROR(INDEX('Monthly 사주 M raw'!$A:$AAQ, MATCH(EOMONTH(TODAY(), -2) + 1, 'Monthly 사주 M raw'!$A:$A, 0), MATCH($B28, 'Monthly 사주 M raw'!$1:$1, 0)), ""), IF(val=0, "", val))} -> 168 | N28: {=LET(val, IFERROR(INDEX('Monthly 사주 M raw'!$A:$AAQ, MATCH(EOMONTH(TODAY(), -1) + 1, 'Monthly 사주 M raw'!$A:$A, 0), MATCH($B28, 'Monthly 사주 M raw'!$1:$1, 0)), ""), IF(val=0, "", val))} -> 159 | O28: =LET(val, IF(OR(M28="", N28=""), "", IFERROR((N28 - M28) / M28, "")), IF(val=0, "", val)) -> -0.053571429 | P28: {=LET(val, IFERROR(INDEX('Weekly 스피킹 raw'!$A:$AAQ, MATCH(TODAY() - WEEKDAY(TODAY(), 2) - 13, 'Weekly 스피킹 raw'!$A:$A, 0), MATCH($A28, 'Weekly 스피킹 raw'!$1:$1, 0)), ""), IF(val=0, "", val))} -> 3 | Q28: {=LET(val, IFERROR(INDEX('Weekly 스피킹 raw'!$A:$AAQ, MATCH(TODAY() - WEEKDAY(TODAY(), 2) - 6, 'Weekly 스피킹 raw'!$A:$A, 0), MATCH($A28, 'Weekly 스피킹 raw'!$1:$1, 0)), ""), IF(val=0, "", val))} -> 5 | R28: =LET(val, IFERROR((Q28 - P28) / P28, ""), IF(val=0, "", val)) -> 0.66666667 | S28: {=LET(val, IFERROR(INDEX('Monthly 스피킹 M raw'!$A:$AAQ, MATCH(EOMONTH(TODAY(), -2) + 1, 'Monthly 스피킹 M raw'!$A:$A, 0), MATCH($B28, 'Monthly 스피킹 M raw'!$1:$1, 0)), ""), IF(val=0, "", val))} -> 35 | T28: {=LET(val, IFERROR(INDEX('Monthly 스피킹 raw'!$A:$AAQ, MATCH(EOMONTH(TODAY(), -1) + 1, 'Monthly 스피킹 raw'!$A:$A, 0), MATCH($B28, 'Monthly 스피킹 raw'!$1:$1, 0)), ""), IF(val=0, "", val))} -> 20 | U28: =LET(val, IF(OR(S28="", T28=""), "", IFERROR((T28 - S28) / S28, "")), IF(val=0, "", val)) -> -0.42857143
C30: 퍼널 (기존) | D30: {=LET(val, IFERROR(INDEX('Weekly 쨈 raw'!$A:$AAQ, MATCH(TODAY() - WEEKDAY(TODAY(), 2) - 13, 'Weekly 쨈 raw'!$A:$A, 0), MATCH($A30, 'Weekly 쨈 raw'!$1:$1, 0)), ""), IF(val=0, "", val))} | E30: {=LET(val, IFERROR(INDEX('Weekly 쨈 raw'!$A:$AAQ, MATCH(TODAY() - WEEKDAY(TODAY(), 2) - 6, 'Weekly 쨈 raw'!$A:$A, 0), MATCH($A30, 'Weekly 쨈 raw'!$1:$1, 0)), ""), IF(val=0, "", val))} | F30: =LET(val, IFERROR((E30 - D30) / D30, ""), IF(val=0, "", val)) | G30: {=LET(val, IFERROR(INDEX('Monthly 쨈 M raw'!$A:$AAQ, MATCH(EOMONTH(TODAY(), -2) + 1, 'Monthly 쨈 M raw'!$A:$A, 0), MATCH($B30, 'Monthly 쨈 M raw'!$1:$1, 0)), 0), IF(val=0, "", val))} | H30: {=LET(val, IFERROR(INDEX('Monthly 쨈 M raw'!$A:$AAQ, MATCH(EOMONTH(TODAY(), -1) + 1, 'Monthly 쨈 M raw'!$A:$A, 0), MATCH($B30, 'Monthly 쨈 M raw'!$1:$1, 0)), ""), IF(val=0, "", val))} | I30: =LET(val, IF(OR(G30="", H30=""), "", IFERROR((H30 - G30) / G30, "")), IF(val=0, "", val)) | J30: {=LET(val, IFERROR(INDEX('Weekly 사주 raw'!$A:$AAQ, MATCH(TODAY() - WEEKDAY(TODAY(), 2) - 13, 'Weekly 사주 raw'!$A:$A, 0), MATCH($A30, 'Weekly 사주 raw'!$1:$1, 0)), ""), IF(val=0, "", val))} | K30: {=LET(val, IFERROR(INDEX('Weekly 사주 raw'!$A:$AAQ, MATCH(TODAY() - WEEKDAY(TODAY(), 2) - 6, 'Weekly 사주 raw'!$A:$A, 0), MATCH($A30, 'Weekly 사주 raw'!$1:$1, 0)), ""), IF(val=0, "", val))} | L30: =LET(val, IFERROR((K30 - J30) / J30, ""), IF(val=0, "", val)) | M30: {=LET(val, IFERROR(INDEX('Monthly 사주 M raw'!$A:$AAQ, MATCH(EOMONTH(TODAY(), -2) + 1, 'Monthly 사주 M raw'!$A:$A, 0), MATCH($B30, 'Monthly 사주 M raw'!$1:$1, 0)), ""), IF(val=0, "", val))} | N30: {=LET(val, IFERROR(INDEX('Monthly 사주 M raw'!$A:$AAQ, MATCH(EOMONTH(TODAY(), -1) + 1, 'Monthly 사주 M raw'!$A:$A, 0), MATCH($B30, 'Monthly 사주 M raw'!$1:$1, 0)), ""), IF(val=0, "", val))} | O30: =LET(val, IF(OR(M30="", N30=""), "", IFERROR((N30 - M30) / M30, "")), IF(val=0, "", val)) | P30: {=LET(val, IFERROR(INDEX('Weekly 스피킹 raw'!$A:$AAQ, MATCH(TODAY() - WEEKDAY(TODAY(), 2) - 13, 'Weekly 스피킹 raw'!$A:$A, 0), MATCH($A30, 'Weekly 스피킹 raw'!$1:$1, 0)), ""), IF(val=0, "", val))} | Q30: {=LET(val, IFERROR(INDEX('Weekly 스피킹 raw'!$A:$AAQ, MATCH(TODAY() - WEEKDAY(TODAY(), 2) - 6, 'Weekly 스피킹 raw'!$A:$A, 0), MATCH($A30, 'Weekly 스피킹 raw'!$1:$1, 0)), ""), IF(val=0, "", val))} | R30: =LET(val, IFERROR((Q30 - P30) / P30, ""), IF(val=0, "", val)) | S30: {=LET(val, IFERROR(INDEX('Monthly 스피킹 M raw'!$A:$AAQ, MATCH(EOMONTH(TODAY(), -2) + 1, 'Monthly 스피킹 M raw'!$A:$A, 0), MATCH($B30, 'Monthly 스피킹 M raw'!$1:$1, 0)), ""), IF(val=0, "", val))} | T30: {=LET(val, IFERROR(INDEX('Monthly 스피킹 raw'!$A:$AAQ, MATCH(EOMONTH(TODAY(), -1) + 1, 'Monthly 스피킹 raw'!$A:$A, 0), MATCH($B30, 'Monthly 스피킹 raw'!$1:$1, 0)), ""), IF(val=0, "", val))} | U30: =LET(val, IF(OR(S30="", T30=""), "", IFERROR((T30 - S30) / S30, "")), IF(val=0, "", val))
A31: Main_View_User_Normal | B31: Main_View_User_Normal | C31: ㄴ Main View User | D31: {=LET(val, IFERROR(INDEX('Weekly 쨈 raw'!$A:$AAQ, MATCH(TODAY() - WEEKDAY(TODAY(), 2) - 13, 'Weekly 쨈 raw'!$A:$A, 0), MATCH($A31, 'Weekly 쨈 raw'!$1:$1, 0)), ""), IF(val=0, "", val))} -> 955 | E31: {=LET(val, IFERROR(INDEX('Weekly 쨈 raw'!$A:$AAQ, MATCH(TODAY() - WEEKDAY(TODAY(), 2) - 6, 'Weekly 쨈 raw'!$A:$A, 0), MATCH($A31, 'Weekly 쨈 raw'!$1:$1, 0)), ""), IF(val=0, "", val))} -> 1754 | F31: =LET(val, IFERROR((E31 - D31) / D31, ""), IF(val=0, "", val)) -> 0.83664921 | G31: {=LET(val, IFERROR(INDEX('Monthly 쨈 M raw'!$A:$AAQ, MATCH(EOMONTH(TODAY(), -2) + 1, 'Monthly 쨈 M raw'!$A:$A, 0), MATCH($B31, 'Monthly 쨈 M raw'!$1:$1, 0)), 0), IF(val=0, "", val))} -> 74836 | H31: {=LET(val, IFERROR(INDEX('Monthly 쨈 M raw'!$A:$AAQ, MATCH(EOMONTH(TODAY(), -1) + 1, 'Monthly 쨈 M raw'!$A:$A, 0), MATCH($B31, 'Monthly 쨈 M raw'!$1:$1, 0)), ""), IF(val=0, "", val))} -> 12716 | I31: =LET(val, IF(OR(G31="", H31=""), "", IFERROR((H31 - G31) / G31, "")), IF(val=0, "", val)) -> -0.83008178 | J31: {=LET(val, IFERROR(INDEX('Weekly 사주 raw'!$A:$AAQ, MATCH(TODAY() - WEEKDAY(TODAY(), 2) - 13, 'Weekly 사주 raw'!$A:$A, 0), MATCH($A31, 'Weekly 사주 raw'!$1:$1, 0)), ""), IF(val=0, "", val))} -> 27238 | K31: {=LET(val, IFERROR(INDEX('Weekly 사주 raw'!$A:$AAQ, MATCH(TODAY() - WEEKDAY(TODAY(), 2) - 6, 'Weekly 사주 raw'!$A:$A, 0), MATCH($A31, 'Weekly 사주 raw'!$1:$1, 0)), ""), IF(val=0, "", val))} -> 29733 | L31: =LET(val, IFERROR((K31 - J31) / J31, ""), IF(val=0, "", val)) -> 0.091599971 | M31: {=LET(val, IFERROR(INDEX('Monthly 사주 M raw'!$A:$AAQ, MATCH(EOMONTH(TODAY(), -2) + 1, 'Monthly 사주 M raw'!$A:$A, 0), MATCH($B31, 'Monthly 사주 M raw'!$1:$1, 0)), ""), IF(val=0, "", val))} -> 74690 | N31: {=LET(val, IFERROR(INDEX('Monthly 사주 M raw'!$A:$AAQ, MATCH(EOMONTH(TODAY(), -1) + 1, 'Monthly 사주 M raw'!$A:$A, 0), MATCH($B31, 'Monthly 사주 M raw'!$1:$1, 0)), ""), IF(val=0, "", val))} -> 65321 | O31: =LET(val, IF(OR(M31="", N31=""), "", IFERROR((N31 - M31) / M31, "")), IF(val=0, "", val)) -> -0.12543848 | P31: {=LET(val, IFERROR(INDEX('Weekly 스피킹 raw'!$A:$AAQ, MATCH(TODAY() - WEEKDAY(TODAY(), 2) - 13, 'Weekly 스피킹 raw'!$A:$A, 0), MATCH($A31, 'Weekly 스피킹 raw'!$1:$1, 0)), ""), IF(val=0, "", val))} -> 16554 | Q31: {=LET(val, IFERROR(INDEX('Weekly 스피킹 raw'!$A:$AAQ, MATCH(TODAY() - WEEKDAY(TODAY(), 2) - 6, 'Weekly 스피킹 raw'!$A:$A, 0), MATCH($A31, 'Weekly 스피킹 raw'!$1:$1, 0)), ""), IF(val=0, "", val))} -> 14388 | R31: =LET(val, IFERROR((Q31 - P31) / P31, ""), IF(val=0, "", val)) -> -0.13084451 | S31: {=LET(val, IFERROR(INDEX('Monthly 스피킹 M raw'!$A:$AAQ, MATCH(EOMONTH(TODAY(), -2) + 1, 'Monthly 스피킹 M raw'!$A:$A, 0), MATCH($B31, 'Monthly 스피킹 M raw'!$1:$1, 0)), ""), IF(val=0, "", val))} -> 58277 | T31: {=LET(val, IFERROR(INDEX('Monthly 스피킹 raw'!$A:$AAQ, MATCH(EOMONTH(TODAY(), -1) + 1, 'Monthly 스피킹 raw'!$A:$A, 0), MATCH($B31, 'Monthly 스피킹 raw'!$1:$1, 0)), ""), IF(val=0, "", val))} -> 38069 | U31: =LET(val, IF(OR(S31="", T31=""), "", IFERROR((T31 - S31) / S31, "")), IF(val=0, "", val)) -> -0.34675773
A32: Product_View_User_Normal | B32: Product_View_User_Normal | C32: ㄴ Product View User | D32: {=LET(val, IFERROR(INDEX('Weekly 쨈 raw'!$A:$AAQ, MATCH(TODAY() - WEEKDAY(TODAY(), 2) - 13, 'Weekly 쨈 raw'!$A:$A, 0), MATCH($A32, 'Weekly 쨈 raw'!$1:$1, 0)), ""), IF(val=0, "", val))} -> 776 | E32: {=LET(val, IFERROR(INDEX('Weekly 쨈 raw'!$A:$AAQ, MATCH(TODAY() - WEEKDAY(TODAY(), 2) - 6, 'Weekly 쨈 raw'!$A:$A, 0), MATCH($A32, 'Weekly 쨈 raw'!$1:$1, 0)), ""), IF(val=0, "", val))} -> 1464 | F32: =LET(val, IFERROR((E32 - D32) / D32, ""), IF(val=0, "", val)) -> 0.88659794 | G32: {=LET(val, IFERROR(INDEX('Monthly 쨈 M raw'!$A:$AAQ, MATCH(EOMONTH(TODAY(), -2) + 1, 'Monthly 쨈 M raw'!$A:$A, 0), MATCH($B32, 'Monthly 쨈 M raw'!$1:$1, 0)), 0), IF(val=0, "", val))} -> 55609 | H32: {=LET(val, IFERROR(INDEX('Monthly 쨈 M raw'!$A:$AAQ, MATCH(EOMONTH(TODAY(), -1) + 1, 'Monthly 쨈 M raw'!$A:$A, 0), MATCH($B32, 'Monthly 쨈 M raw'!$1:$1, 0)), ""), IF(val=0, "", val))} -> 8325 | I32: =LET(val, IF(OR(G32="", H32=""), "", IFERROR((H32 - G32) / G32, "")), IF(val=0, "", val)) -> -0.85029402 | J32: {=LET(val, IFERROR(INDEX('Weekly 사주 raw'!$A:$AAQ, MATCH(TODAY() - WEEKDAY(TODAY(), 2) - 13, 'Weekly 사주 raw'!$A:$A, 0), MATCH($A32, 'Weekly 사주 raw'!$1:$1, 0)), ""), IF(val=0, "", val))} -> 12905 | K32: {=LET(val, IFERROR(INDEX('Weekly 사주 raw'!$A:$AAQ, MATCH(TODAY() - WEEKDAY(TODAY(), 2) - 6, 'Weekly 사주 raw'!$A:$A, 0), MATCH($A32, 'Weekly 사주 raw'!$1:$1, 0)), ""), IF(val=0, "", val))} -> 15165 | L32: =LET(val, IFERROR((K32 - J32) / J32, ""), IF(val=0, "", val)) -> 0.17512592 | M32: {=LET(val, IFERROR(INDEX('Monthly 사주 M raw'!$A:$AAQ, MATCH(EOMONTH(TODAY(), -2) + 1, 'Monthly 사주 M raw'!$A:$A, 0), MATCH($B32, 'Monthly 사주 M raw'!$1:$1, 0)), ""), IF(val=0, "", val))} -> 50079 | N32: {=LET(val, IFERROR(INDEX('Monthly 사주 M raw'!$A:$AAQ, MATCH(EOMONTH(TODAY(), -1) + 1, 'Monthly 사주 M raw'!$A:$A, 0), MATCH($B32, 'Monthly 사주 M raw'!$1:$1, 0)), ""), IF(val=0, "", val))} -> 32715 | O32: =LET(val, IF(OR(M32="", N32=""), "", IFERROR((N32 - M32) / M32, "")), IF(val=0, "", val)) -> -0.34673216 | P32: {=LET(val, IFERROR(INDEX('Weekly 스피킹 raw'!$A:$AAQ, MATCH(TODAY() - WEEKDAY(TODAY(), 2) - 13, 'Weekly 스피킹 raw'!$A:$A, 0), MATCH($A32, 'Weekly 스피킹 raw'!$1:$1, 0)), ""), IF(val=0, "", val))} -> 10851 | Q32: {=LET(val, IFERROR(INDEX('Weekly 스피킹 raw'!$A:$AAQ, MATCH(TODAY() - WEEKDAY(TODAY(), 2) - 6, 'Weekly 스피킹 raw'!$A:$A, 0), MATCH($A32, 'Weekly 스피킹 raw'!$1:$1, 0)), ""), IF(val=0, "", val))} -> 9921 | R32: =LET(val, IFERROR((Q32 - P32) / P32, ""), IF(val=0, "", val)) -> -0.085706387 | S32: {=LET(val, IFERROR(INDEX('Monthly 스피킹 M raw'!$A:$AAQ, MATCH(EOMONTH(TODAY(), -2) + 1, 'Monthly 스피킹 M raw'!$A:$A, 0), MATCH($B32, 'Monthly 스피킹 M raw'!$1:$1, 0)), ""), IF(val=0, "", val))} -> 31706 | T32: {=LET(val, IFERROR(INDEX('Monthly 스피킹 raw'!$A:$AAQ, MATCH(EOMONTH(TODAY(), -1) + 1, 'Monthly 스피킹 raw'!$A:$A, 0), MATCH($B32, 'Monthly 스피킹 raw'!$1:$1, 0)), ""), IF(val=0, "", val))} -> 22372 | U32: =LET(val, IF(OR(S32="", T32=""), "", IFERROR((T32 - S32) / S32, "")), IF(val=0, "", val)) -> -0.29439223
A33: Gen_Done_User_Normal | B33: Gen_Done_User_Normal | C33: ㄴ Gen Done User | D33: {=LET(val, IFERROR(INDEX('Weekly 쨈 raw'!$A:$AAQ, MATCH(TODAY() - WEEKDAY(TODAY(), 2) - 13, 'Weekly 쨈 raw'!$A:$A, 0), MATCH($A33, 'Weekly 쨈 raw'!$1:$1, 0)), ""), IF(val=0, "", val))} -> 455 | E33: {=LET(val, IFERROR(INDEX('Weekly 쨈 raw'!$A:$AAQ, MATCH(TODAY() - WEEKDAY(TODAY(), 2) - 6, 'Weekly 쨈 raw'!$A:$A, 0), MATCH($A33, 'Weekly 쨈 raw'!$1:$1, 0)), ""), IF(val=0, "", val))} -> 801 | F33: =LET(val, IFERROR((E33 - D33) / D33, ""), IF(val=0, "", val)) -> 0.76043956 | G33: {=LET(val, IFERROR(INDEX('Monthly 쨈 M raw'!$A:$AAQ, MATCH(EOMONTH(TODAY(), -2) + 1, 'Monthly 쨈 M raw'!$A:$A, 0), MATCH($B33, 'Monthly 쨈 M raw'!$1:$1, 0)), 0), IF(val=0, "", val))} -> 6987 | H33: {=LET(val, IFERROR(INDEX('Monthly 쨈 M raw'!$A:$AAQ, MATCH(EOMONTH(TODAY(), -1) + 1, 'Monthly 쨈 M raw'!$A:$A, 0), MATCH($B33, 'Monthly 쨈 M raw'!$1:$1, 0)), ""), IF(val=0, "", val))} -> 2289 | I33: =LET(val, IF(OR(G33="", H33=""), "", IFERROR((H33 - G33) / G33, "")), IF(val=0, "", val)) -> -0.67239158 | J33: {=LET(val, IFERROR(INDEX('Weekly 사주 raw'!$A:$AAQ, MATCH(TODAY() - WEEKDAY(TODAY(), 2) - 13, 'Weekly 사주 raw'!$A:$A, 0), MATCH($A33, 'Weekly 사주 raw'!$1:$1, 0)), ""), IF(val=0, "", val))} -> 1131 | K33: {=LET(val, IFERROR(INDEX('Weekly 사주 raw'!$A:$AAQ, MATCH(TODAY() - WEEKDAY(TODAY(), 2) - 6, 'Weekly 사주 raw'!$A:$A, 0), MATCH($A33, 'Weekly 사주 raw'!$1:$1, 0)), ""), IF(val=0, "", val))} -> 1133 | L33: =LET(val, IFERROR((K33 - J33) / J33, ""), IF(val=0, "", val)) -> 0.0017683466 | M33: {=LET(val, IFERROR(INDEX('Monthly 사주 M raw'!$A:$AAQ, MATCH(EOMONTH(TODAY(), -2) + 1, 'Monthly 사주 M raw'!$A:$A, 0), MATCH($B33, 'Monthly 사주 M raw'!$1:$1, 0)), ""), IF(val=0, "", val))} -> 6827 | N33: {=LET(val, IFERROR(INDEX('Monthly 사주 M raw'!$A:$AAQ, MATCH(EOMONTH(TODAY(), -1) + 1, 'Monthly 사주 M raw'!$A:$A, 0), MATCH($B33, 'Monthly 사주 M raw'!$1:$1, 0)), ""), IF(val=0, "", val))} -> 3566 | O33: =LET(val, IF(OR(M33="", N33=""), "", IFERROR((N33 - M33) / M33, "")), IF(val=0, "", val)) -> -0.47766222 | P33: {=LET(val, IFERROR(INDEX('Weekly 스피킹 raw'!$A:$AAQ, MATCH(TODAY() - WEEKDAY(TODAY(), 2) - 13, 'Weekly 스피킹 raw'!$A:$A, 0), MATCH($A33, 'Weekly 스피킹 raw'!$1:$1, 0)), ""), IF(val=0, "", val))} -> 10664 | Q33: {=LET(val, IFERROR(INDEX('Weekly 스피킹 raw'!$A:$AAQ, MATCH(TODAY() - WEEKDAY(TODAY(), 2) - 6, 'Weekly 스피킹 raw'!$A:$A, 0), MATCH($A33, 'Weekly 스피킹 raw'!$1:$1, 0)), ""), IF(val=0, "", val))} -> 9862 | R33: =LET(val, IFERROR((Q33 - P33) / P33, ""), IF(val=0, "", val)) -> -0.075206302 | S33: {=LET(val, IFERROR(INDEX('Monthly 스피킹 M raw'!$A:$AAQ, MATCH(EOMONTH(TODAY(), -2) + 1, 'Monthly 스피킹 M raw'!$A:$A, 0), MATCH($B33, 'Monthly 스피킹 M raw'!$1:$1, 0)), ""), IF(val=0, "", val))} -> 29332 | T33: {=LET(val, IFERROR(INDEX('Monthly 스피킹 raw'!$A:$AAQ, MATCH(EOMONTH(TODAY(), -1) + 1, 'Monthly 스피킹 raw'!$A:$A, 0), MATCH($B33, 'Monthly 스피킹 raw'!$1:$1, 0)), ""), IF(val=0, "", val))} -> 22838 | U33: =LET(val, IF(OR(S33="", T33=""), "", IFERROR((T33 - S33) / S33, "")), IF(val=0, "", val)) -> -0.22139643
A34: Paywall_View_User_Normal | B34: Paywall_View_User_Normal | C34: ㄴ Paywall View User | D34: {=LET(val, IFERROR(INDEX('Weekly 쨈 raw'!$A:$AAQ, MATCH(TODAY() - WEEKDAY(TODAY(), 2) - 13, 'Weekly 쨈 raw'!$A:$A, 0), MATCH($A34, 'Weekly 쨈 raw'!$1:$1, 0)), ""), IF(val=0, "", val))} -> 195 | E34: {=LET(val, IFERROR(INDEX('Weekly 쨈 raw'!$A:$AAQ, MATCH(TODAY() - WEEKDAY(TODAY(), 2) - 6, 'Weekly 쨈 raw'!$A:$A, 0), MATCH($A34, 'Weekly 쨈 raw'!$1:$1, 0)), ""), IF(val=0, "", val))} -> 382 | F34: =LET(val, IFERROR((E34 - D34) / D34, ""), IF(val=0, "", val)) -> 0.95897436 | G34: {=LET(val, IFERROR(INDEX('Monthly 쨈 M raw'!$A:$AAQ, MATCH(EOMONTH(TODAY(), -2) + 1, 'Monthly 쨈 M raw'!$A:$A, 0), MATCH($B34, 'Monthly 쨈 M raw'!$1:$1, 0)), 0), IF(val=0, "", val))} -> 9576 | H34: {=LET(val, IFERROR(INDEX('Monthly 쨈 M raw'!$A:$AAQ, MATCH(EOMONTH(TODAY(), -1) + 1, 'Monthly 쨈 M raw'!$A:$A, 0), MATCH($B34, 'Monthly 쨈 M raw'!$1:$1, 0)), ""), IF(val=0, "", val))} -> 1016 | I34: =LET(val, IF(OR(G34="", H34=""), "", IFERROR((H34 - G34) / G34, "")), IF(val=0, "", val)) -> -0.89390142 | J34: {=LET(val, IFERROR(INDEX('Weekly 사주 raw'!$A:$AAQ, MATCH(TODAY() - WEEKDAY(TODAY(), 2) - 13, 'Weekly 사주 raw'!$A:$A, 0), MATCH($A34, 'Weekly 사주 raw'!$1:$1, 0)), ""), IF(val=0, "", val))} -> 3036 | K34: {=LET(val, IFERROR(INDEX('Weekly 사주 raw'!$A:$AAQ, MATCH(TODAY() - WEEKDAY(TODAY(), 2) - 6, 'Weekly 사주 raw'!$A:$A, 0), MATCH($A34, 'Weekly 사주 raw'!$1:$1, 0)), ""), IF(val=0, "", val))} -> 3433 | L34: =LET(val, IFERROR((K34 - J34) / J34, ""), IF(val=0, "", val)) -> 0.13076416 | M34: {=LET(val, IFERROR(INDEX('Monthly 사주 M raw'!$A:$AAQ, MATCH(EOMONTH(TODAY(), -2) + 1, 'Monthly 사주 M raw'!$A:$A, 0), MATCH($B34, 'Monthly 사주 M raw'!$1:$1, 0)), ""), IF(val=0, "", val))} -> 12366 | N34: {=LET(val, IFERROR(INDEX('Monthly 사주 M raw'!$A:$AAQ, MATCH(EOMONTH(TODAY(), -1) + 1, 'Monthly 사주 M raw'!$A:$A, 0), MATCH($B34, 'Monthly 사주 M raw'!$1:$1, 0)), ""), IF(val=0, "", val))} -> 9761 | O34: =LET(val, IF(OR(M34="", N34=""), "", IFERROR((N34 - M34) / M34, "")), IF(val=0, "", val)) -> -0.21065826 | P34: {=LET(val, IFERROR(INDEX('Weekly 스피킹 raw'!$A:$AAQ, MATCH(TODAY() - WEEKDAY(TODAY(), 2) - 13, 'Weekly 스피킹 raw'!$A:$A, 0), MATCH($A34, 'Weekly 스피킹 raw'!$1:$1, 0)), ""), IF(val=0, "", val))} -> 3660 | Q34: {=LET(val, IFERROR(INDEX('Weekly 스피킹 raw'!$A:$AAQ, MATCH(TODAY() - WEEKDAY(TODAY(), 2) - 6, 'Weekly 스피킹 raw'!$A:$A, 0), MATCH($A34, 'Weekly 스피킹 raw'!$1:$1, 0)), ""), IF(val=0, "", val))} -> 3120 | R34: =LET(val, IFERROR((Q34 - P34) / P34, ""), IF(val=0, "", val)) -> -0.14754098 | S34: {=LET(val, IFERROR(INDEX('Monthly 스피킹 M raw'!$A:$AAQ, MATCH(EOMONTH(TODAY(), -2) + 1, 'Monthly 스피킹 M raw'!$A:$A, 0), MATCH($B34, 'Monthly 스피킹 M raw'!$1:$1, 0)), ""), IF(val=0, "", val))} -> 13575 | T34: {=LET(val, IFERROR(INDEX('Monthly 스피킹 raw'!$A:$AAQ, MATCH(EOMONTH(TODAY(), -1) + 1, 'Monthly 스피킹 raw'!$A:$A, 0), MATCH($B34, 'Monthly 스피킹 raw'!$1:$1, 0)), ""), IF(val=0, "", val))} -> 9514 | U34: =LET(val, IF(OR(S34="", T34=""), "", IFERROR((T34 - S34) / S34, "")), IF(val=0, "", val)) -> -0.29915285
A35: Purchase_Done_User_Normal | B35: Purchase_Done_User_Normal | C35: ㄴ Purchase Done User | D35: {=LET(val, IFERROR(INDEX('Weekly 쨈 raw'!$A:$AAQ, MATCH(TODAY() - WEEKDAY(TODAY(), 2) - 13, 'Weekly 쨈 raw'!$A:$A, 0), MATCH($A35, 'Weekly 쨈 raw'!$1:$1, 0)), ""), IF(val=0, "", val))} -> 66 | E35: {=LET(val, IFERROR(INDEX('Weekly 쨈 raw'!$A:$AAQ, MATCH(TODAY() - WEEKDAY(TODAY(), 2) - 6, 'Weekly 쨈 raw'!$A:$A, 0), MATCH($A35, 'Weekly 쨈 raw'!$1:$1, 0)), ""), IF(val=0, "", val))} -> 114 | F35: =LET(val, IFERROR((E35 - D35) / D35, ""), IF(val=0, "", val)) -> 0.72727273 | G35: {=LET(val, IFERROR(INDEX('Monthly 쨈 M raw'!$A:$AAQ, MATCH(EOMONTH(TODAY(), -2) + 1, 'Monthly 쨈 M raw'!$A:$A, 0), MATCH($B35, 'Monthly 쨈 M raw'!$1:$1, 0)), 0), IF(val=0, "", val))} -> 1162 | H35: {=LET(val, IFERROR(INDEX('Monthly 쨈 M raw'!$A:$AAQ, MATCH(EOMONTH(TODAY(), -1) + 1, 'Monthly 쨈 M raw'!$A:$A, 0), MATCH($B35, 'Monthly 쨈 M raw'!$1:$1, 0)), ""), IF(val=0, "", val))} -> 220 | I35: =LET(val, IF(OR(G35="", H35=""), "", IFERROR((H35 - G35) / G35, "")), IF(val=0, "", val)) -> -0.81067126 | J35: {=LET(val, IFERROR(INDEX('Weekly 사주 raw'!$A:$AAQ, MATCH(TODAY() - WEEKDAY(TODAY(), 2) - 13, 'Weekly 사주 raw'!$A:$A, 0), MATCH($A35, 'Weekly 사주 raw'!$1:$1, 0)), ""), IF(val=0, "", val))} -> 152 | K35: {=LET(val, IFERROR(INDEX('Weekly 사주 raw'!$A:$AAQ, MATCH(TODAY() - WEEKDAY(TODAY(), 2) - 6, 'Weekly 사주 raw'!$A:$A, 0), MATCH($A35, 'Weekly 사주 raw'!$1:$1, 0)), ""), IF(val=0, "", val))} -> 198 | L35: =LET(val, IFERROR((K35 - J35) / J35, ""), IF(val=0, "", val)) -> 0.30263158 | M35: {=LET(val, IFERROR(INDEX('Monthly 사주 M raw'!$A:$AAQ, MATCH(EOMONTH(TODAY(), -2) + 1, 'Monthly 사주 M raw'!$A:$A, 0), MATCH($B35, 'Monthly 사주 M raw'!$1:$1, 0)), ""), IF(val=0, "", val))} -> 735 | N35: {=LET(val, IFERROR(INDEX('Monthly 사주 M raw'!$A:$AAQ, MATCH(EOMONTH(TODAY(), -1) + 1, 'Monthly 사주 M raw'!$A:$A, 0), MATCH($B35, 'Monthly 사주 M raw'!$1:$1, 0)), ""), IF(val=0, "", val))} -> 539 | O35: =LET(val, IF(OR(M35="", N35=""), "", IFERROR((N35 - M35) / M35, "")), IF(val=0, "", val)) -> -0.26666667 | P35: {=LET(val, IFERROR(INDEX('Weekly 스피킹 raw'!$A:$AAQ, MATCH(TODAY() - WEEKDAY(TODAY(), 2) - 13, 'Weekly 스피킹 raw'!$A:$A, 0), MATCH($A35, 'Weekly 스피킹 raw'!$1:$1, 0)), ""), IF(val=0, "", val))} -> 26 | Q35: {=LET(val, IFERROR(INDEX('Weekly 스피킹 raw'!$A:$AAQ, MATCH(TODAY() - WEEKDAY(TODAY(), 2) - 6, 'Weekly 스피킹 raw'!$A:$A, 0), MATCH($A35, 'Weekly 스피킹 raw'!$1:$1, 0)), ""), IF(val=0, "", val))} -> 24 | R35: =LET(val, IFERROR((Q35 - P35) / P35, ""), IF(val=0, "", val)) -> -0.076923077 | S35: {=LET(val, IFERROR(INDEX('Monthly 스피킹 M raw'!$A:$AAQ, MATCH(EOMONTH(TODAY(), -2) + 1, 'Monthly 스피킹 M raw'!$A:$A, 0), MATCH($B35, 'Monthly 스피킹 M raw'!$1:$1, 0)), ""), IF(val=0, "", val))} -> 131 | T35: {=LET(val, IFERROR(INDEX('Monthly 스피킹 raw'!$A:$AAQ, MATCH(EOMONTH(TODAY(), -1) + 1, 'Monthly 스피킹 raw'!$A:$A, 0), MATCH($B35, 'Monthly 스피킹 raw'!$1:$1, 0)), ""), IF(val=0, "", val))} -> 94 | U35: =LET(val, IF(OR(S35="", T35=""), "", IFERROR((T35 - S35) / S35, "")), IF(val=0, "", val)) -> -0.28244275

Sheet Daily ZZEM
AG1: 밈 플친 발송 | BN1: ZZEM 출시 | BR1: 가격 개편(밈) | BW1: 커스텀 프롬프트 출시 퍼널 수치 쨈으로 교체 | BX1: 마케팅 ON | CB1: 뤼튼 밈 종료
B2: Metric | C2: =text(C3, "ddd") -> 월 | D2: =text(D3, "ddd") -> 화 | E2: =text(E3, "ddd") -> 수 | F2: =text(F3, "ddd") -> 목 | G2: =text(G3, "ddd") -> 금 | H2: =text(H3, "ddd") -> 토 | I2: =text(I3, "ddd") -> 일 | J2: =text(J3, "ddd") -> 월 | ... DZ2: =text(DZ3, "ddd") -> 화
A3: sql과 맞는 Metric | C3: 45985 | D3: 45986 | E3: 45987 | F3: 45988 | G3: 45989 | H3: 45990 | I3: 45991 | J3: 45992 | K3: 45993 | L3: 45994 | M3: 45995 | N3: 45996 | O3: 45997 | P3: 45998 | Q3: 45999 | R3: 46000 | S3: 46001 | T3: 46002 | U3: 46003 | V3: 46004 | W3: 46005 | X3: 46006 | Y3: 46007 | Z3: 46008 | AA3: 46009 | AB3: 46010 | AC3: 46011 | AD3: 46012 | AE3: 46013 | AF3: 46014 | AG3: 46015 | AH3: 46016 | AI3: 46017 | AJ3: 46018 | AK3: 46019 | AL3: 46020 | AM3: 46021 | AN3: 46022 | AO3: 46023 | AP3: =AO3+1 -> 46024 | AQ3: =AP3+1 -> 46025 | AR3: =AQ3+1 -> 46026 | AS3: =AR3+1 -> 46027 | AT3: =AS3+1 -> 46028 | AU3: =AT3+1 -> 46029 | AV3: =AU3+1 -> 46030 | AW3: =AV3+1 -> 46031 | ... DZ3: =DY3+1 -> 46112
A4: Paid_Cohort_Retention | B4: Paid Cohort Retention | C4: {=LET(val, IFERROR(INDEX('Daily 쨈 raw'!$A:$Z, MATCH(C$3, 'Daily 쨈 raw'!$A:$A, 0), MATCH($A4, 'Daily 쨈 raw'!$1:$1, 0)), ""), IF(val=0, "", val))} -> 0.59375 | D4: {=LET(val, IFERROR(INDEX('Daily 쨈 raw'!$A:$Z, MATCH(D$3, 'Daily 쨈 raw'!$A:$A, 0), MATCH($A4, 'Daily 쨈 raw'!$1:$1, 0)), ""), IF(val=0, "", val))} -> 0.79220779 | E4: {=LET(val, IFERROR(INDEX('Daily 쨈 raw'!$A:$Z, MATCH(E$3, 'Daily 쨈 raw'!$A:$A, 0), MATCH($A4, 'Daily 쨈 raw'!$1:$1, 0)), ""), IF(val=0, "", val))} -> 0.56603774 | F4: {=LET(val, IFERROR(INDEX('Daily 쨈 raw'!$A:$Z, MATCH(F$3, 'Daily 쨈 raw'!$A:$A, 0), MATCH($A4, 'Daily 쨈 raw'!$1:$1, 0)), ""), IF(val=0, "", val))} -> 0.53846154 | G4: {=LET(val, IFERROR(INDEX('Daily 쨈 raw'!$A:$Z, MATCH(G$3, 'Daily 쨈 raw'!$A:$A, 0), MATCH($A4, 'Daily 쨈 raw'!$1:$1, 0)), ""), IF(val=0, "", val))} -> 0.48571429 | H4: {=LET(val, IFERROR(INDEX('Daily 쨈 raw'!$A:$Z, MATCH(H$3, 'Daily 쨈 raw'!$A:$A, 0), MATCH($A4, 'Daily 쨈 raw'!$1:$1, 0)), ""), IF(val=0, "", val))} -> 0.59036145 | I4: {=LET(val, IFERROR(INDEX('Daily 쨈 raw'!$A:$Z, MATCH(I$3, 'Daily 쨈 raw'!$A:$A, 0), MATCH($A4, 'Daily 쨈 raw'!$1:$1, 0)), ""), IF(val=0, "", val))} -> 0.546875 | J4: {=LET(val, IFERROR(INDEX('Daily 쨈 raw'!$A:$Z, MATCH(J$3, 'Daily 쨈 raw'!$A:$A, 0), MATCH($A4, 'Daily 쨈 raw'!$1:$1, 0)), ""), IF(val=0, "", val))} -> 0.52083333 | ... DZ4: {=LET(val, IFERROR(INDEX('Daily 쨈 raw'!$A:$Z, MATCH(DZ$3, 'Daily 쨈 raw'!$A:$A, 0), MATCH($A4, 'Daily 쨈 raw'!$1:$1, 0)), ""), IF(val=0, "", val))}
A5: D1_Any_Event_User | B5: D1 Any Event User | C5: {=LET(val, IFERROR(INDEX('Daily 쨈 raw'!$A:$Z, MATCH(C$3, 'Daily 쨈 raw'!$A:$A, 0), MATCH($A5, 'Daily 쨈 raw'!$1:$1, 0)), ""), IF(val=0, "", val))} -> 38 | D5: {=LET(val, IFERROR(INDEX('Daily 쨈 raw'!$A:$Z, MATCH(D$3, 'Daily 쨈 raw'!$A:$A, 0), MATCH($A5, 'Daily 쨈 raw'!$1:$1, 0)), ""), IF(val=0, "", val))} -> 61 | E5: {=LET(val, IFERROR(INDEX('Daily 쨈 raw'!$A:$Z, MATCH(E$3, 'Daily 쨈 raw'!$A:$A, 0), MATCH($A5, 'Daily 쨈 raw'!$1:$1, 0)), ""), IF(val=0, "", val))} -> 30 | F5: {=LET(val, IFERROR(INDEX('Daily 쨈 raw'!$A:$Z, MATCH(F$3, 'Daily 쨈 raw'!$A:$A, 0), MATCH($A5, 'Daily 쨈 raw'!$1:$1, 0)), ""), IF(val=0, "", val))} -> 21 | G5: {=LET(val, IFERROR(INDEX('Daily 쨈 raw'!$A:$Z, MATCH(G$3, 'Daily 쨈 raw'!$A:$A, 0), MATCH($A5, 'Daily 쨈 raw'!$1:$1, 0)), ""), IF(val=0, "", val))} -> 17 | H5: {=LET(val, IFERROR(INDEX('Daily 쨈 raw'!$A:$Z, MATCH(H$3, 'Daily 쨈 raw'!$A:$A, 0), MATCH($A5, 'Daily 쨈 raw'!$1:$1, 0)), ""), IF(val=0, "", val))} -> 49 | I5: {=LET(val, IFERROR(INDEX('Daily 쨈 raw'!$A:$Z, MATCH(I$3, 'Daily 쨈 raw'!$A:$A, 0), MATCH($A5, 'Daily 쨈 raw'!$1:$1, 0)), ""), IF(val=0, "", val))} -> 35 | J5: {=LET(val, IFERROR(INDEX('Daily 쨈 raw'!$A:$Z, MATCH(J$3, 'Daily 쨈 raw'!$A:$A, 0), MATCH($A5, 'Daily 쨈 raw'!$1:$1, 0)), ""), IF(val=0, "", val))} -> 25 | ... DZ5: {=LET(val, IFERROR(INDEX('Daily 쨈 raw'!$A:$Z, MATCH(DZ$3, 'Daily 쨈 raw'!$A:$A, 0), MATCH($A5, 'Daily 쨈 raw'!$1:$1, 0)), ""), IF(val=0, "", val))}
A6: D0_Purchase_Done_User | B6: D0 Purchase Done User | C6: {=LET(val, IFERROR(INDEX('Daily 쨈 raw'!$A:$Z, MATCH(C$3, 'Daily 쨈 raw'!$A:$A, 0), MATCH($A6, 'Daily 쨈 raw'!$1:$1, 0)), ""), IF(val=0, "", val))} -> 64 | D6: {=LET(val, IFERROR(INDEX('Daily 쨈 raw'!$A:$Z, MATCH(D$3, 'Daily 쨈 raw'!$A:$A, 0), MATCH($A6, 'Daily 쨈 raw'!$1:$1, 0)), ""), IF(val=0, "", val))} -> 77 | E6: {=LET(val, IFERROR(INDEX('Daily 쨈 raw'!$A:$Z, MATCH(E$3, 'Daily 쨈 raw'!$A:$A, 0), MATCH($A6, 'Daily 쨈 raw'!$1:$1, 0)), ""), IF(val=0, "", val))} -> 53 | F6: {=LET(val, IFERROR(INDEX('Daily 쨈 raw'!$A:$Z, MATCH(F$3, 'Daily 쨈 raw'!$A:$A, 0), MATCH($A6, 'Daily 쨈 raw'!$1:$1, 0)), ""), IF(val=0, "", val))} -> 39 | G6: {=LET(val, IFERROR(INDEX('Daily 쨈 raw'!$A:$Z, MATCH(G$3, 'Daily 쨈 raw'!$A:$A, 0), MATCH($A6, 'Daily 쨈 raw'!$1:$1, 0)), ""), IF(val=0, "", val))} -> 35 | H6: {=LET(val, IFERROR(INDEX('Daily 쨈 raw'!$A:$Z, MATCH(H$3, 'Daily 쨈 raw'!$A:$A, 0), MATCH($A6, 'Daily 쨈 raw'!$1:$1, 0)), ""), IF(val=0, "", val))} -> 83 | I6: {=LET(val, IFERROR(INDEX('Daily 쨈 raw'!$A:$Z, MATCH(I$3, 'Daily 쨈 raw'!$A:$A, 0), MATCH($A6, 'Daily 쨈 raw'!$1:$1, 0)), ""), IF(val=0, "", val))} -> 64 | J6: {=LET(val, IFERROR(INDEX('Daily 쨈 raw'!$A:$Z, MATCH(J$3, 'Daily 쨈 raw'!$A:$A, 0), MATCH($A6, 'Daily 쨈 raw'!$1:$1, 0)), ""), IF(val=0, "", val))} -> 48 | ... DZ6: {=LET(val, IFERROR(INDEX('Daily 쨈 raw'!$A:$Z, MATCH(DZ$3, 'Daily 쨈 raw'!$A:$A, 0), MATCH($A6, 'Daily 쨈 raw'!$1:$1, 0)), ""), IF(val=0, "", val))}
A7: CVR | B7: CVR | C7: {=LET(val, IFERROR(INDEX('Daily 쨈 raw'!$A:$Z, MATCH(C$3, 'Daily 쨈 raw'!$A:$A, 0), MATCH($A7, 'Daily 쨈 raw'!$1:$1, 0)), ""), IF(val=0, "", val))} -> 0.019494365 | D7: {=LET(val, IFERROR(INDEX('Daily 쨈 raw'!$A:$Z, MATCH(D$3, 'Daily 쨈 raw'!$A:$A, 0), MATCH($A7, 'Daily 쨈 raw'!$1:$1, 0)), ""), IF(val=0, "", val))} -> 0.024188791 | E7: {=LET(val, IFERROR(INDEX('Daily 쨈 raw'!$A:$Z, MATCH(E$3, 'Daily 쨈 raw'!$A:$A, 0), MATCH($A7, 'Daily 쨈 raw'!$1:$1, 0)), ""), IF(val=0, "", val))} -> 0.016817191 | F7: {=LET(val, IFERROR(INDEX('Daily 쨈 raw'!$A:$Z, MATCH(F$3, 'Daily 쨈 raw'!$A:$A, 0), MATCH($A7, 'Daily 쨈 raw'!$1:$1, 0)), ""), IF(val=0, "", val))} -> 0.016232668 | G7: {=LET(val, IFERROR(INDEX('Daily 쨈 raw'!$A:$Z, MATCH(G$3, 'Daily 쨈 raw'!$A:$A, 0), MATCH($A7, 'Daily 쨈 raw'!$1:$1, 0)), ""), IF(val=0, "", val))} -> 0.015785861 | H7: {=LET(val, IFERROR(INDEX('Daily 쨈 raw'!$A:$Z, MATCH(H$3, 'Daily 쨈 raw'!$A:$A, 0), MATCH($A7, 'Daily 쨈 raw'!$1:$1, 0)), ""), IF(val=0, "", val))} -> 0.047541869 | I7: {=LET(val, IFERROR(INDEX('Daily 쨈 raw'!$A:$Z, MATCH(I$3, 'Daily 쨈 raw'!$A:$A, 0), MATCH($A7, 'Daily 쨈 raw'!$1:$1, 0)), ""), IF(val=0, "", val))} -> 0.031718062 | J7: {=LET(val, IFERROR(INDEX('Daily 쨈 raw'!$A:$Z, MATCH(J$3, 'Daily 쨈 raw'!$A:$A, 0), MATCH($A7, 'Daily 쨈 raw'!$1:$1, 0)), ""), IF(val=0, "", val))} -> 0.029396596 | ... DZ7: {=LET(val, IFERROR(INDEX('Daily 쨈 raw'!$A:$Z, MATCH(DZ$3, 'Daily 쨈 raw'!$A:$A, 0), MATCH($A7, 'Daily 쨈 raw'!$1:$1, 0)), ""), IF(val=0, "", val))}
A8: Purchase_Done_User_CVR | B8: Purchase Done User | C8: {=LET(val, IFERROR(INDEX('Daily 쨈 raw'!$A:$Z, MATCH(C$3, 'Daily 쨈 raw'!$A:$A, 0), MATCH($A8, 'Daily 쨈 raw'!$1:$1, 0)), ""), IF(val=0, "", val))} -> 64 | D8: {=LET(val, IFERROR(INDEX('Daily 쨈 raw'!$A:$Z, MATCH(D$3, 'Daily 쨈 raw'!$A:$A, 0), MATCH($A8, 'Daily 쨈 raw'!$1:$1, 0)), ""), IF(val=0, "", val))} -> 82 | E8: {=LET(val, IFERROR(INDEX('Daily 쨈 raw'!$A:$Z, MATCH(E$3, 'Daily 쨈 raw'!$A:$A, 0), MATCH($A8, 'Daily 쨈 raw'!$1:$1, 0)), ""), IF(val=0, "", val))} -> 54 | F8: {=LET(val, IFERROR(INDEX('Daily 쨈 raw'!$A:$Z, MATCH(F$3, 'Daily 쨈 raw'!$A:$A, 0), MATCH($A8, 'Daily 쨈 raw'!$1:$1, 0)), ""), IF(val=0, "", val))} -> 48 | G8: {=LET(val, IFERROR(INDEX('Daily 쨈 raw'!$A:$Z, MATCH(G$3, 'Daily 쨈 raw'!$A:$A, 0), MATCH($A8, 'Daily 쨈 raw'!$1:$1, 0)), ""), IF(val=0, "", val))} -> 46 | H8: {=LET(val, IFERROR(INDEX('Daily 쨈 raw'!$A:$Z, MATCH(H$3, 'Daily 쨈 raw'!$A:$A, 0), MATCH($A8, 'Daily 쨈 raw'!$1:$1, 0)), ""), IF(val=0, "", val))} -> 88 | I8: {=LET(val, IFERROR(INDEX('Daily 쨈 raw'!$A:$Z, MATCH(I$3, 'Daily 쨈 raw'!$A:$A, 0), MATCH($A8, 'Daily 쨈 raw'!$1:$1, 0)), ""), IF(val=0, "", val))} -> 72 | J8: {=LET(val, IFERROR(INDEX('Daily 쨈 raw'!$A:$Z, MATCH(J$3, 'Daily 쨈 raw'!$A:$A, 0), MATCH($A8, 'Daily 쨈 raw'!$1:$1, 0)), ""), IF(val=0, "", val))} -> 57 | ... DZ8: {=LET(val, IFERROR(INDEX('Daily 쨈 raw'!$A:$Z, MATCH(DZ$3, 'Daily 쨈 raw'!$A:$A, 0), MATCH($A8, 'Daily 쨈 raw'!$1:$1, 0)), ""), IF(val=0, "", val))}
A9: Gen_Done_User | B9: Gen Done User | C9: {=LET(val, IFERROR(INDEX('Daily 쨈 raw'!$A:$Z, MATCH(C$3, 'Daily 쨈 raw'!$A:$A, 0), MATCH($A9, 'Daily 쨈 raw'!$1:$1, 0)), ""), IF(val=0, "", val))} -> 3283 | D9: {=LET(val, IFERROR(INDEX('Daily 쨈 raw'!$A:$Z, MATCH(D$3, 'Daily 쨈 raw'!$A:$A, 0), MATCH($A9, 'Daily 쨈 raw'!$1:$1, 0)), ""), IF(val=0, "", val))} -> 3390 | E9: {=LET(val, IFERROR(INDEX('Daily 쨈 raw'!$A:$Z, MATCH(E$3, 'Daily 쨈 raw'!$A:$A, 0), MATCH($A9, 'Daily 쨈 raw'!$1:$1, 0)), ""), IF(val=0, "", val))} -> 3211 | F9: {=LET(val, IFERROR(INDEX('Daily 쨈 raw'!$A:$Z, MATCH(F$3, 'Daily 쨈 raw'!$A:$A, 0), MATCH($A9, 'Daily 쨈 raw'!$1:$1, 0)), ""), IF(val=0, "", val))} -> 2957 | G9: {=LET(val, IFERROR(INDEX('Daily 쨈 raw'!$A:$Z, MATCH(G$3, 'Daily 쨈 raw'!$A:$A, 0), MATCH($A9, 'Daily 쨈 raw'!$1:$1, 0)), ""), IF(val=0, "", val))} -> 2914 | H9: {=LET(val, IFERROR(INDEX('Daily 쨈 raw'!$A:$Z, MATCH(H$3, 'Daily 쨈 raw'!$A:$A, 0), MATCH($A9, 'Daily 쨈 raw'!$1:$1, 0)), ""), IF(val=0, "", val))} -> 1851 | I9: {=LET(val, IFERROR(INDEX('Daily 쨈 raw'!$A:$Z, MATCH(I$3, 'Daily 쨈 raw'!$A:$A, 0), MATCH($A9, 'Daily 쨈 raw'!$1:$1, 0)), ""), IF(val=0, "", val))} -> 2270 | J9: {=LET(val, IFERROR(INDEX('Daily 쨈 raw'!$A:$Z, MATCH(J$3, 'Daily 쨈 raw'!$A:$A, 0), MATCH($A9, 'Daily 쨈 raw'!$1:$1, 0)), ""), IF(val=0, "", val))} -> 1939 | ... DZ9: {=LET(val, IFERROR(INDEX('Daily 쨈 raw'!$A:$Z, MATCH(DZ$3, 'Daily 쨈 raw'!$A:$A, 0), MATCH($A9, 'Daily 쨈 raw'!$1:$1, 0)), ""), IF(val=0, "", val))}
A10: Filter_Gen_Done_User | B10: ㄴ 필터 생성 유저 | C10: {=LET(val, IFERROR(INDEX('Daily 쨈 raw'!$A:$Z, MATCH(C$3, 'Daily 쨈 raw'!$A:$A, 0), MATCH($A10, 'Daily 쨈 raw'!$1:$1, 0)), ""), IF(val=0, "", val))} -> 3283 | D10: {=LET(val, IFERROR(INDEX('Daily 쨈 raw'!$A:$Z, MATCH(D$3, 'Daily 쨈 raw'!$A:$A, 0), MATCH($A10, 'Daily 쨈 raw'!$1:$1, 0)), ""), IF(val=0, "", val))} -> 3390 | E10: {=LET(val, IFERROR(INDEX('Daily 쨈 raw'!$A:$Z, MATCH(E$3, 'Daily 쨈 raw'!$A:$A, 0), MATCH($A10, 'Daily 쨈 raw'!$1:$1, 0)), ""), IF(val=0, "", val))} -> 3211 | F10: {=LET(val, IFERROR(INDEX('Daily 쨈 raw'!$A:$Z, MATCH(F$3, 'Daily 쨈 raw'!$A:$A, 0), MATCH($A10, 'Daily 쨈 raw'!$1:$1, 0)), ""), IF(val=0, "", val))} -> 2957 | G10: {=LET(val, IFERROR(INDEX('Daily 쨈 raw'!$A:$Z, MATCH(G$3, 'Daily 쨈 raw'!$A:$A, 0), MATCH($A10, 'Daily 쨈 raw'!$1:$1, 0)), ""), IF(val=0, "", val))} -> 2914 | H10: {=LET(val, IFERROR(INDEX('Daily 쨈 raw'!$A:$Z, MATCH(H$3, 'Daily 쨈 raw'!$A:$A, 0), MATCH($A10, 'Daily 쨈 raw'!$1:$1, 0)), ""), IF(val=0, "", val))} -> 1851 | I10: {=LET(val, IFERROR(INDEX('Daily 쨈 raw'!$A:$Z, MATCH(I$3, 'Daily 쨈 raw'!$A:$A, 0), MATCH($A10, 'Daily 쨈 raw'!$1:$1, 0)), ""), IF(val=0, "", val))} -> 2270 | J10: {=LET(val, IFERROR(INDEX('Daily 쨈 raw'!$A:$Z, MATCH(J$3, 'Daily 쨈 raw'!$A:$A, 0), MATCH($A10, 'Daily 쨈 raw'!$1:$1, 0)), ""), IF(val=0, "", val))} -> 1939 | ... DZ10: {=LET(val, IFERROR(INDEX('Daily 쨈 raw'!$A:$Z, MATCH(DZ$3, 'Daily 쨈 raw'!$A:$A, 0), MATCH($A10, 'Daily 쨈 raw'!$1:$1, 0)), ""), IF(val=0, "", val))}
A11: Custom_Prompt_Gen_Done_User | B11: ㄴ 커스텀 프롬프트 생성 유저 | C11: {=LET(val, IFERROR(INDEX('Daily 쨈 raw'!$A:$Z, MATCH(C$3, 'Daily 쨈 raw'!$A:$A, 0), MATCH($A11, 'Daily 쨈 raw'!$1:$1, 0)), ""), IF(val=0, "", val))} | D11: {=LET(val, IFERROR(INDEX('Daily 쨈 raw'!$A:$Z, MATCH(D$3, 'Daily 쨈 raw'!$A:$A, 0), MATCH($A11, 'Daily 쨈 raw'!$1:$1, 0)), ""), IF(val=0, "", val))} | E11: {=LET(val, IFERROR(INDEX('Daily 쨈 raw'!$A:$Z, MATCH(E$3, 'Daily 쨈 raw'!$A:$A, 0), MATCH($A11, 'Daily 쨈 raw'!$1:$1, 0)), ""), IF(val=0, "", val))} | F11: {=LET(val, IFERROR(INDEX('Daily 쨈 raw'!$A:$Z, MATCH(F$3, 'Daily 쨈 raw'!$A:$A, 0), MATCH($A11, 'Daily 쨈 raw'!$1:$1, 0)), ""), IF(val=0, "", val))} | G11: {=LET(val, IFERROR(INDEX('Daily 쨈 raw'!$A:$Z, MATCH(G$3, 'Daily 쨈 raw'!$A:$A, 0), MATCH($A11, 'Daily 쨈 raw'!$1:$1, 0)), ""), IF(val=0, "", val))} | H11: {=LET(val, IFERROR(INDEX('Daily 쨈 raw'!$A:$Z, MATCH(H$3, 'Daily 쨈 raw'!$A:$A, 0), MATCH($A11, 'Daily 쨈 raw'!$1:$1, 0)), ""), IF(val=0, "", val))} | I11: {=LET(val, IFERROR(INDEX('Daily 쨈 raw'!$A:$Z, MATCH(I$3, 'Daily 쨈 raw'!$A:$A, 0), MATCH($A11, 'Daily 쨈 raw'!$1:$1, 0)), ""), IF(val=0, "", val))} | J11: {=LET(val, IFERROR(INDEX('Daily 쨈 raw'!$A:$Z, MATCH(J$3, 'Daily 쨈 raw'!$A:$A, 0), MATCH($A11, 'Daily 쨈 raw'!$1:$1, 0)), ""), IF(val=0, "", val))} | ... DZ11: {=LET(val, IFERROR(INDEX('Daily 쨈 raw'!$A:$Z, MATCH(DZ$3, 'Daily 쨈 raw'!$A:$A, 0), MATCH($A11, 'Daily 쨈 raw'!$1:$1, 0)), ""), IF(val=0, "", val))}
B12: ㄴ 커스텀 프롬프트 생성 유저 비율 | BW12: =iferror(BW11/BW10, "") -> 0.032102729 | BX12: =iferror(BX11/BX10, "") -> 0.049036778 | BY12: =iferror(BY11/BY10, "") -> 0.02715655 | BZ12: =iferror(BZ11/BZ10, "") -> 0.034090909 | CA12: =iferror(CA11/CA10, "") -> 0.043175487 | CB12: =iferror(CB11/CB10, "") -> 0.1031941 | CC12: =iferror(CC11/CC10, "") -> 0.1147541 | CD12: =iferror(CD11/CD10, "") -> 0.17201835 | ... DZ12: =iferror(DZ11/DZ10, "")
A13: Gen_Done_Count | B13: Gen Done Count | C13: {=LET(val, IFERROR(INDEX('Daily 쨈 raw'!$A:$Z, MATCH(C$3, 'Daily 쨈 raw'!$A:$A, 0), MATCH($A13, 'Daily 쨈 raw'!$1:$1, 0)), ""), IF(val=0, "", val))} -> 4286 | D13: {=LET(val, IFERROR(INDEX('Daily 쨈 raw'!$A:$Z, MATCH(D$3, 'Daily 쨈 raw'!$A:$A, 0), MATCH($A13, 'Daily 쨈 raw'!$1:$1, 0)), ""), IF(val=0, "", val))} -> 4843 | E13: {=LET(val, IFERROR(INDEX('Daily 쨈 raw'!$A:$Z, MATCH(E$3, 'Daily 쨈 raw'!$A:$A, 0), MATCH($A13, 'Daily 쨈 raw'!$1:$1, 0)), ""), IF(val=0, "", val))} -> 4329 | F13: {=LET(val, IFERROR(INDEX('Daily 쨈 raw'!$A:$Z, MATCH(F$3, 'Daily 쨈 raw'!$A:$A, 0), MATCH($A13, 'Daily 쨈 raw'!$1:$1, 0)), ""), IF(val=0, "", val))} -> 4289 | G13: {=LET(val, IFERROR(INDEX('Daily 쨈 raw'!$A:$Z, MATCH(G$3, 'Daily 쨈 raw'!$A:$A, 0), MATCH($A13, 'Daily 쨈 raw'!$1:$1, 0)), ""), IF(val=0, "", val))} -> 4324 | H13: {=LET(val, IFERROR(INDEX('Daily 쨈 raw'!$A:$Z, MATCH(H$3, 'Daily 쨈 raw'!$A:$A, 0), MATCH($A13, 'Daily 쨈 raw'!$1:$1, 0)), ""), IF(val=0, "", val))} -> 3556 | I13: {=LET(val, IFERROR(INDEX('Daily 쨈 raw'!$A:$Z, MATCH(I$3, 'Daily 쨈 raw'!$A:$A, 0), MATCH($A13, 'Daily 쨈 raw'!$1:$1, 0)), ""), IF(val=0, "", val))} -> 4113 | J13: {=LET(val, IFERROR(INDEX('Daily 쨈 raw'!$A:$Z, MATCH(J$3, 'Daily 쨈 raw'!$A:$A, 0), MATCH($A13, 'Daily 쨈 raw'!$1:$1, 0)), ""), IF(val=0, "", val))} -> 3398 | ... DZ13: {=LET(val, IFERROR(INDEX('Daily 쨈 raw'!$A:$Z, MATCH(DZ$3, 'Daily 쨈 raw'!$A:$A, 0), MATCH($A13, 'Daily 쨈 raw'!$1:$1, 0)), ""), IF(val=0, "", val))}
A14: Filter_Gen_Done_Count | B14: ㄴ 필터 생성 건수 | C14: {=LET(val, IFERROR(INDEX('Daily 쨈 raw'!$A:$Z, MATCH(C$3, 'Daily 쨈 raw'!$A:$A, 0), MATCH($A14, 'Daily 쨈 raw'!$1:$1, 0)), ""), IF(val=0, "", val))} -> 4286 | D14: {=LET(val, IFERROR(INDEX('Daily 쨈 raw'!$A:$Z, MATCH(D$3, 'Daily 쨈 raw'!$A:$A, 0), MATCH($A14, 'Daily 쨈 raw'!$1:$1, 0)), ""), IF(val=0, "", val))} -> 4843 | E14: {=LET(val, IFERROR(INDEX('Daily 쨈 raw'!$A:$Z, MATCH(E$3, 'Daily 쨈 raw'!$A:$A, 0), MATCH($A14, 'Daily 쨈 raw'!$1:$1, 0)), ""), IF(val=0, "", val))} -> 4329 | F14: {=LET(val, IFERROR(INDEX('Daily 쨈 raw'!$A:$Z, MATCH(F$3, 'Daily 쨈 raw'!$A:$A, 0), MATCH($A14, 'Daily 쨈 raw'!$1:$1, 0)), ""), IF(val=0, "", val))} -> 4289 | G14: {=LET(val, IFERROR(INDEX('Daily 쨈 raw'!$A:$Z, MATCH(G$3, 'Daily 쨈 raw'!$A:$A, 0), MATCH($A14, 'Daily 쨈 raw'!$1:$1, 0)), ""), IF(val=0, "", val))} -> 4324 | H14: {=LET(val, IFERROR(INDEX('Daily 쨈 raw'!$A:$Z, MATCH(H$3, 'Daily 쨈 raw'!$A:$A, 0), MATCH($A14, 'Daily 쨈 raw'!$1:$1, 0)), ""), IF(val=0, "", val))} -> 3556 | I14: {=LET(val, IFERROR(INDEX('Daily 쨈 raw'!$A:$Z, MATCH(I$3, 'Daily 쨈 raw'!$A:$A, 0), MATCH($A14, 'Daily 쨈 raw'!$1:$1, 0)), ""), IF(val=0, "", val))} -> 4113 | J14: {=LET(val, IFERROR(INDEX('Daily 쨈 raw'!$A:$Z, MATCH(J$3, 'Daily 쨈 raw'!$A:$A, 0), MATCH($A14, 'Daily 쨈 raw'!$1:$1, 0)), ""), IF(val=0, "", val))} -> 3398 | ... DZ14: {=LET(val, IFERROR(INDEX('Daily 쨈 raw'!$A:$Z, MATCH(DZ$3, 'Daily 쨈 raw'!$A:$A, 0), MATCH($A14, 'Daily 쨈 raw'!$1:$1, 0)), ""), IF(val=0, "", val))}
A15: Custom_Prompt_Gen_Done_Count | B15: ㄴ 커스텀 프롬프트 생성 건수 | C15: {=LET(val, IFERROR(INDEX('Daily 쨈 raw'!$A:$Z, MATCH(C$3, 'Daily 쨈 raw'!$A:$A, 0), MATCH($A15, 'Daily 쨈 raw'!$1:$1, 0)), ""), IF(val=0, "", val))} | D15: {=LET(val, IFERROR(INDEX('Daily 쨈 raw'!$A:$Z, MATCH(D$3, 'Daily 쨈 raw'!$A:$A, 0), MATCH($A15, 'Daily 쨈 raw'!$1:$1, 0)), ""), IF(val=0, "", val))} | E15: {=LET(val, IFERROR(INDEX('Daily 쨈 raw'!$A:$Z, MATCH(E$3, 'Daily 쨈 raw'!$A:$A, 0), MATCH($A15, 'Daily 쨈 raw'!$1:$1, 0)), ""), IF(val=0, "", val))} | F15: {=LET(val, IFERROR(INDEX('Daily 쨈 raw'!$A:$Z, MATCH(F$3, 'Daily 쨈 raw'!$A:$A, 0), MATCH($A15, 'Daily 쨈 raw'!$1:$1, 0)), ""), IF(val=0, "", val))} | G15: {=LET(val, IFERROR(INDEX('Daily 쨈 raw'!$A:$Z, MATCH(G$3, 'Daily 쨈 raw'!$A:$A, 0), MATCH($A15, 'Daily 쨈 raw'!$1:$1, 0)), ""), IF(val=0, "", val))} | H15: {=LET(val, IFERROR(INDEX('Daily 쨈 raw'!$A:$Z, MATCH(H$3, 'Daily 쨈 raw'!$A:$A, 0), MATCH($A15, 'Daily 쨈 raw'!$1:$1, 0)), ""), IF(val=0, "", val))} | I15: {=LET(val, IFERROR(INDEX('Daily 쨈 raw'!$A:$Z, MATCH(I$3, 'Daily 쨈 raw'!$A:$A, 0), MATCH($A15, 'Daily 쨈 raw'!$1:$1, 0)), ""), IF(val=0, "", val))} | J15: {=LET(val, IFERROR(INDEX('Daily 쨈 raw'!$A:$Z, MATCH(J$3, 'Daily 쨈 raw'!$A:$A, 0), MATCH($A15, 'Daily 쨈 raw'!$1:$1, 0)), ""), IF(val=0, "", val))} | ... DZ15: {=LET(val, IFERROR(INDEX('Daily 쨈 raw'!$A:$Z, MATCH(DZ$3, 'Daily 쨈 raw'!$A:$A, 0), MATCH($A15, 'Daily 쨈 raw'!$1:$1, 0)), ""), IF(val=0, "", val))}
B16: ㄴ 커스텀 프롬프트 생성 건수 비율 | BW16: =iferror(BW15/BW14, "") -> 0.07415036 | BX16: =iferror(BX15/BX14, "") -> 0.069817401 | BY16: =iferror(BY15/BY14, "") -> 0.028318584 | BZ16: =iferror(BZ15/BZ14, "") -> 0.043438914 | CA16: =iferror(CA15/CA14, "") -> 0.055166375 | CB16: =iferror(CB15/CB14, "") -> 0.098296199 | CC16: =iferror(CC15/CC14, "") -> 0.10790598 | CD16: =iferror(CD15/CD14, "") -> 0.16146394 | ... DZ16: =iferror(DZ15/DZ14, "")
A17: Gen_Done_Count_Per_User | B17: 생성 유저 당 생성 건수 | C17: {=LET(val, IFERROR(INDEX('Daily 쨈 raw'!$A:$Z, MATCH(C$3, 'Daily 쨈 raw'!$A:$A, 0), MATCH($A17, 'Daily 쨈 raw'!$1:$1, 0)), ""), IF(val=0, "", val))} -> 1.3055132 | D17: {=LET(val, IFERROR(INDEX('Daily 쨈 raw'!$A:$Z, MATCH(D$3, 'Daily 쨈 raw'!$A:$A, 0), MATCH($A17, 'Daily 쨈 raw'!$1:$1, 0)), ""), IF(val=0, "", val))} -> 1.4286136 | E17: {=LET(val, IFERROR(INDEX('Daily 쨈 raw'!$A:$Z, MATCH(E$3, 'Daily 쨈 raw'!$A:$A, 0), MATCH($A17, 'Daily 쨈 raw'!$1:$1, 0)), ""), IF(val=0, "", val))} -> 1.3481781 | F17: {=LET(val, IFERROR(INDEX('Daily 쨈 raw'!$A:$Z, MATCH(F$3, 'Daily 쨈 raw'!$A:$A, 0), MATCH($A17, 'Daily 쨈 raw'!$1:$1, 0)), ""), IF(val=0, "", val))} -> 1.4504565 | G17: {=LET(val, IFERROR(INDEX('Daily 쨈 raw'!$A:$Z, MATCH(G$3, 'Daily 쨈 raw'!$A:$A, 0), MATCH($A17, 'Daily 쨈 raw'!$1:$1, 0)), ""), IF(val=0, "", val))} -> 1.483871 | H17: {=LET(val, IFERROR(INDEX('Daily 쨈 raw'!$A:$Z, MATCH(H$3, 'Daily 쨈 raw'!$A:$A, 0), MATCH($A17, 'Daily 쨈 raw'!$1:$1, 0)), ""), IF(val=0, "", val))} -> 1.9211237 | I17: {=LET(val, IFERROR(INDEX('Daily 쨈 raw'!$A:$Z, MATCH(I$3, 'Daily 쨈 raw'!$A:$A, 0), MATCH($A17, 'Daily 쨈 raw'!$1:$1, 0)), ""), IF(val=0, "", val))} -> 1.8118943 | J17: {=LET(val, IFERROR(INDEX('Daily 쨈 raw'!$A:$Z, MATCH(J$3, 'Daily 쨈 raw'!$A:$A, 0), MATCH($A17, 'Daily 쨈 raw'!$1:$1, 0)), ""), IF(val=0, "", val))} -> 1.7524497 | ... DZ17: {=LET(val, IFERROR(INDEX('Daily 쨈 raw'!$A:$Z, MATCH(DZ$3, 'Daily 쨈 raw'!$A:$A, 0), MATCH($A17, 'Daily 쨈 raw'!$1:$1, 0)), ""), IF(val=0, "", val))}
A18: Filter_Gen_Done_Count_Per_User | B18: ㄴ 생성 유저 당 필터 생성 건수 | C18: {=LET(val, IFERROR(INDEX('Daily 쨈 raw'!$A:$Z, MATCH(C$3, 'Daily 쨈 raw'!$A:$A, 0), MATCH($A18, 'Daily 쨈 raw'!$1:$1, 0)), ""), IF(val=0, "", val))} -> 1.3055132 | D18: {=LET(val, IFERROR(INDEX('Daily 쨈 raw'!$A:$Z, MATCH(D$3, 'Daily 쨈 raw'!$A:$A, 0), MATCH($A18, 'Daily 쨈 raw'!$1:$1, 0)), ""), IF(val=0, "", val))} -> 1.4286136 | E18: {=LET(val, IFERROR(INDEX('Daily 쨈 raw'!$A:$Z, MATCH(E$3, 'Daily 쨈 raw'!$A:$A, 0), MATCH($A18, 'Daily 쨈 raw'!$1:$1, 0)), ""), IF(val=0, "", val))} -> 1.3481781 | F18: {=LET(val, IFERROR(INDEX('Daily 쨈 raw'!$A:$Z, MATCH(F$3, 'Daily 쨈 raw'!$A:$A, 0), MATCH($A18, 'Daily 쨈 raw'!$1:$1, 0)), ""), IF(val=0, "", val))} -> 1.4504565 | G18: {=LET(val, IFERROR(INDEX('Daily 쨈 raw'!$A:$Z, MATCH(G$3, 'Daily 쨈 raw'!$A:$A, 0), MATCH($A18, 'Daily 쨈 raw'!$1:$1, 0)), ""), IF(val=0, "", val))} -> 1.483871 | H18: {=LET(val, IFERROR(INDEX('Daily 쨈 raw'!$A:$Z, MATCH(H$3, 'Daily 쨈 raw'!$A:$A, 0), MATCH($A18, 'Daily 쨈 raw'!$1:$1, 0)), ""), IF(val=0, "", val))} -> 1.9211237 | I18: {=LET(val, IFERROR(INDEX('Daily 쨈 raw'!$A:$Z, MATCH(I$3, 'Daily 쨈 raw'!$A:$A, 0), MATCH($A18, 'Daily 쨈 raw'!$1:$1, 0)), ""), IF(val=0, "", val))} -> 1.8118943 | J18: {=LET(val, IFERROR(INDEX('Daily 쨈 raw'!$A:$Z, MATCH(J$3, 'Daily 쨈 raw'!$A:$A, 0), MATCH($A18, 'Daily 쨈 raw'!$1:$1, 0)), ""), IF(val=0, "", val))} -> 1.7524497 | ... DZ18: {=LET(val, IFERROR(INDEX('Daily 쨈 raw'!$A:$Z, MATCH(DZ$3, 'Daily 쨈 raw'!$A:$A, 0), MATCH($A18, 'Daily 쨈 raw'!$1:$1, 0)), ""), IF(val=0, "", val))}
A19: Custom_Prompt_Gen_Done_Count_Per_User | B19: ㄴ 생성 유저 당 커스텀 프롬프트 생성 건수 | C19: {=LET(val, IFERROR(INDEX('Daily 쨈 raw'!$A:$Z, MATCH(C$3, 'Daily 쨈 raw'!$A:$A, 0), MATCH($A19, 'Daily 쨈 raw'!$1:$1, 0)), ""), IF(val=0, "", val))} | D19: {=LET(val, IFERROR(INDEX('Daily 쨈 raw'!$A:$Z, MATCH(D$3, 'Daily 쨈 raw'!$A:$A, 0), MATCH($A19, 'Daily 쨈 raw'!$1:$1, 0)), ""), IF(val=0, "", val))} | E19: {=LET(val, IFERROR(INDEX('Daily 쨈 raw'!$A:$Z, MATCH(E$3, 'Daily 쨈 raw'!$A:$A, 0), MATCH($A19, 'Daily 쨈 raw'!$1:$1, 0)), ""), IF(val=0, "", val))} | F19: {=LET(val, IFERROR(INDEX('Daily 쨈 raw'!$A:$Z, MATCH(F$3, 'Daily 쨈 raw'!$A:$A, 0), MATCH($A19, 'Daily 쨈 raw'!$1:$1, 0)), ""), IF(val=0, "", val))} | G19: {=LET(val, IFERROR(INDEX('Daily 쨈 raw'!$A:$Z, MATCH(G$3, 'Daily 쨈 raw'!$A:$A, 0), MATCH($A19, 'Daily 쨈 raw'!$1:$1, 0)), ""), IF(val=0, "", val))} | H19: {=LET(val, IFERROR(INDEX('Daily 쨈 raw'!$A:$Z, MATCH(H$3, 'Daily 쨈 raw'!$A:$A, 0), MATCH($A19, 'Daily 쨈 raw'!$1:$1, 0)), ""), IF(val=0, "", val))} | I19: {=LET(val, IFERROR(INDEX('Daily 쨈 raw'!$A:$Z, MATCH(I$3, 'Daily 쨈 raw'!$A:$A, 0), MATCH($A19, 'Daily 쨈 raw'!$1:$1, 0)), ""), IF(val=0, "", val))} | J19: {=LET(val, IFERROR(INDEX('Daily 쨈 raw'!$A:$Z, MATCH(J$3, 'Daily 쨈 raw'!$A:$A, 0), MATCH($A19, 'Daily 쨈 raw'!$1:$1, 0)), ""), IF(val=0, "", val))} | ... DZ19: {=LET(val, IFERROR(INDEX('Daily 쨈 raw'!$A:$Z, MATCH(DZ$3, 'Daily 쨈 raw'!$A:$A, 0), MATCH($A19, 'Daily 쨈 raw'!$1:$1, 0)), ""), IF(val=0, "", val))}
A20: ARPPU | B20: ARPPU | C20: {=LET(val, IFERROR(INDEX('Daily 쨈 raw'!$A:$Z, MATCH(C$3, 'Daily 쨈 raw'!$A:$A, 0), MATCH($A20, 'Daily 쨈 raw'!$1:$1, 0)), ""), IF(val=0, "", val))} -> 5637.5 | D20: {=LET(val, IFERROR(INDEX('Daily 쨈 raw'!$A:$Z, MATCH(D$3, 'Daily 쨈 raw'!$A:$A, 0), MATCH($A20, 'Daily 쨈 raw'!$1:$1, 0)), ""), IF(val=0, "", val))} -> 6452.439 | E20: {=LET(val, IFERROR(INDEX('Daily 쨈 raw'!$A:$Z, MATCH(E$3, 'Daily 쨈 raw'!$A:$A, 0), MATCH($A20, 'Daily 쨈 raw'!$1:$1, 0)), ""), IF(val=0, "", val))} -> 6172.2222 | F20: {=LET(val, IFERROR(INDEX('Daily 쨈 raw'!$A:$Z, MATCH(F$3, 'Daily 쨈 raw'!$A:$A, 0), MATCH($A20, 'Daily 쨈 raw'!$1:$1, 0)), ""), IF(val=0, "", val))} -> 5683.3333 | G20: {=LET(val, IFERROR(INDEX('Daily 쨈 raw'!$A:$Z, MATCH(G$3, 'Daily 쨈 raw'!$A:$A, 0), MATCH($A20, 'Daily 쨈 raw'!$1:$1, 0)), ""), IF(val=0, "", val))} -> 6313.0435 | H20: {=LET(val, IFERROR(INDEX('Daily 쨈 raw'!$A:$Z, MATCH(H$3, 'Daily 쨈 raw'!$A:$A, 0), MATCH($A20, 'Daily 쨈 raw'!$1:$1, 0)), ""), IF(val=0, "", val))} -> 6037.5 | I20: {=LET(val, IFERROR(INDEX('Daily 쨈 raw'!$A:$Z, MATCH(I$3, 'Daily 쨈 raw'!$A:$A, 0), MATCH($A20, 'Daily 쨈 raw'!$1:$1, 0)), ""), IF(val=0, "", val))} -> 6279.1667 | J20: {=LET(val, IFERROR(INDEX('Daily 쨈 raw'!$A:$Z, MATCH(J$3, 'Daily 쨈 raw'!$A:$A, 0), MATCH($A20, 'Daily 쨈 raw'!$1:$1, 0)), ""), IF(val=0, "", val))} -> 6464.9123 | ... DZ20: {=LET(val, IFERROR(INDEX('Daily 쨈 raw'!$A:$Z, MATCH(DZ$3, 'Daily 쨈 raw'!$A:$A, 0), MATCH($A20, 'Daily 쨈 raw'!$1:$1, 0)), ""), IF(val=0, "", val))}
A21: Revenue | B21: Revenue | C21: {=LET(val, IFERROR(INDEX('Daily 쨈 raw'!$A:$Z, MATCH(C$3, 'Daily 쨈 raw'!$A:$A, 0), MATCH($A21, 'Daily 쨈 raw'!$1:$1, 0)), ""), IF(val=0, "", val))} -> 360800 | D21: {=LET(val, IFERROR(INDEX('Daily 쨈 raw'!$A:$Z, MATCH(D$3, 'Daily 쨈 raw'!$A:$A, 0), MATCH($A21, 'Daily 쨈 raw'!$1:$1, 0)), ""), IF(val=0, "", val))} -> 529100 | E21: {=LET(val, IFERROR(INDEX('Daily 쨈 raw'!$A:$Z, MATCH(E$3, 'Daily 쨈 raw'!$A:$A, 0), MATCH($A21, 'Daily 쨈 raw'!$1:$1, 0)), ""), IF(val=0, "", val))} -> 333300 | F21: {=LET(val, IFERROR(INDEX('Daily 쨈 raw'!$A:$Z, MATCH(F$3, 'Daily 쨈 raw'!$A:$A, 0), MATCH($A21, 'Daily 쨈 raw'!$1:$1, 0)), ""), IF(val=0, "", val))} -> 272800 | G21: {=LET(val, IFERROR(INDEX('Daily 쨈 raw'!$A:$Z, MATCH(G$3, 'Daily 쨈 raw'!$A:$A, 0), MATCH($A21, 'Daily 쨈 raw'!$1:$1, 0)), ""), IF(val=0, "", val))} -> 290400 | H21: {=LET(val, IFERROR(INDEX('Daily 쨈 raw'!$A:$Z, MATCH(H$3, 'Daily 쨈 raw'!$A:$A, 0), MATCH($A21, 'Daily 쨈 raw'!$1:$1, 0)), ""), IF(val=0, "", val))} -> 531300 | I21: {=LET(val, IFERROR(INDEX('Daily 쨈 raw'!$A:$Z, MATCH(I$3, 'Daily 쨈 raw'!$A:$A, 0), MATCH($A21, 'Daily 쨈 raw'!$1:$1, 0)), ""), IF(val=0, "", val))} -> 452100 | J21: {=LET(val, IFERROR(INDEX('Daily 쨈 raw'!$A:$Z, MATCH(J$3, 'Daily 쨈 raw'!$A:$A, 0), MATCH($A21, 'Daily 쨈 raw'!$1:$1, 0)), ""), IF(val=0, "", val))} -> 368500 | ... DZ21: {=LET(val, IFERROR(INDEX('Daily 쨈 raw'!$A:$Z, MATCH(DZ$3, 'Daily 쨈 raw'!$A:$A, 0), MATCH($A21, 'Daily 쨈 raw'!$1:$1, 0)), ""), IF(val=0, "", val))}
A22: Purchase_Done_User_ARPPU | B22: Purchase Done User | C22: {=LET(val, IFERROR(INDEX('Daily 쨈 raw'!$A:$ZZ, MATCH(C$3, 'Daily 쨈 raw'!$A:$A, 0), MATCH($A22, 'Daily 쨈 raw'!$1:$1, 0)), ""), IF(val=0, "", val))} -> 64 | D22: {=LET(val, IFERROR(INDEX('Daily 쨈 raw'!$A:$ZZ, MATCH(D$3, 'Daily 쨈 raw'!$A:$A, 0), MATCH($A22, 'Daily 쨈 raw'!$1:$1, 0)), ""), IF(val=0, "", val))} -> 82 | E22: {=LET(val, IFERROR(INDEX('Daily 쨈 raw'!$A:$ZZ, MATCH(E$3, 'Daily 쨈 raw'!$A:$A, 0), MATCH($A22, 'Daily 쨈 raw'!$1:$1, 0)), ""), IF(val=0, "", val))} -> 54 | F22: {=LET(val, IFERROR(INDEX('Daily 쨈 raw'!$A:$ZZ, MATCH(F$3, 'Daily 쨈 raw'!$A:$A, 0), MATCH($A22, 'Daily 쨈 raw'!$1:$1, 0)), ""), IF(val=0, "", val))} -> 48 | G22: {=LET(val, IFERROR(INDEX('Daily 쨈 raw'!$A:$ZZ, MATCH(G$3, 'Daily 쨈 raw'!$A:$A, 0), MATCH($A22, 'Daily 쨈 raw'!$1:$1, 0)), ""), IF(val=0, "", val))} -> 46 | H22: {=LET(val, IFERROR(INDEX('Daily 쨈 raw'!$A:$ZZ, MATCH(H$3, 'Daily 쨈 raw'!$A:$A, 0), MATCH($A22, 'Daily 쨈 raw'!$1:$1, 0)), ""), IF(val=0, "", val))} -> 88 | I22: {=LET(val, IFERROR(INDEX('Daily 쨈 raw'!$A:$ZZ, MATCH(I$3, 'Daily 쨈 raw'!$A:$A, 0), MATCH($A22, 'Daily 쨈 raw'!$1:$1, 0)), ""), IF(val=0, "", val))} -> 72 | J22: {=LET(val, IFERROR(INDEX('Daily 쨈 raw'!$A:$ZZ, MATCH(J$3, 'Daily 쨈 raw'!$A:$A, 0), MATCH($A22, 'Daily 쨈 raw'!$1:$1, 0)), ""), IF(val=0, "", val))} -> 57 | ... DZ22: {=LET(val, IFERROR(INDEX('Daily 쨈 raw'!$A:$ZZ, MATCH(DZ$3, 'Daily 쨈 raw'!$A:$A, 0), MATCH($A22, 'Daily 쨈 raw'!$1:$1, 0)), ""), IF(val=0, "", val))}
A23: Purchase_Done_Count | B23: Purchase Done Count | C23: {=LET(val, IFERROR(INDEX('Daily 쨈 raw'!$A:$ZZ, MATCH(C$3, 'Daily 쨈 raw'!$A:$A, 0), MATCH($A23, 'Daily 쨈 raw'!$1:$1, 0)), ""), IF(val=0, "", val))} -> 65 | D23: {=LET(val, IFERROR(INDEX('Daily 쨈 raw'!$A:$ZZ, MATCH(D$3, 'Daily 쨈 raw'!$A:$A, 0), MATCH($A23, 'Daily 쨈 raw'!$1:$1, 0)), ""), IF(val=0, "", val))} -> 86 | E23: {=LET(val, IFERROR(INDEX('Daily 쨈 raw'!$A:$ZZ, MATCH(E$3, 'Daily 쨈 raw'!$A:$A, 0), MATCH($A23, 'Daily 쨈 raw'!$1:$1, 0)), ""), IF(val=0, "", val))} -> 55 | F23: {=LET(val, IFERROR(INDEX('Daily 쨈 raw'!$A:$ZZ, MATCH(F$3, 'Daily 쨈 raw'!$A:$A, 0), MATCH($A23, 'Daily 쨈 raw'!$1:$1, 0)), ""), IF(val=0, "", val))} -> 50 | G23: {=LET(val, IFERROR(INDEX('Daily 쨈 raw'!$A:$ZZ, MATCH(G$3, 'Daily 쨈 raw'!$A:$A, 0), MATCH($A23, 'Daily 쨈 raw'!$1:$1, 0)), ""), IF(val=0, "", val))} -> 48 | H23: {=LET(val, IFERROR(INDEX('Daily 쨈 raw'!$A:$ZZ, MATCH(H$3, 'Daily 쨈 raw'!$A:$A, 0), MATCH($A23, 'Daily 쨈 raw'!$1:$1, 0)), ""), IF(val=0, "", val))} -> 95 | I23: {=LET(val, IFERROR(INDEX('Daily 쨈 raw'!$A:$ZZ, MATCH(I$3, 'Daily 쨈 raw'!$A:$A, 0), MATCH($A23, 'Daily 쨈 raw'!$1:$1, 0)), ""), IF(val=0, "", val))} -> 76 | J23: {=LET(val, IFERROR(INDEX('Daily 쨈 raw'!$A:$ZZ, MATCH(J$3, 'Daily 쨈 raw'!$A:$A, 0), MATCH($A23, 'Daily 쨈 raw'!$1:$1, 0)), ""), IF(val=0, "", val))} -> 60 | ... DZ23: {=LET(val, IFERROR(INDEX('Daily 쨈 raw'!$A:$ZZ, MATCH(DZ$3, 'Daily 쨈 raw'!$A:$A, 0), MATCH($A23, 'Daily 쨈 raw'!$1:$1, 0)), ""), IF(val=0, "", val))}
A24: Margin_Rate | B24: 마진율 | C24: {=LET(val, IFERROR(INDEX('Daily 쨈 raw'!$A:$ZZ, MATCH(C$3, 'Daily 쨈 raw'!$A:$A, 0), MATCH($A24, 'Daily 쨈 raw'!$1:$1, 0)), ""), IF(val=0, "", val))} -> -0.55578215 | D24: {=LET(val, IFERROR(INDEX('Daily 쨈 raw'!$A:$ZZ, MATCH(D$3, 'Daily 쨈 raw'!$A:$A, 0), MATCH($A24, 'Daily 쨈 raw'!$1:$1, 0)), ""), IF(val=0, "", val))} -> -0.25472009 | E24: {=LET(val, IFERROR(INDEX('Daily 쨈 raw'!$A:$ZZ, MATCH(E$3, 'Daily 쨈 raw'!$A:$A, 0), MATCH($A24, 'Daily 쨈 raw'!$1:$1, 0)), ""), IF(val=0, "", val))} -> -0.72882958 | F24: {=LET(val, IFERROR(INDEX('Daily 쨈 raw'!$A:$ZZ, MATCH(F$3, 'Daily 쨈 raw'!$A:$A, 0), MATCH($A24, 'Daily 쨈 raw'!$1:$1, 0)), ""), IF(val=0, "", val))} -> -0.91370271 | G24: {=LET(val, IFERROR(INDEX('Daily 쨈 raw'!$A:$ZZ, MATCH(G$3, 'Daily 쨈 raw'!$A:$A, 0), MATCH($A24, 'Daily 쨈 raw'!$1:$1, 0)), ""), IF(val=0, "", val))} -> -0.80823967 | H24: {=LET(val, IFERROR(INDEX('Daily 쨈 raw'!$A:$ZZ, MATCH(H$3, 'Daily 쨈 raw'!$A:$A, 0), MATCH($A24, 'Daily 쨈 raw'!$1:$1, 0)), ""), IF(val=0, "", val))} -> 0.077168643 | I24: {=LET(val, IFERROR(INDEX('Daily 쨈 raw'!$A:$ZZ, MATCH(I$3, 'Daily 쨈 raw'!$A:$A, 0), MATCH($A24, 'Daily 쨈 raw'!$1:$1, 0)), ""), IF(val=0, "", val))} -> -0.291405 | J24: {=LET(val, IFERROR(INDEX('Daily 쨈 raw'!$A:$ZZ, MATCH(J$3, 'Daily 쨈 raw'!$A:$A, 0), MATCH($A24, 'Daily 쨈 raw'!$1:$1, 0)), ""), IF(val=0, "", val))} -> -0.23321303 | ... DZ24: {=LET(val, IFERROR(INDEX('Daily 쨈 raw'!$A:$ZZ, MATCH(DZ$3, 'Daily 쨈 raw'!$A:$A, 0), MATCH($A24, 'Daily 쨈 raw'!$1:$1, 0)), ""), IF(val=0, "", val))}
A25: Cost | B25: Cost | C25: {=LET(val, IFERROR(INDEX('Daily 쨈 raw'!$A:$ZZ, MATCH(C$3, 'Daily 쨈 raw'!$A:$A, 0), MATCH($A25, 'Daily 쨈 raw'!$1:$1, 0)), ""), IF(val=0, "", val))} -> 561326.2 | D25: {=LET(val, IFERROR(INDEX('Daily 쨈 raw'!$A:$ZZ, MATCH(D$3, 'Daily 쨈 raw'!$A:$A, 0), MATCH($A25, 'Daily 쨈 raw'!$1:$1, 0)), ""), IF(val=0, "", val))} -> 663872.4 | E25: {=LET(val, IFERROR(INDEX('Daily 쨈 raw'!$A:$ZZ, MATCH(E$3, 'Daily 쨈 raw'!$A:$A, 0), MATCH($A25, 'Daily 쨈 raw'!$1:$1, 0)), ""), IF(val=0, "", val))} -> 576218.9 | F25: {=LET(val, IFERROR(INDEX('Daily 쨈 raw'!$A:$ZZ, MATCH(F$3, 'Daily 쨈 raw'!$A:$A, 0), MATCH($A25, 'Daily 쨈 raw'!$1:$1, 0)), ""), IF(val=0, "", val))} -> 522058.1 | G25: {=LET(val, IFERROR(INDEX('Daily 쨈 raw'!$A:$ZZ, MATCH(G$3, 'Daily 쨈 raw'!$A:$A, 0), MATCH($A25, 'Daily 쨈 raw'!$1:$1, 0)), ""), IF(val=0, "", val))} -> 525112.8 | H25: {=LET(val, IFERROR(INDEX('Daily 쨈 raw'!$A:$ZZ, MATCH(H$3, 'Daily 쨈 raw'!$A:$A, 0), MATCH($A25, 'Daily 쨈 raw'!$1:$1, 0)), ""), IF(val=0, "", val))} -> 490300.3 | I25: {=LET(val, IFERROR(INDEX('Daily 쨈 raw'!$A:$ZZ, MATCH(I$3, 'Daily 쨈 raw'!$A:$A, 0), MATCH($A25, 'Daily 쨈 raw'!$1:$1, 0)), ""), IF(val=0, "", val))} -> 583844.2 | J25: {=LET(val, IFERROR(INDEX('Daily 쨈 raw'!$A:$ZZ, MATCH(J$3, 'Daily 쨈 raw'!$A:$A, 0), MATCH($A25, 'Daily 쨈 raw'!$1:$1, 0)), ""), IF(val=0, "", val))} -> 454439 | ... DZ25: {=LET(val, IFERROR(INDEX('Daily 쨈 raw'!$A:$ZZ, MATCH(DZ$3, 'Daily 쨈 raw'!$A:$A, 0), MATCH($A25, 'Daily 쨈 raw'!$1:$1, 0)), ""), IF(val=0, "", val))}
A26: Revenue_ | B26: Revenue | C26: {=LET(val, IFERROR(INDEX('Daily 쨈 raw'!$A:$ZZ, MATCH(C$3, 'Daily 쨈 raw'!$A:$A, 0), MATCH($A26, 'Daily 쨈 raw'!$1:$1, 0)), ""), IF(val=0, "", val))} -> 360800 | D26: {=LET(val, IFERROR(INDEX('Daily 쨈 raw'!$A:$ZZ, MATCH(D$3, 'Daily 쨈 raw'!$A:$A, 0), MATCH($A26, 'Daily 쨈 raw'!$1:$1, 0)), ""), IF(val=0, "", val))} -> 529100 | E26: {=LET(val, IFERROR(INDEX('Daily 쨈 raw'!$A:$ZZ, MATCH(E$3, 'Daily 쨈 raw'!$A:$A, 0), MATCH($A26, 'Daily 쨈 raw'!$1:$1, 0)), ""), IF(val=0, "", val))} -> 333300 | F26: {=LET(val, IFERROR(INDEX('Daily 쨈 raw'!$A:$ZZ, MATCH(F$3, 'Daily 쨈 raw'!$A:$A, 0), MATCH($A26, 'Daily 쨈 raw'!$1:$1, 0)), ""), IF(val=0, "", val))} -> 272800 | G26: {=LET(val, IFERROR(INDEX('Daily 쨈 raw'!$A:$ZZ, MATCH(G$3, 'Daily 쨈 raw'!$A:$A, 0), MATCH($A26, 'Daily 쨈 raw'!$1:$1, 0)), ""), IF(val=0, "", val))} -> 290400 | H26: {=LET(val, IFERROR(INDEX('Daily 쨈 raw'!$A:$ZZ, MATCH(H$3, 'Daily 쨈 raw'!$A:$A, 0), MATCH($A26, 'Daily 쨈 raw'!$1:$1, 0)), ""), IF(val=0, "", val))} -> 531300 | I26: {=LET(val, IFERROR(INDEX('Daily 쨈 raw'!$A:$ZZ, MATCH(I$3, 'Daily 쨈 raw'!$A:$A, 0), MATCH($A26, 'Daily 쨈 raw'!$1:$1, 0)), ""), IF(val=0, "", val))} -> 452100 | J26: {=LET(val, IFERROR(INDEX('Daily 쨈 raw'!$A:$ZZ, MATCH(J$3, 'Daily 쨈 raw'!$A:$A, 0), MATCH($A26, 'Daily 쨈 raw'!$1:$1, 0)), ""), IF(val=0, "", val))} -> 368500 | ... DZ26: {=LET(val, IFERROR(INDEX('Daily 쨈 raw'!$A:$ZZ, MATCH(DZ$3, 'Daily 쨈 raw'!$A:$A, 0), MATCH($A26, 'Daily 쨈 raw'!$1:$1, 0)), ""), IF(val=0, "", val))}
B27: 퍼널 (신규) | C27: {=LET(val, IFERROR(INDEX('Daily 쨈 raw'!$A:$ZZ, MATCH(C$3, 'Daily 쨈 raw'!$A:$A, 0), MATCH($A27, 'Daily 쨈 raw'!$1:$1, 0)), ""), IF(val=0, "", val))} | D27: {=LET(val, IFERROR(INDEX('Daily 쨈 raw'!$A:$ZZ, MATCH(D$3, 'Daily 쨈 raw'!$A:$A, 0), MATCH($A27, 'Daily 쨈 raw'!$1:$1, 0)), ""), IF(val=0, "", val))} | E27: {=LET(val, IFERROR(INDEX('Daily 쨈 raw'!$A:$ZZ, MATCH(E$3, 'Daily 쨈 raw'!$A:$A, 0), MATCH($A27, 'Daily 쨈 raw'!$1:$1, 0)), ""), IF(val=0, "", val))} | F27: {=LET(val, IFERROR(INDEX('Daily 쨈 raw'!$A:$ZZ, MATCH(F$3, 'Daily 쨈 raw'!$A:$A, 0), MATCH($A27, 'Daily 쨈 raw'!$1:$1, 0)), ""), IF(val=0, "", val))} | G27: {=LET(val, IFERROR(INDEX('Daily 쨈 raw'!$A:$ZZ, MATCH(G$3, 'Daily 쨈 raw'!$A:$A, 0), MATCH($A27, 'Daily 쨈 raw'!$1:$1, 0)), ""), IF(val=0, "", val))} | H27: {=LET(val, IFERROR(INDEX('Daily 쨈 raw'!$A:$ZZ, MATCH(H$3, 'Daily 쨈 raw'!$A:$A, 0), MATCH($A27, 'Daily 쨈 raw'!$1:$1, 0)), ""), IF(val=0, "", val))} | I27: {=LET(val, IFERROR(INDEX('Daily 쨈 raw'!$A:$ZZ, MATCH(I$3, 'Daily 쨈 raw'!$A:$A, 0), MATCH($A27, 'Daily 쨈 raw'!$1:$1, 0)), ""), IF(val=0, "", val))} | J27: {=LET(val, IFERROR(INDEX('Daily 쨈 raw'!$A:$ZZ, MATCH(J$3, 'Daily 쨈 raw'!$A:$A, 0), MATCH($A27, 'Daily 쨈 raw'!$1:$1, 0)), ""), IF(val=0, "", val))} | ... DW27: {=LET(val, IFERROR(INDEX('Daily 쨈 raw'!$A:$ZZ, MATCH(DW$3, 'Daily 쨈 raw'!$A:$A, 0), MATCH($A27, 'Daily 쨈 raw'!$1:$1, 0)), ""), IF(val=0, "", val))}
A28: Install_User_New | B28: ㄴ Install User (ZZEM) | C28: {=LET(val, IFERROR(INDEX('Daily 쨈 raw'!$A:$ZZ, MATCH(C$3, 'Daily 쨈 raw'!$A:$A, 0), MATCH($A28, 'Daily 쨈 raw'!$1:$1, 0)), ""), IF(val=0, "", val))} | D28: {=LET(val, IFERROR(INDEX('Daily 쨈 raw'!$A:$ZZ, MATCH(D$3, 'Daily 쨈 raw'!$A:$A, 0), MATCH($A28, 'Daily 쨈 raw'!$1:$1, 0)), ""), IF(val=0, "", val))} | E28: {=LET(val, IFERROR(INDEX('Daily 쨈 raw'!$A:$ZZ, MATCH(E$3, 'Daily 쨈 raw'!$A:$A, 0), MATCH($A28, 'Daily 쨈 raw'!$1:$1, 0)), ""), IF(val=0, "", val))} | F28: {=LET(val, IFERROR(INDEX('Daily 쨈 raw'!$A:$ZZ, MATCH(F$3, 'Daily 쨈 raw'!$A:$A, 0), MATCH($A28, 'Daily 쨈 raw'!$1:$1, 0)), ""), IF(val=0, "", val))} | G28: {=LET(val, IFERROR(INDEX('Daily 쨈 raw'!$A:$ZZ, MATCH(G$3, 'Daily 쨈 raw'!$A:$A, 0), MATCH($A28, 'Daily 쨈 raw'!$1:$1, 0)), ""), IF(val=0, "", val))} | H28: {=LET(val, IFERROR(INDEX('Daily 쨈 raw'!$A:$ZZ, MATCH(H$3, 'Daily 쨈 raw'!$A:$A, 0), MATCH($A28, 'Daily 쨈 raw'!$1:$1, 0)), ""), IF(val=0, "", val))} | I28: {=LET(val, IFERROR(INDEX('Daily 쨈 raw'!$A:$ZZ, MATCH(I$3, 'Daily 쨈 raw'!$A:$A, 0), MATCH($A28, 'Daily 쨈 raw'!$1:$1, 0)), ""), IF(val=0, "", val))} | J28: {=LET(val, IFERROR(INDEX('Daily 쨈 raw'!$A:$ZZ, MATCH(J$3, 'Daily 쨈 raw'!$A:$A, 0), MATCH($A28, 'Daily 쨈 raw'!$1:$1, 0)), ""), IF(val=0, "", val))} | ... DW28: {=LET(val, IFERROR(INDEX('Daily 쨈 raw'!$A:$ZZ, MATCH(DW$3, 'Daily 쨈 raw'!$A:$A, 0), MATCH($A28, 'Daily 쨈 raw'!$1:$1, 0)), ""), IF(val=0, "", val))}
A29: Sign_Up_User_New | B29: ㄴ Sign Up User (ZZEM) | C29: {=LET(val, IFERROR(INDEX('Daily 쨈 raw'!$A:$ZZ, MATCH(C$3, 'Daily 쨈 raw'!$A:$A, 0), MATCH($A29, 'Daily 쨈 raw'!$1:$1, 0)), ""), IF(val=0, "", val))} | D29: {=LET(val, IFERROR(INDEX('Daily 쨈 raw'!$A:$ZZ, MATCH(D$3, 'Daily 쨈 raw'!$A:$A, 0), MATCH($A29, 'Daily 쨈 raw'!$1:$1, 0)), ""), IF(val=0, "", val))} | E29: {=LET(val, IFERROR(INDEX('Daily 쨈 raw'!$A:$ZZ, MATCH(E$3, 'Daily 쨈 raw'!$A:$A, 0), MATCH($A29, 'Daily 쨈 raw'!$1:$1, 0)), ""), IF(val=0, "", val))} | F29: {=LET(val, IFERROR(INDEX('Daily 쨈 raw'!$A:$ZZ, MATCH(F$3, 'Daily 쨈 raw'!$A:$A, 0), MATCH($A29, 'Daily 쨈 raw'!$1:$1, 0)), ""), IF(val=0, "", val))} | G29: {=LET(val, IFERROR(INDEX('Daily 쨈 raw'!$A:$ZZ, MATCH(G$3, 'Daily 쨈 raw'!$A:$A, 0), MATCH($A29, 'Daily 쨈 raw'!$1:$1, 0)), ""), IF(val=0, "", val))} | H29: {=LET(val, IFERROR(INDEX('Daily 쨈 raw'!$A:$ZZ, MATCH(H$3, 'Daily 쨈 raw'!$A:$A, 0), MATCH($A29, 'Daily 쨈 raw'!$1:$1, 0)), ""), IF(val=0, "", val))} | I29: {=LET(val, IFERROR(INDEX('Daily 쨈 raw'!$A:$ZZ, MATCH(I$3, 'Daily 쨈 raw'!$A:$A, 0), MATCH($A29, 'Daily 쨈 raw'!$1:$1, 0)), ""), IF(val=0, "", val))} | J29: {=LET(val, IFERROR(INDEX('Daily 쨈 raw'!$A:$ZZ, MATCH(J$3, 'Daily 쨈 raw'!$A:$A, 0), MATCH($A29, 'Daily 쨈 raw'!$1:$1, 0)), ""), IF(val=0, "", val))} | ... DW29: {=LET(val, IFERROR(INDEX('Daily 쨈 raw'!$A:$ZZ, MATCH(DW$3, 'Daily 쨈 raw'!$A:$A, 0), MATCH($A29, 'Daily 쨈 raw'!$1:$1, 0)), ""), IF(val=0, "", val))}
A30: Main_View_User_New | B30: ㄴ Main View User | C30: {=LET(val, IFERROR(INDEX('Daily 쨈 raw'!$A:$ZZ, MATCH(C$3, 'Daily 쨈 raw'!$A:$A, 0), MATCH($A30, 'Daily 쨈 raw'!$1:$1, 0)), ""), IF(val=0, "", val))} -> 362 | D30: {=LET(val, IFERROR(INDEX('Daily 쨈 raw'!$A:$ZZ, MATCH(D$3, 'Daily 쨈 raw'!$A:$A, 0), MATCH($A30, 'Daily 쨈 raw'!$1:$1, 0)), ""), IF(val=0, "", val))} -> 474 | E30: {=LET(val, IFERROR(INDEX('Daily 쨈 raw'!$A:$ZZ, MATCH(E$3, 'Daily 쨈 raw'!$A:$A, 0), MATCH($A30, 'Daily 쨈 raw'!$1:$1, 0)), ""), IF(val=0, "", val))} -> 396 | F30: {=LET(val, IFERROR(INDEX('Daily 쨈 raw'!$A:$ZZ, MATCH(F$3, 'Daily 쨈 raw'!$A:$A, 0), MATCH($A30, 'Daily 쨈 raw'!$1:$1, 0)), ""), IF(val=0, "", val))} -> 459 | G30: {=LET(val, IFERROR(INDEX('Daily 쨈 raw'!$A:$ZZ, MATCH(G$3, 'Daily 쨈 raw'!$A:$A, 0), MATCH($A30, 'Daily 쨈 raw'!$1:$1, 0)), ""), IF(val=0, "", val))} -> 393 | H30: {=LET(val, IFERROR(INDEX('Daily 쨈 raw'!$A:$ZZ, MATCH(H$3, 'Daily 쨈 raw'!$A:$A, 0), MATCH($A30, 'Daily 쨈 raw'!$1:$1, 0)), ""), IF(val=0, "", val))} -> 382 | I30: {=LET(val, IFERROR(INDEX('Daily 쨈 raw'!$A:$ZZ, MATCH(I$3, 'Daily 쨈 raw'!$A:$A, 0), MATCH($A30, 'Daily 쨈 raw'!$1:$1, 0)), ""), IF(val=0, "", val))} -> 410 | J30: {=LET(val, IFERROR(INDEX('Daily 쨈 raw'!$A:$ZZ, MATCH(J$3, 'Daily 쨈 raw'!$A:$A, 0), MATCH($A30, 'Daily 쨈 raw'!$1:$1, 0)), ""), IF(val=0, "", val))} -> 372 | ... DW30: {=LET(val, IFERROR(INDEX('Daily 쨈 raw'!$A:$ZZ, MATCH(DW$3, 'Daily 쨈 raw'!$A:$A, 0), MATCH($A30, 'Daily 쨈 raw'!$1:$1, 0)), ""), IF(val=0, "", val))}
A31: Product_View_User_New | B31: ㄴ Product View User | C31: {=LET(val, IFERROR(INDEX('Daily 쨈 raw'!$A:$ZZ, MATCH(C$3, 'Daily 쨈 raw'!$A:$A, 0), MATCH($A31, 'Daily 쨈 raw'!$1:$1, 0)), ""), IF(val=0, "", val))} -> 161 | D31: {=LET(val, IFERROR(INDEX('Daily 쨈 raw'!$A:$ZZ, MATCH(D$3, 'Daily 쨈 raw'!$A:$A, 0), MATCH($A31, 'Daily 쨈 raw'!$1:$1, 0)), ""), IF(val=0, "", val))} -> 245 | E31: {=LET(val, IFERROR(INDEX('Daily 쨈 raw'!$A:$ZZ, MATCH(E$3, 'Daily 쨈 raw'!$A:$A, 0), MATCH($A31, 'Daily 쨈 raw'!$1:$1, 0)), ""), IF(val=0, "", val))} -> 162 | F31: {=LET(val, IFERROR(INDEX('Daily 쨈 raw'!$A:$ZZ, MATCH(F$3, 'Daily 쨈 raw'!$A:$A, 0), MATCH($A31, 'Daily 쨈 raw'!$1:$1, 0)), ""), IF(val=0, "", val))} -> 212 | G31: {=LET(val, IFERROR(INDEX('Daily 쨈 raw'!$A:$ZZ, MATCH(G$3, 'Daily 쨈 raw'!$A:$A, 0), MATCH($A31, 'Daily 쨈 raw'!$1:$1, 0)), ""), IF(val=0, "", val))} -> 175 | H31: {=LET(val, IFERROR(INDEX('Daily 쨈 raw'!$A:$ZZ, MATCH(H$3, 'Daily 쨈 raw'!$A:$A, 0), MATCH($A31, 'Daily 쨈 raw'!$1:$1, 0)), ""), IF(val=0, "", val))} -> 132 | I31: {=LET(val, IFERROR(INDEX('Daily 쨈 raw'!$A:$ZZ, MATCH(I$3, 'Daily 쨈 raw'!$A:$A, 0), MATCH($A31, 'Daily 쨈 raw'!$1:$1, 0)), ""), IF(val=0, "", val))} -> 140 | J31: {=LET(val, IFERROR(INDEX('Daily 쨈 raw'!$A:$ZZ, MATCH(J$3, 'Daily 쨈 raw'!$A:$A, 0), MATCH($A31, 'Daily 쨈 raw'!$1:$1, 0)), ""), IF(val=0, "", val))} -> 141 | ... DW31: {=LET(val, IFERROR(INDEX('Daily 쨈 raw'!$A:$ZZ, MATCH(DW$3, 'Daily 쨈 raw'!$A:$A, 0), MATCH($A31, 'Daily 쨈 raw'!$1:$1, 0)), ""), IF(val=0, "", val))}
A32: Gen_Done_User_New | B32: ㄴ Gen Done User | C32: {=LET(val, IFERROR(INDEX('Daily 쨈 raw'!$A:$ZZ, MATCH(C$3, 'Daily 쨈 raw'!$A:$A, 0), MATCH($A32, 'Daily 쨈 raw'!$1:$1, 0)), ""), IF(val=0, "", val))} -> 91 | D32: {=LET(val, IFERROR(INDEX('Daily 쨈 raw'!$A:$ZZ, MATCH(D$3, 'Daily 쨈 raw'!$A:$A, 0), MATCH($A32, 'Daily 쨈 raw'!$1:$1, 0)), ""), IF(val=0, "", val))} -> 155 | E32: {=LET(val, IFERROR(INDEX('Daily 쨈 raw'!$A:$ZZ, MATCH(E$3, 'Daily 쨈 raw'!$A:$A, 0), MATCH($A32, 'Daily 쨈 raw'!$1:$1, 0)), ""), IF(val=0, "", val))} -> 87 | F32: {=LET(val, IFERROR(INDEX('Daily 쨈 raw'!$A:$ZZ, MATCH(F$3, 'Daily 쨈 raw'!$A:$A, 0), MATCH($A32, 'Daily 쨈 raw'!$1:$1, 0)), ""), IF(val=0, "", val))} -> 116 | G32: {=LET(val, IFERROR(INDEX('Daily 쨈 raw'!$A:$ZZ, MATCH(G$3, 'Daily 쨈 raw'!$A:$A, 0), MATCH($A32, 'Daily 쨈 raw'!$1:$1, 0)), ""), IF(val=0, "", val))} -> 106 | H32: {=LET(val, IFERROR(INDEX('Daily 쨈 raw'!$A:$ZZ, MATCH(H$3, 'Daily 쨈 raw'!$A:$A, 0), MATCH($A32, 'Daily 쨈 raw'!$1:$1, 0)), ""), IF(val=0, "", val))} -> 50 | I32: {=LET(val, IFERROR(INDEX('Daily 쨈 raw'!$A:$ZZ, MATCH(I$3, 'Daily 쨈 raw'!$A:$A, 0), MATCH($A32, 'Daily 쨈 raw'!$1:$1, 0)), ""), IF(val=0, "", val))} -> 57 | J32: {=LET(val, IFERROR(INDEX('Daily 쨈 raw'!$A:$ZZ, MATCH(J$3, 'Daily 쨈 raw'!$A:$A, 0), MATCH($A32, 'Daily 쨈 raw'!$1:$1, 0)), ""), IF(val=0, "", val))} -> 54 | ... DW32: {=LET(val, IFERROR(INDEX('Daily 쨈 raw'!$A:$ZZ, MATCH(DW$3, 'Daily 쨈 raw'!$A:$A, 0), MATCH($A32, 'Daily 쨈 raw'!$1:$1, 0)), ""), IF(val=0, "", val))}
A33: Paywall_View_User_New | B33: ㄴ Paywall View User | C33: {=LET(val, IFERROR(INDEX('Daily 쨈 raw'!$A:$ZZ, MATCH(C$3, 'Daily 쨈 raw'!$A:$A, 0), MATCH($A33, 'Daily 쨈 raw'!$1:$1, 0)), ""), IF(val=0, "", val))} -> 32 | D33: {=LET(val, IFERROR(INDEX('Daily 쨈 raw'!$A:$ZZ, MATCH(D$3, 'Daily 쨈 raw'!$A:$A, 0), MATCH($A33, 'Daily 쨈 raw'!$1:$1, 0)), ""), IF(val=0, "", val))} -> 59 | E33: {=LET(val, IFERROR(INDEX('Daily 쨈 raw'!$A:$ZZ, MATCH(E$3, 'Daily 쨈 raw'!$A:$A, 0), MATCH($A33, 'Daily 쨈 raw'!$1:$1, 0)), ""), IF(val=0, "", val))} -> 38 | F33: {=LET(val, IFERROR(INDEX('Daily 쨈 raw'!$A:$ZZ, MATCH(F$3, 'Daily 쨈 raw'!$A:$A, 0), MATCH($A33, 'Daily 쨈 raw'!$1:$1, 0)), ""), IF(val=0, "", val))} -> 40 | G33: {=LET(val, IFERROR(INDEX('Daily 쨈 raw'!$A:$ZZ, MATCH(G$3, 'Daily 쨈 raw'!$A:$A, 0), MATCH($A33, 'Daily 쨈 raw'!$1:$1, 0)), ""), IF(val=0, "", val))} -> 47 | H33: {=LET(val, IFERROR(INDEX('Daily 쨈 raw'!$A:$ZZ, MATCH(H$3, 'Daily 쨈 raw'!$A:$A, 0), MATCH($A33, 'Daily 쨈 raw'!$1:$1, 0)), ""), IF(val=0, "", val))} -> 43 | I33: {=LET(val, IFERROR(INDEX('Daily 쨈 raw'!$A:$ZZ, MATCH(I$3, 'Daily 쨈 raw'!$A:$A, 0), MATCH($A33, 'Daily 쨈 raw'!$1:$1, 0)), ""), IF(val=0, "", val))} -> 43 | J33: {=LET(val, IFERROR(INDEX('Daily 쨈 raw'!$A:$ZZ, MATCH(J$3, 'Daily 쨈 raw'!$A:$A, 0), MATCH($A33, 'Daily 쨈 raw'!$1:$1, 0)), ""), IF(val=0, "", val))} -> 35 | ... DW33: {=LET(val, IFERROR(INDEX('Daily 쨈 raw'!$A:$ZZ, MATCH(DW$3, 'Daily 쨈 raw'!$A:$A, 0), MATCH($A33, 'Daily 쨈 raw'!$1:$1, 0)), ""), IF(val=0, "", val))}
A34: Purchase_Done_User_New | B34: ㄴ Purchase Done User | C34: {=LET(val, IFERROR(INDEX('Daily 쨈 raw'!$A:$ZZ, MATCH(C$3, 'Daily 쨈 raw'!$A:$A, 0), MATCH($A34, 'Daily 쨈 raw'!$1:$1, 0)), ""), IF(val=0, "", val))} -> 3 | D34: {=LET(val, IFERROR(INDEX('Daily 쨈 raw'!$A:$ZZ, MATCH(D$3, 'Daily 쨈 raw'!$A:$A, 0), MATCH($A34, 'Daily 쨈 raw'!$1:$1, 0)), ""), IF(val=0, "", val))} -> 5 | E34: {=LET(val, IFERROR(INDEX('Daily 쨈 raw'!$A:$ZZ, MATCH(E$3, 'Daily 쨈 raw'!$A:$A, 0), MATCH($A34, 'Daily 쨈 raw'!$1:$1, 0)), ""), IF(val=0, "", val))} -> 8 | F34: {=LET(val, IFERROR(INDEX('Daily 쨈 raw'!$A:$ZZ, MATCH(F$3, 'Daily 쨈 raw'!$A:$A, 0), MATCH($A34, 'Daily 쨈 raw'!$1:$1, 0)), ""), IF(val=0, "", val))} -> 5 | G34: {=LET(val, IFERROR(INDEX('Daily 쨈 raw'!$A:$ZZ, MATCH(G$3, 'Daily 쨈 raw'!$A:$A, 0), MATCH($A34, 'Daily 쨈 raw'!$1:$1, 0)), ""), IF(val=0, "", val))} -> 7 | H34: {=LET(val, IFERROR(INDEX('Daily 쨈 raw'!$A:$ZZ, MATCH(H$3, 'Daily 쨈 raw'!$A:$A, 0), MATCH($A34, 'Daily 쨈 raw'!$1:$1, 0)), ""), IF(val=0, "", val))} -> 8 | I34: {=LET(val, IFERROR(INDEX('Daily 쨈 raw'!$A:$ZZ, MATCH(I$3, 'Daily 쨈 raw'!$A:$A, 0), MATCH($A34, 'Daily 쨈 raw'!$1:$1, 0)), ""), IF(val=0, "", val))} -> 3 | J34: {=LET(val, IFERROR(INDEX('Daily 쨈 raw'!$A:$ZZ, MATCH(J$3, 'Daily 쨈 raw'!$A:$A, 0), MATCH($A34, 'Daily 쨈 raw'!$1:$1, 0)), ""), IF(val=0, "", val))} -> 3 | ... DW34: {=LET(val, IFERROR(INDEX('Daily 쨈 raw'!$A:$ZZ, MATCH(DW$3, 'Daily 쨈 raw'!$A:$A, 0), MATCH($A34, 'Daily 쨈 raw'!$1:$1, 0)), ""), IF(val=0, "", val))}
B35: 퍼널 (기존) | C35: {=LET(val, IFERROR(INDEX('Daily 쨈 raw'!$A:$ZZ, MATCH(C$3, 'Daily 쨈 raw'!$A:$A, 0), MATCH($A35, 'Daily 쨈 raw'!$1:$1, 0)), ""), IF(val=0, "", val))} | D35: {=LET(val, IFERROR(INDEX('Daily 쨈 raw'!$A:$ZZ, MATCH(D$3, 'Daily 쨈 raw'!$A:$A, 0), MATCH($A35, 'Daily 쨈 raw'!$1:$1, 0)), ""), IF(val=0, "", val))} | E35: {=LET(val, IFERROR(INDEX('Daily 쨈 raw'!$A:$ZZ, MATCH(E$3, 'Daily 쨈 raw'!$A:$A, 0), MATCH($A35, 'Daily 쨈 raw'!$1:$1, 0)), ""), IF(val=0, "", val))} | F35: {=LET(val, IFERROR(INDEX('Daily 쨈 raw'!$A:$ZZ, MATCH(F$3, 'Daily 쨈 raw'!$A:$A, 0), MATCH($A35, 'Daily 쨈 raw'!$1:$1, 0)), ""), IF(val=0, "", val))} | G35: {=LET(val, IFERROR(INDEX('Daily 쨈 raw'!$A:$ZZ, MATCH(G$3, 'Daily 쨈 raw'!$A:$A, 0), MATCH($A35, 'Daily 쨈 raw'!$1:$1, 0)), ""), IF(val=0, "", val))} | H35: {=LET(val, IFERROR(INDEX('Daily 쨈 raw'!$A:$ZZ, MATCH(H$3, 'Daily 쨈 raw'!$A:$A, 0), MATCH($A35, 'Daily 쨈 raw'!$1:$1, 0)), ""), IF(val=0, "", val))} | I35: {=LET(val, IFERROR(INDEX('Daily 쨈 raw'!$A:$ZZ, MATCH(I$3, 'Daily 쨈 raw'!$A:$A, 0), MATCH($A35, 'Daily 쨈 raw'!$1:$1, 0)), ""), IF(val=0, "", val))} | J35: {=LET(val, IFERROR(INDEX('Daily 쨈 raw'!$A:$ZZ, MATCH(J$3, 'Daily 쨈 raw'!$A:$A, 0), MATCH($A35, 'Daily 쨈 raw'!$1:$1, 0)), ""), IF(val=0, "", val))} | ... DW35: {=LET(val, IFERROR(INDEX('Daily 쨈 raw'!$A:$ZZ, MATCH(DW$3, 'Daily 쨈 raw'!$A:$A, 0), MATCH($A35, 'Daily 쨈 raw'!$1:$1, 0)), ""), IF(val=0, "", val))}
A36: Main_View_User_Normal | B36: ㄴ Main View User (ZZEM) | C36: {=LET(val, IFERROR(INDEX('Daily 쨈 raw'!$A:$ZZ, MATCH(C$3, 'Daily 쨈 raw'!$A:$A, 0), MATCH($A36, 'Daily 쨈 raw'!$1:$1, 0)), ""), IF(val=0, "", val))} -> 7263 | D36: {=LET(val, IFERROR(INDEX('Daily 쨈 raw'!$A:$ZZ, MATCH(D$3, 'Daily 쨈 raw'!$A:$A, 0), MATCH($A36, 'Daily 쨈 raw'!$1:$1, 0)), ""), IF(val=0, "", val))} -> 7706 | E36: {=LET(val, IFERROR(INDEX('Daily 쨈 raw'!$A:$ZZ, MATCH(E$3, 'Daily 쨈 raw'!$A:$A, 0), MATCH($A36, 'Daily 쨈 raw'!$1:$1, 0)), ""), IF(val=0, "", val))} -> 7440 | F36: {=LET(val, IFERROR(INDEX('Daily 쨈 raw'!$A:$ZZ, MATCH(F$3, 'Daily 쨈 raw'!$A:$A, 0), MATCH($A36, 'Daily 쨈 raw'!$1:$1, 0)), ""), IF(val=0, "", val))} -> 6612 | G36: {=LET(val, IFERROR(INDEX('Daily 쨈 raw'!$A:$ZZ, MATCH(G$3, 'Daily 쨈 raw'!$A:$A, 0), MATCH($A36, 'Daily 쨈 raw'!$1:$1, 0)), ""), IF(val=0, "", val))} -> 7268 | H36: {=LET(val, IFERROR(INDEX('Daily 쨈 raw'!$A:$ZZ, MATCH(H$3, 'Daily 쨈 raw'!$A:$A, 0), MATCH($A36, 'Daily 쨈 raw'!$1:$1, 0)), ""), IF(val=0, "", val))} -> 7292 | I36: {=LET(val, IFERROR(INDEX('Daily 쨈 raw'!$A:$ZZ, MATCH(I$3, 'Daily 쨈 raw'!$A:$A, 0), MATCH($A36, 'Daily 쨈 raw'!$1:$1, 0)), ""), IF(val=0, "", val))} -> 7323 | J36: {=LET(val, IFERROR(INDEX('Daily 쨈 raw'!$A:$ZZ, MATCH(J$3, 'Daily 쨈 raw'!$A:$A, 0), MATCH($A36, 'Daily 쨈 raw'!$1:$1, 0)), ""), IF(val=0, "", val))} -> 6822 | ... DW36: {=LET(val, IFERROR(INDEX('Daily 쨈 raw'!$A:$ZZ, MATCH(DW$3, 'Daily 쨈 raw'!$A:$A, 0), MATCH($A36, 'Daily 쨈 raw'!$1:$1, 0)), ""), IF(val=0, "", val))}
A37: Product_View_User_Normal | B37: ㄴ Product View User (ZZEM) | C37: {=LET(val, IFERROR(INDEX('Daily 쨈 raw'!$A:$ZZ, MATCH(C$3, 'Daily 쨈 raw'!$A:$A, 0), MATCH($A37, 'Daily 쨈 raw'!$1:$1, 0)), ""), IF(val=0, "", val))} -> 5558 | D37: {=LET(val, IFERROR(INDEX('Daily 쨈 raw'!$A:$ZZ, MATCH(D$3, 'Daily 쨈 raw'!$A:$A, 0), MATCH($A37, 'Daily 쨈 raw'!$1:$1, 0)), ""), IF(val=0, "", val))} -> 5780 | E37: {=LET(val, IFERROR(INDEX('Daily 쨈 raw'!$A:$ZZ, MATCH(E$3, 'Daily 쨈 raw'!$A:$A, 0), MATCH($A37, 'Daily 쨈 raw'!$1:$1, 0)), ""), IF(val=0, "", val))} -> 5594 | F37: {=LET(val, IFERROR(INDEX('Daily 쨈 raw'!$A:$ZZ, MATCH(F$3, 'Daily 쨈 raw'!$A:$A, 0), MATCH($A37, 'Daily 쨈 raw'!$1:$1, 0)), ""), IF(val=0, "", val))} -> 4514 | G37: {=LET(val, IFERROR(INDEX('Daily 쨈 raw'!$A:$ZZ, MATCH(G$3, 'Daily 쨈 raw'!$A:$A, 0), MATCH($A37, 'Daily 쨈 raw'!$1:$1, 0)), ""), IF(val=0, "", val))} -> 5119 | H37: {=LET(val, IFERROR(INDEX('Daily 쨈 raw'!$A:$ZZ, MATCH(H$3, 'Daily 쨈 raw'!$A:$A, 0), MATCH($A37, 'Daily 쨈 raw'!$1:$1, 0)), ""), IF(val=0, "", val))} -> 5373 | I37: {=LET(val, IFERROR(INDEX('Daily 쨈 raw'!$A:$ZZ, MATCH(I$3, 'Daily 쨈 raw'!$A:$A, 0), MATCH($A37, 'Daily 쨈 raw'!$1:$1, 0)), ""), IF(val=0, "", val))} -> 5425 | J37: {=LET(val, IFERROR(INDEX('Daily 쨈 raw'!$A:$ZZ, MATCH(J$3, 'Daily 쨈 raw'!$A:$A, 0), MATCH($A37, 'Daily 쨈 raw'!$1:$1, 0)), ""), IF(val=0, "", val))} -> 4899 | ... DW37: {=LET(val, IFERROR(INDEX('Daily 쨈 raw'!$A:$ZZ, MATCH(DW$3, 'Daily 쨈 raw'!$A:$A, 0), MATCH($A37, 'Daily 쨈 raw'!$1:$1, 0)), ""), IF(val=0, "", val))}
A38: Gen_Done_User_Normal | B38: ㄴ Gen Done User | C38: {=LET(val, IFERROR(INDEX('Daily 쨈 raw'!$A:$ZZ, MATCH(C$3, 'Daily 쨈 raw'!$A:$A, 0), MATCH($A38, 'Daily 쨈 raw'!$1:$1, 0)), ""), IF(val=0, "", val))} -> 3192 | D38: {=LET(val, IFERROR(INDEX('Daily 쨈 raw'!$A:$ZZ, MATCH(D$3, 'Daily 쨈 raw'!$A:$A, 0), MATCH($A38, 'Daily 쨈 raw'!$1:$1, 0)), ""), IF(val=0, "", val))} -> 3235 | E38: {=LET(val, IFERROR(INDEX('Daily 쨈 raw'!$A:$ZZ, MATCH(E$3, 'Daily 쨈 raw'!$A:$A, 0), MATCH($A38, 'Daily 쨈 raw'!$1:$1, 0)), ""), IF(val=0, "", val))} -> 3124 | F38: {=LET(val, IFERROR(INDEX('Daily 쨈 raw'!$A:$ZZ, MATCH(F$3, 'Daily 쨈 raw'!$A:$A, 0), MATCH($A38, 'Daily 쨈 raw'!$1:$1, 0)), ""), IF(val=0, "", val))} -> 2841 | G38: {=LET(val, IFERROR(INDEX('Daily 쨈 raw'!$A:$ZZ, MATCH(G$3, 'Daily 쨈 raw'!$A:$A, 0), MATCH($A38, 'Daily 쨈 raw'!$1:$1, 0)), ""), IF(val=0, "", val))} -> 2808 | H38: {=LET(val, IFERROR(INDEX('Daily 쨈 raw'!$A:$ZZ, MATCH(H$3, 'Daily 쨈 raw'!$A:$A, 0), MATCH($A38, 'Daily 쨈 raw'!$1:$1, 0)), ""), IF(val=0, "", val))} -> 1801 | I38: {=LET(val, IFERROR(INDEX('Daily 쨈 raw'!$A:$ZZ, MATCH(I$3, 'Daily 쨈 raw'!$A:$A, 0), MATCH($A38, 'Daily 쨈 raw'!$1:$1, 0)), ""), IF(val=0, "", val))} -> 2213 | J38: {=LET(val, IFERROR(INDEX('Daily 쨈 raw'!$A:$ZZ, MATCH(J$3, 'Daily 쨈 raw'!$A:$A, 0), MATCH($A38, 'Daily 쨈 raw'!$1:$1, 0)), ""), IF(val=0, "", val))} -> 1885 | ... DW38: {=LET(val, IFERROR(INDEX('Daily 쨈 raw'!$A:$ZZ, MATCH(DW$3, 'Daily 쨈 raw'!$A:$A, 0), MATCH($A38, 'Daily 쨈 raw'!$1:$1, 0)), ""), IF(val=0, "", val))}
A39: Paywall_View_User_Normal | B39: ㄴ Paywall View User | C39: {=LET(val, IFERROR(INDEX('Daily 쨈 raw'!$A:$ZZ, MATCH(C$3, 'Daily 쨈 raw'!$A:$A, 0), MATCH($A39, 'Daily 쨈 raw'!$1:$1, 0)), ""), IF(val=0, "", val))} -> 539 | D39: {=LET(val, IFERROR(INDEX('Daily 쨈 raw'!$A:$ZZ, MATCH(D$3, 'Daily 쨈 raw'!$A:$A, 0), MATCH($A39, 'Daily 쨈 raw'!$1:$1, 0)), ""), IF(val=0, "", val))} -> 749 | E39: {=LET(val, IFERROR(INDEX('Daily 쨈 raw'!$A:$ZZ, MATCH(E$3, 'Daily 쨈 raw'!$A:$A, 0), MATCH($A39, 'Daily 쨈 raw'!$1:$1, 0)), ""), IF(val=0, "", val))} -> 594 | F39: {=LET(val, IFERROR(INDEX('Daily 쨈 raw'!$A:$ZZ, MATCH(F$3, 'Daily 쨈 raw'!$A:$A, 0), MATCH($A39, 'Daily 쨈 raw'!$1:$1, 0)), ""), IF(val=0, "", val))} -> 586 | G39: {=LET(val, IFERROR(INDEX('Daily 쨈 raw'!$A:$ZZ, MATCH(G$3, 'Daily 쨈 raw'!$A:$A, 0), MATCH($A39, 'Daily 쨈 raw'!$1:$1, 0)), ""), IF(val=0, "", val))} -> 539 | H39: {=LET(val, IFERROR(INDEX('Daily 쨈 raw'!$A:$ZZ, MATCH(H$3, 'Daily 쨈 raw'!$A:$A, 0), MATCH($A39, 'Daily 쨈 raw'!$1:$1, 0)), ""), IF(val=0, "", val))} -> 1140 | I39: {=LET(val, IFERROR(INDEX('Daily 쨈 raw'!$A:$ZZ, MATCH(I$3, 'Daily 쨈 raw'!$A:$A, 0), MATCH($A39, 'Daily 쨈 raw'!$1:$1, 0)), ""), IF(val=0, "", val))} -> 1067 | J39: {=LET(val, IFERROR(INDEX('Daily 쨈 raw'!$A:$ZZ, MATCH(J$3, 'Daily 쨈 raw'!$A:$A, 0), MATCH($A39, 'Daily 쨈 raw'!$1:$1, 0)), ""), IF(val=0, "", val))} -> 897 | ... DW39: {=LET(val, IFERROR(INDEX('Daily 쨈 raw'!$A:$ZZ, MATCH(DW$3, 'Daily 쨈 raw'!$A:$A, 0), MATCH($A39, 'Daily 쨈 raw'!$1:$1, 0)), ""), IF(val=0, "", val))}
A40: Purchase_Done_User_Normal | B40: ㄴ Purchase Done User | C40: {=LET(val, IFERROR(INDEX('Daily 쨈 raw'!$A:$ZZ, MATCH(C$3, 'Daily 쨈 raw'!$A:$A, 0), MATCH($A40, 'Daily 쨈 raw'!$1:$1, 0)), ""), IF(val=0, "", val))} -> 61 | D40: {=LET(val, IFERROR(INDEX('Daily 쨈 raw'!$A:$ZZ, MATCH(D$3, 'Daily 쨈 raw'!$A:$A, 0), MATCH($A40, 'Daily 쨈 raw'!$1:$1, 0)), ""), IF(val=0, "", val))} -> 77 | E40: {=LET(val, IFERROR(INDEX('Daily 쨈 raw'!$A:$ZZ, MATCH(E$3, 'Daily 쨈 raw'!$A:$A, 0), MATCH($A40, 'Daily 쨈 raw'!$1:$1, 0)), ""), IF(val=0, "", val))} -> 46 | F40: {=LET(val, IFERROR(INDEX('Daily 쨈 raw'!$A:$ZZ, MATCH(F$3, 'Daily 쨈 raw'!$A:$A, 0), MATCH($A40, 'Daily 쨈 raw'!$1:$1, 0)), ""), IF(val=0, "", val))} -> 43 | G40: {=LET(val, IFERROR(INDEX('Daily 쨈 raw'!$A:$ZZ, MATCH(G$3, 'Daily 쨈 raw'!$A:$A, 0), MATCH($A40, 'Daily 쨈 raw'!$1:$1, 0)), ""), IF(val=0, "", val))} -> 39 | H40: {=LET(val, IFERROR(INDEX('Daily 쨈 raw'!$A:$ZZ, MATCH(H$3, 'Daily 쨈 raw'!$A:$A, 0), MATCH($A40, 'Daily 쨈 raw'!$1:$1, 0)), ""), IF(val=0, "", val))} -> 80 | I40: {=LET(val, IFERROR(INDEX('Daily 쨈 raw'!$A:$ZZ, MATCH(I$3, 'Daily 쨈 raw'!$A:$A, 0), MATCH($A40, 'Daily 쨈 raw'!$1:$1, 0)), ""), IF(val=0, "", val))} -> 69 | J40: {=LET(val, IFERROR(INDEX('Daily 쨈 raw'!$A:$ZZ, MATCH(J$3, 'Daily 쨈 raw'!$A:$A, 0), MATCH($A40, 'Daily 쨈 raw'!$1:$1, 0)), ""), IF(val=0, "", val))} -> 54 | ... DW40: {=LET(val, IFERROR(INDEX('Daily 쨈 raw'!$A:$ZZ, MATCH(DW$3, 'Daily 쨈 raw'!$A:$A, 0), MATCH($A40, 'Daily 쨈 raw'!$1:$1, 0)), ""), IF(val=0, "", val))}
BA41: {=IFERROR(INDEX('Daily 쨈 raw'!$A:$Z, MATCH(BA$3, 'Daily 쨈 raw'!$A:$A, 0), MATCH($A41, 'Daily 쨈 raw'!$1:$1, 0)), "")}

Sheet Weekly ZZEM
G1: 밈 플친톡 발송 | L1: ZZEM 출시: 1/26 (월) 가격 개편(밈): 1/30 (금) | M1: 커스텀 프롬프트: 2/4 (수) 퍼널 값 쨈으로 교체: 2/4 (수) 마케팅 ON: 2/4 (수) | N1: 뤼튼 밈 종료: 2/8 (일) | O1: 커스텀 프롬프트: 2/19 (목)
C2: W1 | D2: W2 | E2: W3 | F2: W4 | G2: W5 | H2: W6 | I2: W7 | J2: W8 | K2: W9 | L2: W10 | M2: W11 | N2: W12 | O2: W13 | P2: W14 | Q2: W15 | R2: W16 | S2: W17 | T2: W18 | U2: W13
A3: sql과 맞는 Metric | B3: Metric | C3: 45985 | D3: 45992 | E3: 45999 | F3: 46006 | G3: 46013 | H3: 46020 | I3: =H3+7 -> 46027 | J3: =I3+7 -> 46034 | K3: =J3+7 -> 46041 | L3: =K3+7 -> 46048 | M3: =L3+7 -> 46055 | N3: =M3+7 -> 46062 | O3: =N3+7 -> 46069 | P3: =O3+7 -> 46076 | ... U3: =T3+7 -> 46111
A4: Paid_Cohort_Retention | B4: Paid Cohort Retention | C4: {=LET(val, IFERROR(INDEX('Weekly 쨈 raw'!$A:$AAQ, MATCH(C$3, 'Weekly 쨈 raw'!$A:$A, 0), MATCH($A4, 'Weekly 쨈 raw'!$1:$1, 0)), ""), IF(val=0, "", val))} -> 0.70120482 | D4: {=LET(val, IFERROR(INDEX('Weekly 쨈 raw'!$A:$AAQ, MATCH(D$3, 'Weekly 쨈 raw'!$A:$A, 0), MATCH($A4, 'Weekly 쨈 raw'!$1:$1, 0)), ""), IF(val=0, "", val))} -> 0.57285429 | E4: {=LET(val, IFERROR(INDEX('Weekly 쨈 raw'!$A:$AAQ, MATCH(E$3, 'Weekly 쨈 raw'!$A:$A, 0), MATCH($A4, 'Weekly 쨈 raw'!$1:$1, 0)), ""), IF(val=0, "", val))} -> 0.47578348 | F4: {=LET(val, IFERROR(INDEX('Weekly 쨈 raw'!$A:$AAQ, MATCH(F$3, 'Weekly 쨈 raw'!$A:$A, 0), MATCH($A4, 'Weekly 쨈 raw'!$1:$1, 0)), ""), IF(val=0, "", val))} -> 0.54085603 | G4: {=LET(val, IFERROR(INDEX('Weekly 쨈 raw'!$A:$AAQ, MATCH(G$3, 'Weekly 쨈 raw'!$A:$A, 0), MATCH($A4, 'Weekly 쨈 raw'!$1:$1, 0)), ""), IF(val=0, "", val))} -> 0.59556104 | H4: {=LET(val, IFERROR(INDEX('Weekly 쨈 raw'!$A:$AAQ, MATCH(H$3, 'Weekly 쨈 raw'!$A:$A, 0), MATCH($A4, 'Weekly 쨈 raw'!$1:$1, 0)), ""), IF(val=0, "", val))} -> 0.5106383 | I4: {=LET(val, IFERROR(INDEX('Weekly 쨈 raw'!$A:$AAQ, MATCH(I$3, 'Weekly 쨈 raw'!$A:$A, 0), MATCH($A4, 'Weekly 쨈 raw'!$1:$1, 0)), ""), IF(val=0, "", val))} -> 0.50862069 | J4: {=LET(val, IFERROR(INDEX('Weekly 쨈 raw'!$A:$AAQ, MATCH(J$3, 'Weekly 쨈 raw'!$A:$A, 0), MATCH($A4, 'Weekly 쨈 raw'!$1:$1, 0)), ""), IF(val=0, "", val))} -> 0.50161812 | ... P4: {=LET(val, IFERROR(INDEX('Weekly 쨈 raw'!$A:$AAQ, MATCH(P$3, 'Weekly 쨈 raw'!$A:$A, 0), MATCH($A4, 'Weekly 쨈 raw'!$1:$1, 0)), ""), IF(val=0, "", val))} | Q4: {=IF(IFERROR(INDEX('Weekly 쨈 raw'!$A:$AAQ, MATCH(Q$3, 'Weekly 쨈 raw'!$A:$A, 0), MATCH($A4, 'Weekly 쨈 raw'!$1:$1, 0)), 0)=0, "", IFERROR(INDEX('Weekly 쨈 raw'!$A:$AAQ, MATCH(Q$3, 'Weekly 쨈 raw'!$A:$A, 0), MATCH($A4, 'Weekly 쨈 raw'!$1:$1, 0)), 0))} | R4: {=IF(IFERROR(INDEX('Weekly 쨈 raw'!$A:$AAQ, MATCH(R$3, 'Weekly 쨈 raw'!$A:$A, 0), MATCH($A4, 'Weekly 쨈 raw'!$1:$1, 0)), 0)=0, "", IFERROR(INDEX('Weekly 쨈 raw'!$A:$AAQ, MATCH(R$3, 'Weekly 쨈 raw'!$A:$A, 0), MATCH($A4, 'Weekly 쨈 raw'!$1:$1, 0)), 0))} | S4: {=IF(IFERROR(INDEX('Weekly 쨈 raw'!$A:$AAQ, MATCH(S$3, 'Weekly 쨈 raw'!$A:$A, 0), MATCH($A4, 'Weekly 쨈 raw'!$1:$1, 0)), 0)=0, "", IFERROR(INDEX('Weekly 쨈 raw'!$A:$AAQ, MATCH(S$3, 'Weekly 쨈 raw'!$A:$A, 0), MATCH($A4, 'Weekly 쨈 raw'!$1:$1, 0)), 0))} | T4: {=IF(IFERROR(INDEX('Weekly 쨈 raw'!$A:$AAQ, MATCH(T$3, 'Weekly 쨈 raw'!$A:$A, 0), MATCH($A4, 'Weekly 쨈 raw'!$1:$1, 0)), 0)=0, "", IFERROR(INDEX('Weekly 쨈 raw'!$A:$AAQ, MATCH(T$3, 'Weekly 쨈 raw'!$A:$A, 0), MATCH($A4, 'Weekly 쨈 raw'!$1:$1, 0)), 0))} | U4: {=IF(IFERROR(INDEX('Weekly 쨈 raw'!$A:$AAQ, MATCH(U$3, 'Weekly 쨈 raw'!$A:$A, 0), MATCH($A4, 'Weekly 쨈 raw'!$1:$1, 0)), 0)=0, "", IFERROR(INDEX('Weekly 쨈 raw'!$A:$AAQ, MATCH(U$3, 'Weekly 쨈 raw'!$A:$A, 0), MATCH($A4, 'Weekly 쨈 raw'!$1:$1, 0)), 0))}
A5: W1_Any_Event_User | B5: W1 Any Event User | C5: {=LET(val, IFERROR(INDEX('Weekly 쨈 raw'!$A:$AAQ, MATCH(C$3, 'Weekly 쨈 raw'!$A:$A, 0), MATCH($A5, 'Weekly 쨈 raw'!$1:$1, 0)), ""), IF(val=0, "", val))} -> 291 | D5: {=LET(val, IFERROR(INDEX('Weekly 쨈 raw'!$A:$AAQ, MATCH(D$3, 'Weekly 쨈 raw'!$A:$A, 0), MATCH($A5, 'Weekly 쨈 raw'!$1:$1, 0)), ""), IF(val=0, "", val))} -> 287 | E5: {=LET(val, IFERROR(INDEX('Weekly 쨈 raw'!$A:$AAQ, MATCH(E$3, 'Weekly 쨈 raw'!$A:$A, 0), MATCH($A5, 'Weekly 쨈 raw'!$1:$1, 0)), ""), IF(val=0, "", val))} -> 167 | F5: {=LET(val, IFERROR(INDEX('Weekly 쨈 raw'!$A:$AAQ, MATCH(F$3, 'Weekly 쨈 raw'!$A:$A, 0), MATCH($A5, 'Weekly 쨈 raw'!$1:$1, 0)), ""), IF(val=0, "", val))} -> 139 | G5: {=LET(val, IFERROR(INDEX('Weekly 쨈 raw'!$A:$AAQ, MATCH(G$3, 'Weekly 쨈 raw'!$A:$A, 0), MATCH($A5, 'Weekly 쨈 raw'!$1:$1, 0)), ""), IF(val=0, "", val))} -> 483 | H5: {=LET(val, IFERROR(INDEX('Weekly 쨈 raw'!$A:$AAQ, MATCH(H$3, 'Weekly 쨈 raw'!$A:$A, 0), MATCH($A5, 'Weekly 쨈 raw'!$1:$1, 0)), ""), IF(val=0, "", val))} -> 216 | I5: {=LET(val, IFERROR(INDEX('Weekly 쨈 raw'!$A:$AAQ, MATCH(I$3, 'Weekly 쨈 raw'!$A:$A, 0), MATCH($A5, 'Weekly 쨈 raw'!$1:$1, 0)), ""), IF(val=0, "", val))} -> 118 | J5: {=LET(val, IFERROR(INDEX('Weekly 쨈 raw'!$A:$AAQ, MATCH(J$3, 'Weekly 쨈 raw'!$A:$A, 0), MATCH($A5, 'Weekly 쨈 raw'!$1:$1, 0)), ""), IF(val=0, "", val))} -> 155 | ... P5: {=LET(val, IFERROR(INDEX('Weekly 쨈 raw'!$A:$AAQ, MATCH(P$3, 'Weekly 쨈 raw'!$A:$A, 0), MATCH($A5, 'Weekly 쨈 raw'!$1:$1, 0)), ""), IF(val=0, "", val))} | Q5: {=IF(IFERROR(INDEX('Weekly 쨈 raw'!$A:$AAQ, MATCH(Q$3, 'Weekly 쨈 raw'!$A:$A, 0), MATCH($A5, 'Weekly 쨈 raw'!$1:$1, 0)), 0)=0, "", IFERROR(INDEX('Weekly 쨈 raw'!$A:$AAQ, MATCH(Q$3, 'Weekly 쨈 raw'!$A:$A, 0), MATCH($A5, 'Weekly 쨈 raw'!$1:$1, 0)), 0))} | R5: {=IF(IFERROR(INDEX('Weekly 쨈 raw'!$A:$AAQ, MATCH(R$3, 'Weekly 쨈 raw'!$A:$A, 0), MATCH($A5, 'Weekly 쨈 raw'!$1:$1, 0)), 0)=0, "", IFERROR(INDEX('Weekly 쨈 raw'!$A:$AAQ, MATCH(R$3, 'Weekly 쨈 raw'!$A:$A, 0), MATCH($A5, 'Weekly 쨈 raw'!$1:$1, 0)), 0))} | S5: {=IF(IFERROR(INDEX('Weekly 쨈 raw'!$A:$AAQ, MATCH(S$3, 'Weekly 쨈 raw'!$A:$A, 0), MATCH($A5, 'Weekly 쨈 raw'!$1:$1, 0)), 0)=0, "", IFERROR(INDEX('Weekly 쨈 raw'!$A:$AAQ, MATCH(S$3, 'Weekly 쨈 raw'!$A:$A, 0), MATCH($A5, 'Weekly 쨈 raw'!$1:$1, 0)), 0))} | T5: {=IF(IFERROR(INDEX('Weekly 쨈 raw'!$A:$AAQ, MATCH(T$3, 'Weekly 쨈 raw'!$A:$A, 0), MATCH($A5, 'Weekly 쨈 raw'!$1:$1, 0)), 0)=0, "", IFERROR(INDEX('Weekly 쨈 raw'!$A:$AAQ, MATCH(T$3, 'Weekly 쨈 raw'!$A:$A, 0), MATCH($A5, 'Weekly 쨈 raw'!$1:$1, 0)), 0))} | U5: {=IF(IFERROR(INDEX('Weekly 쨈 raw'!$A:$AAQ, MATCH(U$3, 'Weekly 쨈 raw'!$A:$A, 0), MATCH($A5, 'Weekly 쨈 raw'!$1:$1, 0)), 0)=0, "", IFERROR(INDEX('Weekly 쨈 raw'!$A:$AAQ, MATCH(U$3, 'Weekly 쨈 raw'!$A:$A, 0), MATCH($A5, 'Weekly 쨈 raw'!$1:$1, 0)), 0))}
A6: W0_Purchase_Done_User | B6: W0 Purchase Done User | C6: {=LET(val, IFERROR(INDEX('Weekly 쨈 raw'!$A:$AAQ, MATCH(C$3, 'Weekly 쨈 raw'!$A:$A, 0), MATCH($A6, 'Weekly 쨈 raw'!$1:$1, 0)), ""), IF(val=0, "", val))} -> 415 | D6: {=LET(val, IFERROR(INDEX('Weekly 쨈 raw'!$A:$AAQ, MATCH(D$3, 'Weekly 쨈 raw'!$A:$A, 0), MATCH($A6, 'Weekly 쨈 raw'!$1:$1, 0)), ""), IF(val=0, "", val))} -> 501 | E6: {=LET(val, IFERROR(INDEX('Weekly 쨈 raw'!$A:$AAQ, MATCH(E$3, 'Weekly 쨈 raw'!$A:$A, 0), MATCH($A6, 'Weekly 쨈 raw'!$1:$1, 0)), ""), IF(val=0, "", val))} -> 351 | F6: {=LET(val, IFERROR(INDEX('Weekly 쨈 raw'!$A:$AAQ, MATCH(F$3, 'Weekly 쨈 raw'!$A:$A, 0), MATCH($A6, 'Weekly 쨈 raw'!$1:$1, 0)), ""), IF(val=0, "", val))} -> 257 | G6: {=LET(val, IFERROR(INDEX('Weekly 쨈 raw'!$A:$AAQ, MATCH(G$3, 'Weekly 쨈 raw'!$A:$A, 0), MATCH($A6, 'Weekly 쨈 raw'!$1:$1, 0)), ""), IF(val=0, "", val))} -> 811 | H6: {=LET(val, IFERROR(INDEX('Weekly 쨈 raw'!$A:$AAQ, MATCH(H$3, 'Weekly 쨈 raw'!$A:$A, 0), MATCH($A6, 'Weekly 쨈 raw'!$1:$1, 0)), ""), IF(val=0, "", val))} -> 423 | I6: {=LET(val, IFERROR(INDEX('Weekly 쨈 raw'!$A:$AAQ, MATCH(I$3, 'Weekly 쨈 raw'!$A:$A, 0), MATCH($A6, 'Weekly 쨈 raw'!$1:$1, 0)), ""), IF(val=0, "", val))} -> 232 | J6: {=LET(val, IFERROR(INDEX('Weekly 쨈 raw'!$A:$AAQ, MATCH(J$3, 'Weekly 쨈 raw'!$A:$A, 0), MATCH($A6, 'Weekly 쨈 raw'!$1:$1, 0)), ""), IF(val=0, "", val))} -> 309 | ... P6: {=LET(val, IFERROR(INDEX('Weekly 쨈 raw'!$A:$AAQ, MATCH(P$3, 'Weekly 쨈 raw'!$A:$A, 0), MATCH($A6, 'Weekly 쨈 raw'!$1:$1, 0)), ""), IF(val=0, "", val))} -> 14 | Q6: {=IF(IFERROR(INDEX('Weekly 쨈 raw'!$A:$AAQ, MATCH(Q$3, 'Weekly 쨈 raw'!$A:$A, 0), MATCH($A6, 'Weekly 쨈 raw'!$1:$1, 0)), 0)=0, "", IFERROR(INDEX('Weekly 쨈 raw'!$A:$AAQ, MATCH(Q$3, 'Weekly 쨈 raw'!$A:$A, 0), MATCH($A6, 'Weekly 쨈 raw'!$1:$1, 0)), 0))} | R6: {=IF(IFERROR(INDEX('Weekly 쨈 raw'!$A:$AAQ, MATCH(R$3, 'Weekly 쨈 raw'!$A:$A, 0), MATCH($A6, 'Weekly 쨈 raw'!$1:$1, 0)), 0)=0, "", IFERROR(INDEX('Weekly 쨈 raw'!$A:$AAQ, MATCH(R$3, 'Weekly 쨈 raw'!$A:$A, 0), MATCH($A6, 'Weekly 쨈 raw'!$1:$1, 0)), 0))} | S6: {=IF(IFERROR(INDEX('Weekly 쨈 raw'!$A:$AAQ, MATCH(S$3, 'Weekly 쨈 raw'!$A:$A, 0), MATCH($A6, 'Weekly 쨈 raw'!$1:$1, 0)), 0)=0, "", IFERROR(INDEX('Weekly 쨈 raw'!$A:$AAQ, MATCH(S$3, 'Weekly 쨈 raw'!$A:$A, 0), MATCH($A6, 'Weekly 쨈 raw'!$1:$1, 0)), 0))} | T6: {=IF(IFERROR(INDEX('Weekly 쨈 raw'!$A:$AAQ, MATCH(T$3, 'Weekly 쨈 raw'!$A:$A, 0), MATCH($A6, 'Weekly 쨈 raw'!$1:$1, 0)), 0)=0, "", IFERROR(INDEX('Weekly 쨈 raw'!$A:$AAQ, MATCH(T$3, 'Weekly 쨈 raw'!$A:$A, 0), MATCH($A6, 'Weekly 쨈 raw'!$1:$1, 0)), 0))} | U6: {=IF(IFERROR(INDEX('Weekly 쨈 raw'!$A:$AAQ, MATCH(U$3, 'Weekly 쨈 raw'!$A:$A, 0), MATCH($A6, 'Weekly 쨈 raw'!$1:$1, 0)), 0)=0, "", IFERROR(INDEX('Weekly 쨈 raw'!$A:$AAQ, MATCH(U$3, 'Weekly 쨈 raw'!$A:$A, 0), MATCH($A6, 'Weekly 쨈 raw'!$1:$1, 0)), 0))}
A7: CVR | B7: CVR | C7: {=LET(val, IFERROR(INDEX('Weekly 쨈 raw'!$A:$AAQ, MATCH(C$3, 'Weekly 쨈 raw'!$A:$A, 0), MATCH($A7, 'Weekly 쨈 raw'!$1:$1, 0)), ""), IF(val=0, "", val))} -> 0.041466827 | D7: {=LET(val, IFERROR(INDEX('Weekly 쨈 raw'!$A:$AAQ, MATCH(D$3, 'Weekly 쨈 raw'!$A:$A, 0), MATCH($A7, 'Weekly 쨈 raw'!$1:$1, 0)), ""), IF(val=0, "", val))} -> 0.11791237 | E7: {=LET(val, IFERROR(INDEX('Weekly 쨈 raw'!$A:$AAQ, MATCH(E$3, 'Weekly 쨈 raw'!$A:$A, 0), MATCH($A7, 'Weekly 쨈 raw'!$1:$1, 0)), ""), IF(val=0, "", val))} -> 0.12939002 | F7: {=LET(val, IFERROR(INDEX('Weekly 쨈 raw'!$A:$AAQ, MATCH(F$3, 'Weekly 쨈 raw'!$A:$A, 0), MATCH($A7, 'Weekly 쨈 raw'!$1:$1, 0)), ""), IF(val=0, "", val))} -> 0.13064397 | G7: {=LET(val, IFERROR(INDEX('Weekly 쨈 raw'!$A:$AAQ, MATCH(G$3, 'Weekly 쨈 raw'!$A:$A, 0), MATCH($A7, 'Weekly 쨈 raw'!$1:$1, 0)), ""), IF(val=0, "", val))} -> 0.20495646 | H7: {=LET(val, IFERROR(INDEX('Weekly 쨈 raw'!$A:$AAQ, MATCH(H$3, 'Weekly 쨈 raw'!$A:$A, 0), MATCH($A7, 'Weekly 쨈 raw'!$1:$1, 0)), ""), IF(val=0, "", val))} -> 0.144177 | I7: {=LET(val, IFERROR(INDEX('Weekly 쨈 raw'!$A:$AAQ, MATCH(I$3, 'Weekly 쨈 raw'!$A:$A, 0), MATCH($A7, 'Weekly 쨈 raw'!$1:$1, 0)), ""), IF(val=0, "", val))} -> 0.11436856 | J7: {=LET(val, IFERROR(INDEX('Weekly 쨈 raw'!$A:$AAQ, MATCH(J$3, 'Weekly 쨈 raw'!$A:$A, 0), MATCH($A7, 'Weekly 쨈 raw'!$1:$1, 0)), ""), IF(val=0, "", val))} -> 0.15576782 | ... P7: {=LET(val, IFERROR(INDEX('Weekly 쨈 raw'!$A:$AAQ, MATCH(P$3, 'Weekly 쨈 raw'!$A:$A, 0), MATCH($A7, 'Weekly 쨈 raw'!$1:$1, 0)), ""), IF(val=0, "", val))} -> 0.06684492 | Q7: {=IF(IFERROR(INDEX('Weekly 쨈 raw'!$A:$AAQ, MATCH(Q$3, 'Weekly 쨈 raw'!$A:$A, 0), MATCH($A7, 'Weekly 쨈 raw'!$1:$1, 0)), 0)=0, "", IFERROR(INDEX('Weekly 쨈 raw'!$A:$AAQ, MATCH(Q$3, 'Weekly 쨈 raw'!$A:$A, 0), MATCH($A7, 'Weekly 쨈 raw'!$1:$1, 0)), 0))} | R7: {=IF(IFERROR(INDEX('Weekly 쨈 raw'!$A:$AAQ, MATCH(R$3, 'Weekly 쨈 raw'!$A:$A, 0), MATCH($A7, 'Weekly 쨈 raw'!$1:$1, 0)), 0)=0, "", IFERROR(INDEX('Weekly 쨈 raw'!$A:$AAQ, MATCH(R$3, 'Weekly 쨈 raw'!$A:$A, 0), MATCH($A7, 'Weekly 쨈 raw'!$1:$1, 0)), 0))} | S7: {=IF(IFERROR(INDEX('Weekly 쨈 raw'!$A:$AAQ, MATCH(S$3, 'Weekly 쨈 raw'!$A:$A, 0), MATCH($A7, 'Weekly 쨈 raw'!$1:$1, 0)), 0)=0, "", IFERROR(INDEX('Weekly 쨈 raw'!$A:$AAQ, MATCH(S$3, 'Weekly 쨈 raw'!$A:$A, 0), MATCH($A7, 'Weekly 쨈 raw'!$1:$1, 0)), 0))} | T7: {=IF(IFERROR(INDEX('Weekly 쨈 raw'!$A:$AAQ, MATCH(T$3, 'Weekly 쨈 raw'!$A:$A, 0), MATCH($A7, 'Weekly 쨈 raw'!$1:$1, 0)), 0)=0, "", IFERROR(INDEX('Weekly 쨈 raw'!$A:$AAQ, MATCH(T$3, 'Weekly 쨈 raw'!$A:$A, 0), MATCH($A7, 'Weekly 쨈 raw'!$1:$1, 0)), 0))} | U7: {=IF(IFERROR(INDEX('Weekly 쨈 raw'!$A:$AAQ, MATCH(U$3, 'Weekly 쨈 raw'!$A:$A, 0), MATCH($A7, 'Weekly 쨈 raw'!$1:$1, 0)), 0)=0, "", IFERROR(INDEX('Weekly 쨈 raw'!$A:$AAQ, MATCH(U$3, 'Weekly 쨈 raw'!$A:$A, 0), MATCH($A7, 'Weekly 쨈 raw'!$1:$1, 0)), 0))}
A8: Purchase_Done_User_CVR | B8: Purchase Done User | C8: {=LET(val, IFERROR(INDEX('Weekly 쨈 raw'!$A:$AAQ, MATCH(C$3, 'Weekly 쨈 raw'!$A:$A, 0), MATCH($A8, 'Weekly 쨈 raw'!$1:$1, 0)), ""), IF(val=0, "", val))} -> 415 | D8: {=LET(val, IFERROR(INDEX('Weekly 쨈 raw'!$A:$AAQ, MATCH(D$3, 'Weekly 쨈 raw'!$A:$A, 0), MATCH($A8, 'Weekly 쨈 raw'!$1:$1, 0)), ""), IF(val=0, "", val))} -> 549 | E8: {=LET(val, IFERROR(INDEX('Weekly 쨈 raw'!$A:$AAQ, MATCH(E$3, 'Weekly 쨈 raw'!$A:$A, 0), MATCH($A8, 'Weekly 쨈 raw'!$1:$1, 0)), ""), IF(val=0, "", val))} -> 420 | F8: {=LET(val, IFERROR(INDEX('Weekly 쨈 raw'!$A:$AAQ, MATCH(F$3, 'Weekly 쨈 raw'!$A:$A, 0), MATCH($A8, 'Weekly 쨈 raw'!$1:$1, 0)), ""), IF(val=0, "", val))} -> 353 | G8: {=LET(val, IFERROR(INDEX('Weekly 쨈 raw'!$A:$AAQ, MATCH(G$3, 'Weekly 쨈 raw'!$A:$A, 0), MATCH($A8, 'Weekly 쨈 raw'!$1:$1, 0)), ""), IF(val=0, "", val))} -> 918 | H8: {=LET(val, IFERROR(INDEX('Weekly 쨈 raw'!$A:$AAQ, MATCH(H$3, 'Weekly 쨈 raw'!$A:$A, 0), MATCH($A8, 'Weekly 쨈 raw'!$1:$1, 0)), ""), IF(val=0, "", val))} -> 593 | I8: {=LET(val, IFERROR(INDEX('Weekly 쨈 raw'!$A:$AAQ, MATCH(I$3, 'Weekly 쨈 raw'!$A:$A, 0), MATCH($A8, 'Weekly 쨈 raw'!$1:$1, 0)), ""), IF(val=0, "", val))} -> 355 | J8: {=LET(val, IFERROR(INDEX('Weekly 쨈 raw'!$A:$AAQ, MATCH(J$3, 'Weekly 쨈 raw'!$A:$A, 0), MATCH($A8, 'Weekly 쨈 raw'!$1:$1, 0)), ""), IF(val=0, "", val))} -> 424 | ... P8: {=LET(val, IFERROR(INDEX('Weekly 쨈 raw'!$A:$AAQ, MATCH(P$3, 'Weekly 쨈 raw'!$A:$A, 0), MATCH($A8, 'Weekly 쨈 raw'!$1:$1, 0)), ""), IF(val=0, "", val))} -> 25 | Q8: {=IF(IFERROR(INDEX('Weekly 쨈 raw'!$A:$AAQ, MATCH(Q$3, 'Weekly 쨈 raw'!$A:$A, 0), MATCH($A8, 'Weekly 쨈 raw'!$1:$1, 0)), 0)=0, "", IFERROR(INDEX('Weekly 쨈 raw'!$A:$AAQ, MATCH(Q$3, 'Weekly 쨈 raw'!$A:$A, 0), MATCH($A8, 'Weekly 쨈 raw'!$1:$1, 0)), 0))} | R8: {=IF(IFERROR(INDEX('Weekly 쨈 raw'!$A:$AAQ, MATCH(R$3, 'Weekly 쨈 raw'!$A:$A, 0), MATCH($A8, 'Weekly 쨈 raw'!$1:$1, 0)), 0)=0, "", IFERROR(INDEX('Weekly 쨈 raw'!$A:$AAQ, MATCH(R$3, 'Weekly 쨈 raw'!$A:$A, 0), MATCH($A8, 'Weekly 쨈 raw'!$1:$1, 0)), 0))} | S8: {=IF(IFERROR(INDEX('Weekly 쨈 raw'!$A:$AAQ, MATCH(S$3, 'Weekly 쨈 raw'!$A:$A, 0), MATCH($A8, 'Weekly 쨈 raw'!$1:$1, 0)), 0)=0, "", IFERROR(INDEX('Weekly 쨈 raw'!$A:$AAQ, MATCH(S$3, 'Weekly 쨈 raw'!$A:$A, 0), MATCH($A8, 'Weekly 쨈 raw'!$1:$1, 0)), 0))} | T8: {=IF(IFERROR(INDEX('Weekly 쨈 raw'!$A:$AAQ, MATCH(T$3, 'Weekly 쨈 raw'!$A:$A, 0), MATCH($A8, 'Weekly 쨈 raw'!$1:$1, 0)), 0)=0, "", IFERROR(INDEX('Weekly 쨈 raw'!$A:$AAQ, MATCH(T$3, 'Weekly 쨈 raw'!$A:$A, 0), MATCH($A8, 'Weekly 쨈 raw'!$1:$1, 0)), 0))} | U8: {=IF(IFERROR(INDEX('Weekly 쨈 raw'!$A:$AAQ, MATCH(U$3, 'Weekly 쨈 raw'!$A:$A, 0), MATCH($A8, 'Weekly 쨈 raw'!$1:$1, 0)), 0)=0, "", IFERROR(INDEX('Weekly 쨈 raw'!$A:$AAQ, MATCH(U$3, 'Weekly 쨈 raw'!$A:$A, 0), MATCH($A8, 'Weekly 쨈 raw'!$1:$1, 0)), 0))}
A9: Gen_Done_User | B9: Gen Done User | C9: {=LET(val, IFERROR(INDEX('Weekly 쨈 raw'!$A:$AAQ, MATCH(C$3, 'Weekly 쨈 raw'!$A:$A, 0), MATCH($A9, 'Weekly 쨈 raw'!$1:$1, 0)), ""), IF(val=0, "", val))} -> 10008 | D9: {=LET(val, IFERROR(INDEX('Weekly 쨈 raw'!$A:$AAQ, MATCH(D$3, 'Weekly 쨈 raw'!$A:$A, 0), MATCH($A9, 'Weekly 쨈 raw'!$1:$1, 0)), ""), IF(val=0, "", val))} -> 4656 | E9: {=LET(val, IFERROR(INDEX('Weekly 쨈 raw'!$A:$AAQ, MATCH(E$3, 'Weekly 쨈 raw'!$A:$A, 0), MATCH($A9, 'Weekly 쨈 raw'!$1:$1, 0)), ""), IF(val=0, "", val))} -> 3246 | F9: {=LET(val, IFERROR(INDEX('Weekly 쨈 raw'!$A:$AAQ, MATCH(F$3, 'Weekly 쨈 raw'!$A:$A, 0), MATCH($A9, 'Weekly 쨈 raw'!$1:$1, 0)), ""), IF(val=0, "", val))} -> 2702 | G9: {=LET(val, IFERROR(INDEX('Weekly 쨈 raw'!$A:$AAQ, MATCH(G$3, 'Weekly 쨈 raw'!$A:$A, 0), MATCH($A9, 'Weekly 쨈 raw'!$1:$1, 0)), ""), IF(val=0, "", val))} -> 4479 | H9: {=LET(val, IFERROR(INDEX('Weekly 쨈 raw'!$A:$AAQ, MATCH(H$3, 'Weekly 쨈 raw'!$A:$A, 0), MATCH($A9, 'Weekly 쨈 raw'!$1:$1, 0)), ""), IF(val=0, "", val))} -> 4113 | I9: {=LET(val, IFERROR(INDEX('Weekly 쨈 raw'!$A:$AAQ, MATCH(I$3, 'Weekly 쨈 raw'!$A:$A, 0), MATCH($A9, 'Weekly 쨈 raw'!$1:$1, 0)), ""), IF(val=0, "", val))} -> 3104 | J9: {=LET(val, IFERROR(INDEX('Weekly 쨈 raw'!$A:$AAQ, MATCH(J$3, 'Weekly 쨈 raw'!$A:$A, 0), MATCH($A9, 'Weekly 쨈 raw'!$1:$1, 0)), ""), IF(val=0, "", val))} -> 2722 | ... P9: {=LET(val, IFERROR(INDEX('Weekly 쨈 raw'!$A:$AAQ, MATCH(P$3, 'Weekly 쨈 raw'!$A:$A, 0), MATCH($A9, 'Weekly 쨈 raw'!$1:$1, 0)), ""), IF(val=0, "", val))} -> 374 | Q9: {=IF(IFERROR(INDEX('Weekly 쨈 raw'!$A:$AAQ, MATCH(Q$3, 'Weekly 쨈 raw'!$A:$A, 0), MATCH($A9, 'Weekly 쨈 raw'!$1:$1, 0)), 0)=0, "", IFERROR(INDEX('Weekly 쨈 raw'!$A:$AAQ, MATCH(Q$3, 'Weekly 쨈 raw'!$A:$A, 0), MATCH($A9, 'Weekly 쨈 raw'!$1:$1, 0)), 0))} | R9: {=IF(IFERROR(INDEX('Weekly 쨈 raw'!$A:$AAQ, MATCH(R$3, 'Weekly 쨈 raw'!$A:$A, 0), MATCH($A9, 'Weekly 쨈 raw'!$1:$1, 0)), 0)=0, "", IFERROR(INDEX('Weekly 쨈 raw'!$A:$AAQ, MATCH(R$3, 'Weekly 쨈 raw'!$A:$A, 0), MATCH($A9, 'Weekly 쨈 raw'!$1:$1, 0)), 0))} | S9: {=IF(IFERROR(INDEX('Weekly 쨈 raw'!$A:$AAQ, MATCH(S$3, 'Weekly 쨈 raw'!$A:$A, 0), MATCH($A9, 'Weekly 쨈 raw'!$1:$1, 0)), 0)=0, "", IFERROR(INDEX('Weekly 쨈 raw'!$A:$AAQ, MATCH(S$3, 'Weekly 쨈 raw'!$A:$A, 0), MATCH($A9, 'Weekly 쨈 raw'!$1:$1, 0)), 0))} | T9: {=IF(IFERROR(INDEX('Weekly 쨈 raw'!$A:$AAQ, MATCH(T$3, 'Weekly 쨈 raw'!$A:$A, 0), MATCH($A9, 'Weekly 쨈 raw'!$1:$1, 0)), 0)=0, "", IFERROR(INDEX('Weekly 쨈 raw'!$A:$AAQ, MATCH(T$3, 'Weekly 쨈 raw'!$A:$A, 0), MATCH($A9, 'Weekly 쨈 raw'!$1:$1, 0)), 0))} | U9: {=IF(IFERROR(INDEX('Weekly 쨈 raw'!$A:$AAQ, MATCH(U$3, 'Weekly 쨈 raw'!$A:$A, 0), MATCH($A9, 'Weekly 쨈 raw'!$1:$1, 0)), 0)=0, "", IFERROR(INDEX('Weekly 쨈 raw'!$A:$AAQ, MATCH(U$3, 'Weekly 쨈 raw'!$A:$A, 0), MATCH($A9, 'Weekly 쨈 raw'!$1:$1, 0)), 0))}
A10: Filter_Gen_Done_User | B10: ㄴ 필터 생성 유저 | C10: {=LET(val, IFERROR(INDEX('Weekly 쨈 raw'!$A:$AAQ, MATCH(C$3, 'Weekly 쨈 raw'!$A:$A, 0), MATCH($A10, 'Weekly 쨈 raw'!$1:$1, 0)), ""), IF(val=0, "", val))} -> 10008 | D10: {=LET(val, IFERROR(INDEX('Weekly 쨈 raw'!$A:$AAQ, MATCH(D$3, 'Weekly 쨈 raw'!$A:$A, 0), MATCH($A10, 'Weekly 쨈 raw'!$1:$1, 0)), ""), IF(val=0, "", val))} -> 4656 | E10: {=LET(val, IFERROR(INDEX('Weekly 쨈 raw'!$A:$AAQ, MATCH(E$3, 'Weekly 쨈 raw'!$A:$A, 0), MATCH($A10, 'Weekly 쨈 raw'!$1:$1, 0)), ""), IF(val=0, "", val))} -> 3246 | F10: {=LET(val, IFERROR(INDEX('Weekly 쨈 raw'!$A:$AAQ, MATCH(F$3, 'Weekly 쨈 raw'!$A:$A, 0), MATCH($A10, 'Weekly 쨈 raw'!$1:$1, 0)), ""), IF(val=0, "", val))} -> 2702 | G10: {=LET(val, IFERROR(INDEX('Weekly 쨈 raw'!$A:$AAQ, MATCH(G$3, 'Weekly 쨈 raw'!$A:$A, 0), MATCH($A10, 'Weekly 쨈 raw'!$1:$1, 0)), ""), IF(val=0, "", val))} -> 4479 | H10: {=LET(val, IFERROR(INDEX('Weekly 쨈 raw'!$A:$AAQ, MATCH(H$3, 'Weekly 쨈 raw'!$A:$A, 0), MATCH($A10, 'Weekly 쨈 raw'!$1:$1, 0)), ""), IF(val=0, "", val))} -> 4113 | I10: {=LET(val, IFERROR(INDEX('Weekly 쨈 raw'!$A:$AAQ, MATCH(I$3, 'Weekly 쨈 raw'!$A:$A, 0), MATCH($A10, 'Weekly 쨈 raw'!$1:$1, 0)), ""), IF(val=0, "", val))} -> 3104 | J10: {=LET(val, IFERROR(INDEX('Weekly 쨈 raw'!$A:$AAQ, MATCH(J$3, 'Weekly 쨈 raw'!$A:$A, 0), MATCH($A10, 'Weekly 쨈 raw'!$1:$1, 0)), ""), IF(val=0, "", val))} -> 2722 | ... U10: {=LET(val, IFERROR(INDEX('Weekly 쨈 raw'!$A:$AAQ, MATCH(U$3, 'Weekly 쨈 raw'!$A:$A, 0), MATCH($A10, 'Weekly 쨈 raw'!$1:$1, 0)), ""), IF(val=0, "", val))}
A11: Custom_Prompt_Gen_Done_User | B11: ㄴ 커스텀 프롬프트 생성 유저 | C11: {=LET(val, IFERROR(INDEX('Weekly 쨈 raw'!$A:$AAQ, MATCH(C$3, 'Weekly 쨈 raw'!$A:$A, 0), MATCH($A11, 'Weekly 쨈 raw'!$1:$1, 0)), ""), IF(val=0, "", val))} | D11: {=LET(val, IFERROR(INDEX('Weekly 쨈 raw'!$A:$AAQ, MATCH(D$3, 'Weekly 쨈 raw'!$A:$A, 0), MATCH($A11, 'Weekly 쨈 raw'!$1:$1, 0)), ""), IF(val=0, "", val))} | E11: {=LET(val, IFERROR(INDEX('Weekly 쨈 raw'!$A:$AAQ, MATCH(E$3, 'Weekly 쨈 raw'!$A:$A, 0), MATCH($A11, 'Weekly 쨈 raw'!$1:$1, 0)), ""), IF(val=0, "", val))} | F11: {=LET(val, IFERROR(INDEX('Weekly 쨈 raw'!$A:$AAQ, MATCH(F$3, 'Weekly 쨈 raw'!$A:$A, 0), MATCH($A11, 'Weekly 쨈 raw'!$1:$1, 0)), ""), IF(val=0, "", val))} | G11: {=LET(val, IFERROR(INDEX('Weekly 쨈 raw'!$A:$AAQ, MATCH(G$3, 'Weekly 쨈 raw'!$A:$A, 0), MATCH($A11, 'Weekly 쨈 raw'!$1:$1, 0)), ""), IF(val=0, "", val))} | H11: {=LET(val, IFERROR(INDEX('Weekly 쨈 raw'!$A:$AAQ, MATCH(H$3, 'Weekly 쨈 raw'!$A:$A, 0), MATCH($A11, 'Weekly 쨈 raw'!$1:$1, 0)), ""), IF(val=0, "", val))} | I11: {=LET(val, IFERROR(INDEX('Weekly 쨈 raw'!$A:$AAQ, MATCH(I$3, 'Weekly 쨈 raw'!$A:$A, 0), MATCH($A11, 'Weekly 쨈 raw'!$1:$1, 0)), ""), IF(val=0, "", val))} | J11: {=LET(val, IFERROR(INDEX('Weekly 쨈 raw'!$A:$AAQ, MATCH(J$3, 'Weekly 쨈 raw'!$A:$A, 0), MATCH($A11, 'Weekly 쨈 raw'!$1:$1, 0)), ""), IF(val=0, "", val))} | ... U11: {=LET(val, IFERROR(INDEX('Weekly 쨈 raw'!$A:$AAQ, MATCH(U$3, 'Weekly 쨈 raw'!$A:$A, 0), MATCH($A11, 'Weekly 쨈 raw'!$1:$1, 0)), ""), IF(val=0, "", val))}
B12: ㄴ 커스텀 프롬프트 생성 유저 비율 | M12: =M11/M9 -> 0.038461538 | N12: =N11/N9 -> 0.1748286 | O12: =O11/O9 -> 0.14828897 | P12: =P11/P9 -> 0.072192513 | Q12: =iferror(Q11/Q9, "") | R12: =iferror(R11/R9, "") | S12: =iferror(S11/S9, "") | T12: =iferror(T11/T9, "") | U12: =iferror(U11/U9, "")
A13: Gen_Done_Count | B13: Gen Done Count | C13: {=LET(val, IFERROR(INDEX('Weekly 쨈 raw'!$A:$AAQ, MATCH(C$3, 'Weekly 쨈 raw'!$A:$A, 0), MATCH($A13, 'Weekly 쨈 raw'!$1:$1, 0)), ""), IF(val=0, "", val))} -> 29740 | D13: {=LET(val, IFERROR(INDEX('Weekly 쨈 raw'!$A:$AAQ, MATCH(D$3, 'Weekly 쨈 raw'!$A:$A, 0), MATCH($A13, 'Weekly 쨈 raw'!$1:$1, 0)), ""), IF(val=0, "", val))} -> 19960 | E13: {=LET(val, IFERROR(INDEX('Weekly 쨈 raw'!$A:$AAQ, MATCH(E$3, 'Weekly 쨈 raw'!$A:$A, 0), MATCH($A13, 'Weekly 쨈 raw'!$1:$1, 0)), ""), IF(val=0, "", val))} -> 15695 | F13: {=LET(val, IFERROR(INDEX('Weekly 쨈 raw'!$A:$AAQ, MATCH(F$3, 'Weekly 쨈 raw'!$A:$A, 0), MATCH($A13, 'Weekly 쨈 raw'!$1:$1, 0)), ""), IF(val=0, "", val))} -> 10949 | G13: {=LET(val, IFERROR(INDEX('Weekly 쨈 raw'!$A:$AAQ, MATCH(G$3, 'Weekly 쨈 raw'!$A:$A, 0), MATCH($A13, 'Weekly 쨈 raw'!$1:$1, 0)), ""), IF(val=0, "", val))} -> 14924 | H13: {=LET(val, IFERROR(INDEX('Weekly 쨈 raw'!$A:$AAQ, MATCH(H$3, 'Weekly 쨈 raw'!$A:$A, 0), MATCH($A13, 'Weekly 쨈 raw'!$1:$1, 0)), ""), IF(val=0, "", val))} -> 12910 | I13: {=LET(val, IFERROR(INDEX('Weekly 쨈 raw'!$A:$AAQ, MATCH(I$3, 'Weekly 쨈 raw'!$A:$A, 0), MATCH($A13, 'Weekly 쨈 raw'!$1:$1, 0)), ""), IF(val=0, "", val))} -> 9204 | J13: {=LET(val, IFERROR(INDEX('Weekly 쨈 raw'!$A:$AAQ, MATCH(J$3, 'Weekly 쨈 raw'!$A:$A, 0), MATCH($A13, 'Weekly 쨈 raw'!$1:$1, 0)), ""), IF(val=0, "", val))} -> 7448 | ... U13: {=LET(val, IFERROR(INDEX('Weekly 쨈 raw'!$A:$AAQ, MATCH(U$3, 'Weekly 쨈 raw'!$A:$A, 0), MATCH($A13, 'Weekly 쨈 raw'!$1:$1, 0)), ""), IF(val=0, "", val))}
A14: Filter_Gen_Done_Count | B14: ㄴ 필터 생성 건수 | C14: {=LET(val, IFERROR(INDEX('Weekly 쨈 raw'!$A:$AAQ, MATCH(C$3, 'Weekly 쨈 raw'!$A:$A, 0), MATCH($A14, 'Weekly 쨈 raw'!$1:$1, 0)), ""), IF(val=0, "", val))} -> 29740 | D14: {=LET(val, IFERROR(INDEX('Weekly 쨈 raw'!$A:$AAQ, MATCH(D$3, 'Weekly 쨈 raw'!$A:$A, 0), MATCH($A14, 'Weekly 쨈 raw'!$1:$1, 0)), ""), IF(val=0, "", val))} -> 19960 | E14: {=LET(val, IFERROR(INDEX('Weekly 쨈 raw'!$A:$AAQ, MATCH(E$3, 'Weekly 쨈 raw'!$A:$A, 0), MATCH($A14, 'Weekly 쨈 raw'!$1:$1, 0)), ""), IF(val=0, "", val))} -> 15695 | F14: {=LET(val, IFERROR(INDEX('Weekly 쨈 raw'!$A:$AAQ, MATCH(F$3, 'Weekly 쨈 raw'!$A:$A, 0), MATCH($A14, 'Weekly 쨈 raw'!$1:$1, 0)), ""), IF(val=0, "", val))} -> 10949 | G14: {=LET(val, IFERROR(INDEX('Weekly 쨈 raw'!$A:$AAQ, MATCH(G$3, 'Weekly 쨈 raw'!$A:$A, 0), MATCH($A14, 'Weekly 쨈 raw'!$1:$1, 0)), ""), IF(val=0, "", val))} -> 14924 | H14: {=LET(val, IFERROR(INDEX('Weekly 쨈 raw'!$A:$AAQ, MATCH(H$3, 'Weekly 쨈 raw'!$A:$A, 0), MATCH($A14, 'Weekly 쨈 raw'!$1:$1, 0)), ""), IF(val=0, "", val))} -> 12910 | I14: {=LET(val, IFERROR(INDEX('Weekly 쨈 raw'!$A:$AAQ, MATCH(I$3, 'Weekly 쨈 raw'!$A:$A, 0), MATCH($A14, 'Weekly 쨈 raw'!$1:$1, 0)), ""), IF(val=0, "", val))} -> 9204 | J14: {=LET(val, IFERROR(INDEX('Weekly 쨈 raw'!$A:$AAQ, MATCH(J$3, 'Weekly 쨈 raw'!$A:$A, 0), MATCH($A14, 'Weekly 쨈 raw'!$1:$1, 0)), ""), IF(val=0, "", val))} -> 7448 | ... U14: {=LET(val, IFERROR(INDEX('Weekly 쨈 raw'!$A:$AAQ, MATCH(U$3, 'Weekly 쨈 raw'!$A:$A, 0), MATCH($A14, 'Weekly 쨈 raw'!$1:$1, 0)), ""), IF(val=0, "", val))}
A15: Custom_Prompt_Gen_Done_Count | B15: ㄴ 커스텀 프롬프트 생성 건수 | C15: {=LET(val, IFERROR(INDEX('Weekly 쨈 raw'!$A:$AAQ, MATCH(C$3, 'Weekly 쨈 raw'!$A:$A, 0), MATCH($A15, 'Weekly 쨈 raw'!$1:$1, 0)), ""), IF(val=0, "", val))} | D15: {=LET(val, IFERROR(INDEX('Weekly 쨈 raw'!$A:$AAQ, MATCH(D$3, 'Weekly 쨈 raw'!$A:$A, 0), MATCH($A15, 'Weekly 쨈 raw'!$1:$1, 0)), ""), IF(val=0, "", val))} | E15: {=LET(val, IFERROR(INDEX('Weekly 쨈 raw'!$A:$AAQ, MATCH(E$3, 'Weekly 쨈 raw'!$A:$A, 0), MATCH($A15, 'Weekly 쨈 raw'!$1:$1, 0)), ""), IF(val=0, "", val))} | F15: {=LET(val, IFERROR(INDEX('Weekly 쨈 raw'!$A:$AAQ, MATCH(F$3, 'Weekly 쨈 raw'!$A:$A, 0), MATCH($A15, 'Weekly 쨈 raw'!$1:$1, 0)), ""), IF(val=0, "", val))} | G15: {=LET(val, IFERROR(INDEX('Weekly 쨈 raw'!$A:$AAQ, MATCH(G$3, 'Weekly 쨈 raw'!$A:$A, 0), MATCH($A15, 'Weekly 쨈 raw'!$1:$1, 0)), ""), IF(val=0, "", val))} | H15: {=LET(val, IFERROR(INDEX('Weekly 쨈 raw'!$A:$AAQ, MATCH(H$3, 'Weekly 쨈 raw'!$A:$A, 0), MATCH($A15, 'Weekly 쨈 raw'!$1:$1, 0)), ""), IF(val=0, "", val))} | I15: {=LET(val, IFERROR(INDEX('Weekly 쨈 raw'!$A:$AAQ, MATCH(I$3, 'Weekly 쨈 raw'!$A:$A, 0), MATCH($A15, 'Weekly 쨈 raw'!$1:$1, 0)), ""), IF(val=0, "", val))} | J15: {=LET(val, IFERROR(INDEX('Weekly 쨈 raw'!$A:$AAQ, MATCH(J$3, 'Weekly 쨈 raw'!$A:$A, 0), MATCH($A15, 'Weekly 쨈 raw'!$1:$1, 0)), ""), IF(val=0, "", val))} | ... U15: {=LET(val, IFERROR(INDEX('Weekly 쨈 raw'!$A:$AAQ, MATCH(U$3, 'Weekly 쨈 raw'!$A:$A, 0), MATCH($A15, 'Weekly 쨈 raw'!$1:$1, 0)), ""), IF(val=0, "", val))}
B16: ㄴ 커스텀 프롬프트 생성 건수 비율 | M16: =M15/M13 -> 0.035659705 | N16: =N15/N13 -> 0.14381703 | O16: =O15/O13 -> 0.11026701 | P16: =P15/P13 -> 0.082489146
A17: Gen_Done_Count_Per_User | B17: 생성 유저 당 생성 건수 | C17: {=LET(val, IFERROR(INDEX('Weekly 쨈 raw'!$A:$AAQ, MATCH(C$3, 'Weekly 쨈 raw'!$A:$A, 0), MATCH($A17, 'Weekly 쨈 raw'!$1:$1, 0)), ""), IF(val=0, "", val))} -> 2.9716227 | D17: {=LET(val, IFERROR(INDEX('Weekly 쨈 raw'!$A:$AAQ, MATCH(D$3, 'Weekly 쨈 raw'!$A:$A, 0), MATCH($A17, 'Weekly 쨈 raw'!$1:$1, 0)), ""), IF(val=0, "", val))} -> 4.2869416 | E17: {=LET(val, IFERROR(INDEX('Weekly 쨈 raw'!$A:$AAQ, MATCH(E$3, 'Weekly 쨈 raw'!$A:$A, 0), MATCH($A17, 'Weekly 쨈 raw'!$1:$1, 0)), ""), IF(val=0, "", val))} -> 4.8351818 | F17: {=LET(val, IFERROR(INDEX('Weekly 쨈 raw'!$A:$AAQ, MATCH(F$3, 'Weekly 쨈 raw'!$A:$A, 0), MATCH($A17, 'Weekly 쨈 raw'!$1:$1, 0)), ""), IF(val=0, "", val))} -> 4.0521836 | G17: {=LET(val, IFERROR(INDEX('Weekly 쨈 raw'!$A:$AAQ, MATCH(G$3, 'Weekly 쨈 raw'!$A:$A, 0), MATCH($A17, 'Weekly 쨈 raw'!$1:$1, 0)), ""), IF(val=0, "", val))} -> 3.3319937 | H17: {=LET(val, IFERROR(INDEX('Weekly 쨈 raw'!$A:$AAQ, MATCH(H$3, 'Weekly 쨈 raw'!$A:$A, 0), MATCH($A17, 'Weekly 쨈 raw'!$1:$1, 0)), ""), IF(val=0, "", val))} -> 3.1388281 | I17: {=LET(val, IFERROR(INDEX('Weekly 쨈 raw'!$A:$AAQ, MATCH(I$3, 'Weekly 쨈 raw'!$A:$A, 0), MATCH($A17, 'Weekly 쨈 raw'!$1:$1, 0)), ""), IF(val=0, "", val))} -> 2.9652062 | J17: {=LET(val, IFERROR(INDEX('Weekly 쨈 raw'!$A:$AAQ, MATCH(J$3, 'Weekly 쨈 raw'!$A:$A, 0), MATCH($A17, 'Weekly 쨈 raw'!$1:$1, 0)), ""), IF(val=0, "", val))} -> 2.7362234 | ... U17: {=LET(val, IFERROR(INDEX('Weekly 쨈 raw'!$A:$AAQ, MATCH(U$3, 'Weekly 쨈 raw'!$A:$A, 0), MATCH($A17, 'Weekly 쨈 raw'!$1:$1, 0)), ""), IF(val=0, "", val))}
A18: Filter_Gen_Done_Count_Per_User | B18: ㄴ 생성 유저 당 필터 생성 건수 | C18: {=LET(val, IFERROR(INDEX('Weekly 쨈 raw'!$A:$AAQ, MATCH(C$3, 'Weekly 쨈 raw'!$A:$A, 0), MATCH($A18, 'Weekly 쨈 raw'!$1:$1, 0)), ""), IF(val=0, "", val))} -> 2.9716227 | D18: {=LET(val, IFERROR(INDEX('Weekly 쨈 raw'!$A:$AAQ, MATCH(D$3, 'Weekly 쨈 raw'!$A:$A, 0), MATCH($A18, 'Weekly 쨈 raw'!$1:$1, 0)), ""), IF(val=0, "", val))} -> 4.2869416 | E18: {=LET(val, IFERROR(INDEX('Weekly 쨈 raw'!$A:$AAQ, MATCH(E$3, 'Weekly 쨈 raw'!$A:$A, 0), MATCH($A18, 'Weekly 쨈 raw'!$1:$1, 0)), ""), IF(val=0, "", val))} -> 4.8351818 | F18: {=LET(val, IFERROR(INDEX('Weekly 쨈 raw'!$A:$AAQ, MATCH(F$3, 'Weekly 쨈 raw'!$A:$A, 0), MATCH($A18, 'Weekly 쨈 raw'!$1:$1, 0)), ""), IF(val=0, "", val))} -> 4.0521836 | G18: {=LET(val, IFERROR(INDEX('Weekly 쨈 raw'!$A:$AAQ, MATCH(G$3, 'Weekly 쨈 raw'!$A:$A, 0), MATCH($A18, 'Weekly 쨈 raw'!$1:$1, 0)), ""), IF(val=0, "", val))} -> 3.3319937 | H18: {=LET(val, IFERROR(INDEX('Weekly 쨈 raw'!$A:$AAQ, MATCH(H$3, 'Weekly 쨈 raw'!$A:$A, 0), MATCH($A18, 'Weekly 쨈 raw'!$1:$1, 0)), ""), IF(val=0, "", val))} -> 3.1388281 | I18: {=LET(val, IFERROR(INDEX('Weekly 쨈 raw'!$A:$AAQ, MATCH(I$3, 'Weekly 쨈 raw'!$A:$A, 0), MATCH($A18, 'Weekly 쨈 raw'!$1:$1, 0)), ""), IF(val=0, "", val))} -> 2.9652062 | J18: {=LET(val, IFERROR(INDEX('Weekly 쨈 raw'!$A:$AAQ, MATCH(J$3, 'Weekly 쨈 raw'!$A:$A, 0), MATCH($A18, 'Weekly 쨈 raw'!$1:$1, 0)), ""), IF(val=0, "", val))} -> 2.7362234 | ... U18: {=LET(val, IFERROR(INDEX('Weekly 쨈 raw'!$A:$AAQ, MATCH(U$3, 'Weekly 쨈 raw'!$A:$A, 0), MATCH($A18, 'Weekly 쨈 raw'!$1:$1, 0)), ""), IF(val=0, "", val))}
A19: Custom_Prompt_Gen_Done_Count_Per_User | B19: ㄴ 생성 유저 당 커스텀 프롬프트 생성 건수 | C19: {=LET(val, IFERROR(INDEX('Weekly 쨈 raw'!$A:$AAQ, MATCH(C$3, 'Weekly 쨈 raw'!$A:$A, 0), MATCH($A19, 'Weekly 쨈 raw'!$1:$1, 0)), ""), IF(val=0, "", val))} | D19: {=LET(val, IFERROR(INDEX('Weekly 쨈 raw'!$A:$AAQ, MATCH(D$3, 'Weekly 쨈 raw'!$A:$A, 0), MATCH($A19, 'Weekly 쨈 raw'!$1:$1, 0)), ""), IF(val=0, "", val))} | E19: {=LET(val, IFERROR(INDEX('Weekly 쨈 raw'!$A:$AAQ, MATCH(E$3, 'Weekly 쨈 raw'!$A:$A, 0), MATCH($A19, 'Weekly 쨈 raw'!$1:$1, 0)), ""), IF(val=0, "", val))} | F19: {=LET(val, IFERROR(INDEX('Weekly 쨈 raw'!$A:$AAQ, MATCH(F$3, 'Weekly 쨈 raw'!$A:$A, 0), MATCH($A19, 'Weekly 쨈 raw'!$1:$1, 0)), ""), IF(val=0, "", val))} | G19: {=LET(val, IFERROR(INDEX('Weekly 쨈 raw'!$A:$AAQ, MATCH(G$3, 'Weekly 쨈 raw'!$A:$A, 0), MATCH($A19, 'Weekly 쨈 raw'!$1:$1, 0)), ""), IF(val=0, "", val))} | H19: {=LET(val, IFERROR(INDEX('Weekly 쨈 raw'!$A:$AAQ, MATCH(H$3, 'Weekly 쨈 raw'!$A:$A, 0), MATCH($A19, 'Weekly 쨈 raw'!$1:$1, 0)), ""), IF(val=0, "", val))} | I19: {=LET(val, IFERROR(INDEX('Weekly 쨈 raw'!$A:$AAQ, MATCH(I$3, 'Weekly 쨈 raw'!$A:$A, 0), MATCH($A19, 'Weekly 쨈 raw'!$1:$1, 0)), ""), IF(val=0, "", val))} | J19: {=LET(val, IFERROR(INDEX('Weekly 쨈 raw'!$A:$AAQ, MATCH(J$3, 'Weekly 쨈 raw'!$A:$A, 0), MATCH($A19, 'Weekly 쨈 raw'!$1:$1, 0)), ""), IF(val=0, "", val))} | ... U19: {=LET(val, IFERROR(INDEX('Weekly 쨈 raw'!$A:$AAQ, MATCH(U$3, 'Weekly 쨈 raw'!$A:$A, 0), MATCH($A19, 'Weekly 쨈 raw'!$1:$1, 0)), ""), IF(val=0, "", val))}
A20: ARPPU | B20: ARPPU | C20: {=LET(val, IFERROR(INDEX('Weekly 쨈 raw'!$A:$AAQ, MATCH(C$3, 'Weekly 쨈 raw'!$A:$A, 0), MATCH($A20, 'Weekly 쨈 raw'!$1:$1, 0)), ""), IF(val=0, "", val))} -> 6674.2169 | D20: {=LET(val, IFERROR(INDEX('Weekly 쨈 raw'!$A:$AAQ, MATCH(D$3, 'Weekly 쨈 raw'!$A:$A, 0), MATCH($A20, 'Weekly 쨈 raw'!$1:$1, 0)), ""), IF(val=0, "", val))} -> 6816.3934 | E20: {=LET(val, IFERROR(INDEX('Weekly 쨈 raw'!$A:$AAQ, MATCH(E$3, 'Weekly 쨈 raw'!$A:$A, 0), MATCH($A20, 'Weekly 쨈 raw'!$1:$1, 0)), ""), IF(val=0, "", val))} -> 6178.3333 | F20: {=LET(val, IFERROR(INDEX('Weekly 쨈 raw'!$A:$AAQ, MATCH(F$3, 'Weekly 쨈 raw'!$A:$A, 0), MATCH($A20, 'Weekly 쨈 raw'!$1:$1, 0)), ""), IF(val=0, "", val))} -> 6671.6714 | G20: {=LET(val, IFERROR(INDEX('Weekly 쨈 raw'!$A:$AAQ, MATCH(G$3, 'Weekly 쨈 raw'!$A:$A, 0), MATCH($A20, 'Weekly 쨈 raw'!$1:$1, 0)), ""), IF(val=0, "", val))} -> 7648.4749 | H20: {=LET(val, IFERROR(INDEX('Weekly 쨈 raw'!$A:$AAQ, MATCH(H$3, 'Weekly 쨈 raw'!$A:$A, 0), MATCH($A20, 'Weekly 쨈 raw'!$1:$1, 0)), ""), IF(val=0, "", val))} -> 7781.6189 | I20: {=LET(val, IFERROR(INDEX('Weekly 쨈 raw'!$A:$AAQ, MATCH(I$3, 'Weekly 쨈 raw'!$A:$A, 0), MATCH($A20, 'Weekly 쨈 raw'!$1:$1, 0)), ""), IF(val=0, "", val))} -> 7954.0845 | J20: {=LET(val, IFERROR(INDEX('Weekly 쨈 raw'!$A:$AAQ, MATCH(J$3, 'Weekly 쨈 raw'!$A:$A, 0), MATCH($A20, 'Weekly 쨈 raw'!$1:$1, 0)), ""), IF(val=0, "", val))} -> 7642.9245 | ... P20: {=LET(val, IFERROR(INDEX('Weekly 쨈 raw'!$A:$AAQ, MATCH(P$3, 'Weekly 쨈 raw'!$A:$A, 0), MATCH($A20, 'Weekly 쨈 raw'!$1:$1, 0)), ""), IF(val=0, "", val))} -> 12488 | Q20: {=IF(IFERROR(INDEX('Weekly 쨈 raw'!$A:$AAQ, MATCH(Q$3, 'Weekly 쨈 raw'!$A:$A, 0), MATCH($A20, 'Weekly 쨈 raw'!$1:$1, 0)), 0)=0, "", IFERROR(INDEX('Weekly 쨈 raw'!$A:$AAQ, MATCH(Q$3, 'Weekly 쨈 raw'!$A:$A, 0), MATCH($A20, 'Weekly 쨈 raw'!$1:$1, 0)), 0))} | R20: {=IF(IFERROR(INDEX('Weekly 쨈 raw'!$A:$AAQ, MATCH(R$3, 'Weekly 쨈 raw'!$A:$A, 0), MATCH($A20, 'Weekly 쨈 raw'!$1:$1, 0)), 0)=0, "", IFERROR(INDEX('Weekly 쨈 raw'!$A:$AAQ, MATCH(R$3, 'Weekly 쨈 raw'!$A:$A, 0), MATCH($A20, 'Weekly 쨈 raw'!$1:$1, 0)), 0))} | S20: {=IF(IFERROR(INDEX('Weekly 쨈 raw'!$A:$AAQ, MATCH(S$3, 'Weekly 쨈 raw'!$A:$A, 0), MATCH($A20, 'Weekly 쨈 raw'!$1:$1, 0)), 0)=0, "", IFERROR(INDEX('Weekly 쨈 raw'!$A:$AAQ, MATCH(S$3, 'Weekly 쨈 raw'!$A:$A, 0), MATCH($A20, 'Weekly 쨈 raw'!$1:$1, 0)), 0))} | T20: {=IF(IFERROR(INDEX('Weekly 쨈 raw'!$A:$AAQ, MATCH(T$3, 'Weekly 쨈 raw'!$A:$A, 0), MATCH($A20, 'Weekly 쨈 raw'!$1:$1, 0)), 0)=0, "", IFERROR(INDEX('Weekly 쨈 raw'!$A:$AAQ, MATCH(T$3, 'Weekly 쨈 raw'!$A:$A, 0), MATCH($A20, 'Weekly 쨈 raw'!$1:$1, 0)), 0))} | U20: {=IF(IFERROR(INDEX('Weekly 쨈 raw'!$A:$AAQ, MATCH(U$3, 'Weekly 쨈 raw'!$A:$A, 0), MATCH($A20, 'Weekly 쨈 raw'!$1:$1, 0)), 0)=0, "", IFERROR(INDEX('Weekly 쨈 raw'!$A:$AAQ, MATCH(U$3, 'Weekly 쨈 raw'!$A:$A, 0), MATCH($A20, 'Weekly 쨈 raw'!$1:$1, 0)), 0))}
A21: Revenue | B21: Revenue | C21: {=LET(val, IFERROR(INDEX('Weekly 쨈 raw'!$A:$AAQ, MATCH(C$3, 'Weekly 쨈 raw'!$A:$A, 0), MATCH($A21, 'Weekly 쨈 raw'!$1:$1, 0)), ""), IF(val=0, "", val))} -> 2769800 | D21: {=LET(val, IFERROR(INDEX('Weekly 쨈 raw'!$A:$AAQ, MATCH(D$3, 'Weekly 쨈 raw'!$A:$A, 0), MATCH($A21, 'Weekly 쨈 raw'!$1:$1, 0)), ""), IF(val=0, "", val))} -> 3742200 | E21: {=LET(val, IFERROR(INDEX('Weekly 쨈 raw'!$A:$AAQ, MATCH(E$3, 'Weekly 쨈 raw'!$A:$A, 0), MATCH($A21, 'Weekly 쨈 raw'!$1:$1, 0)), ""), IF(val=0, "", val))} -> 2594900 | F21: {=LET(val, IFERROR(INDEX('Weekly 쨈 raw'!$A:$AAQ, MATCH(F$3, 'Weekly 쨈 raw'!$A:$A, 0), MATCH($A21, 'Weekly 쨈 raw'!$1:$1, 0)), ""), IF(val=0, "", val))} -> 2355100 | G21: {=LET(val, IFERROR(INDEX('Weekly 쨈 raw'!$A:$AAQ, MATCH(G$3, 'Weekly 쨈 raw'!$A:$A, 0), MATCH($A21, 'Weekly 쨈 raw'!$1:$1, 0)), ""), IF(val=0, "", val))} -> 7021300 | H21: {=LET(val, IFERROR(INDEX('Weekly 쨈 raw'!$A:$AAQ, MATCH(H$3, 'Weekly 쨈 raw'!$A:$A, 0), MATCH($A21, 'Weekly 쨈 raw'!$1:$1, 0)), ""), IF(val=0, "", val))} -> 4614500 | I21: {=LET(val, IFERROR(INDEX('Weekly 쨈 raw'!$A:$AAQ, MATCH(I$3, 'Weekly 쨈 raw'!$A:$A, 0), MATCH($A21, 'Weekly 쨈 raw'!$1:$1, 0)), ""), IF(val=0, "", val))} -> 2823700 | J21: {=LET(val, IFERROR(INDEX('Weekly 쨈 raw'!$A:$AAQ, MATCH(J$3, 'Weekly 쨈 raw'!$A:$A, 0), MATCH($A21, 'Weekly 쨈 raw'!$1:$1, 0)), ""), IF(val=0, "", val))} -> 3240600 | ... P21: {=LET(val, IFERROR(INDEX('Weekly 쨈 raw'!$A:$AAQ, MATCH(P$3, 'Weekly 쨈 raw'!$A:$A, 0), MATCH($A21, 'Weekly 쨈 raw'!$1:$1, 0)), ""), IF(val=0, "", val))} -> 312200 | Q21: {=IF(IFERROR(INDEX('Weekly 쨈 raw'!$A:$AAQ, MATCH(Q$3, 'Weekly 쨈 raw'!$A:$A, 0), MATCH($A21, 'Weekly 쨈 raw'!$1:$1, 0)), 0)=0, "", IFERROR(INDEX('Weekly 쨈 raw'!$A:$AAQ, MATCH(Q$3, 'Weekly 쨈 raw'!$A:$A, 0), MATCH($A21, 'Weekly 쨈 raw'!$1:$1, 0)), 0))} | R21: {=IF(IFERROR(INDEX('Weekly 쨈 raw'!$A:$AAQ, MATCH(R$3, 'Weekly 쨈 raw'!$A:$A, 0), MATCH($A21, 'Weekly 쨈 raw'!$1:$1, 0)), 0)=0, "", IFERROR(INDEX('Weekly 쨈 raw'!$A:$AAQ, MATCH(R$3, 'Weekly 쨈 raw'!$A:$A, 0), MATCH($A21, 'Weekly 쨈 raw'!$1:$1, 0)), 0))} | S21: {=IF(IFERROR(INDEX('Weekly 쨈 raw'!$A:$AAQ, MATCH(S$3, 'Weekly 쨈 raw'!$A:$A, 0), MATCH($A21, 'Weekly 쨈 raw'!$1:$1, 0)), 0)=0, "", IFERROR(INDEX('Weekly 쨈 raw'!$A:$AAQ, MATCH(S$3, 'Weekly 쨈 raw'!$A:$A, 0), MATCH($A21, 'Weekly 쨈 raw'!$1:$1, 0)), 0))} | T21: {=IF(IFERROR(INDEX('Weekly 쨈 raw'!$A:$AAQ, MATCH(T$3, 'Weekly 쨈 raw'!$A:$A, 0), MATCH($A21, 'Weekly 쨈 raw'!$1:$1, 0)), 0)=0, "", IFERROR(INDEX('Weekly 쨈 raw'!$A:$AAQ, MATCH(T$3, 'Weekly 쨈 raw'!$A:$A, 0), MATCH($A21, 'Weekly 쨈 raw'!$1:$1, 0)), 0))} | U21: {=IF(IFERROR(INDEX('Weekly 쨈 raw'!$A:$AAQ, MATCH(U$3, 'Weekly 쨈 raw'!$A:$A, 0), MATCH($A21, 'Weekly 쨈 raw'!$1:$1, 0)), 0)=0, "", IFERROR(INDEX('Weekly 쨈 raw'!$A:$AAQ, MATCH(U$3, 'Weekly 쨈 raw'!$A:$A, 0), MATCH($A21, 'Weekly 쨈 raw'!$1:$1, 0)), 0))}
A22: Purchase_Done_User_ARPPU | B22: Purchase Done User | C22: {=LET(val, IFERROR(INDEX('Weekly 쨈 raw'!$A:$AAQ, MATCH(C$3, 'Weekly 쨈 raw'!$A:$A, 0), MATCH($A22, 'Weekly 쨈 raw'!$1:$1, 0)), ""), IF(val=0, "", val))} -> 415 | D22: {=LET(val, IFERROR(INDEX('Weekly 쨈 raw'!$A:$AAQ, MATCH(D$3, 'Weekly 쨈 raw'!$A:$A, 0), MATCH($A22, 'Weekly 쨈 raw'!$1:$1, 0)), ""), IF(val=0, "", val))} -> 549 | E22: {=LET(val, IFERROR(INDEX('Weekly 쨈 raw'!$A:$AAQ, MATCH(E$3, 'Weekly 쨈 raw'!$A:$A, 0), MATCH($A22, 'Weekly 쨈 raw'!$1:$1, 0)), ""), IF(val=0, "", val))} -> 420 | F22: {=LET(val, IFERROR(INDEX('Weekly 쨈 raw'!$A:$AAQ, MATCH(F$3, 'Weekly 쨈 raw'!$A:$A, 0), MATCH($A22, 'Weekly 쨈 raw'!$1:$1, 0)), ""), IF(val=0, "", val))} -> 353 | G22: {=LET(val, IFERROR(INDEX('Weekly 쨈 raw'!$A:$AAQ, MATCH(G$3, 'Weekly 쨈 raw'!$A:$A, 0), MATCH($A22, 'Weekly 쨈 raw'!$1:$1, 0)), ""), IF(val=0, "", val))} -> 918 | H22: {=LET(val, IFERROR(INDEX('Weekly 쨈 raw'!$A:$AAQ, MATCH(H$3, 'Weekly 쨈 raw'!$A:$A, 0), MATCH($A22, 'Weekly 쨈 raw'!$1:$1, 0)), ""), IF(val=0, "", val))} -> 593 | I22: {=LET(val, IFERROR(INDEX('Weekly 쨈 raw'!$A:$AAQ, MATCH(I$3, 'Weekly 쨈 raw'!$A:$A, 0), MATCH($A22, 'Weekly 쨈 raw'!$1:$1, 0)), ""), IF(val=0, "", val))} -> 355 | J22: {=LET(val, IFERROR(INDEX('Weekly 쨈 raw'!$A:$AAQ, MATCH(J$3, 'Weekly 쨈 raw'!$A:$A, 0), MATCH($A22, 'Weekly 쨈 raw'!$1:$1, 0)), ""), IF(val=0, "", val))} -> 424 | ... P22: {=LET(val, IFERROR(INDEX('Weekly 쨈 raw'!$A:$AAQ, MATCH(P$3, 'Weekly 쨈 raw'!$A:$A, 0), MATCH($A22, 'Weekly 쨈 raw'!$1:$1, 0)), ""), IF(val=0, "", val))} -> 25 | Q22: {=IF(IFERROR(INDEX('Weekly 쨈 raw'!$A:$AAQ, MATCH(Q$3, 'Weekly 쨈 raw'!$A:$A, 0), MATCH($A22, 'Weekly 쨈 raw'!$1:$1, 0)), 0)=0, "", IFERROR(INDEX('Weekly 쨈 raw'!$A:$AAQ, MATCH(Q$3, 'Weekly 쨈 raw'!$A:$A, 0), MATCH($A22, 'Weekly 쨈 raw'!$1:$1, 0)), 0))} | R22: {=IF(IFERROR(INDEX('Weekly 쨈 raw'!$A:$AAQ, MATCH(R$3, 'Weekly 쨈 raw'!$A:$A, 0), MATCH($A22, 'Weekly 쨈 raw'!$1:$1, 0)), 0)=0, "", IFERROR(INDEX('Weekly 쨈 raw'!$A:$AAQ, MATCH(R$3, 'Weekly 쨈 raw'!$A:$A, 0), MATCH($A22, 'Weekly 쨈 raw'!$1:$1, 0)), 0))} | S22: {=IF(IFERROR(INDEX('Weekly 쨈 raw'!$A:$AAQ, MATCH(S$3, 'Weekly 쨈 raw'!$A:$A, 0), MATCH($A22, 'Weekly 쨈 raw'!$1:$1, 0)), 0)=0, "", IFERROR(INDEX('Weekly 쨈 raw'!$A:$AAQ, MATCH(S$3, 'Weekly 쨈 raw'!$A:$A, 0), MATCH($A22, 'Weekly 쨈 raw'!$1:$1, 0)), 0))} | T22: {=IF(IFERROR(INDEX('Weekly 쨈 raw'!$A:$AAQ, MATCH(T$3, 'Weekly 쨈 raw'!$A:$A, 0), MATCH($A22, 'Weekly 쨈 raw'!$1:$1, 0)), 0)=0, "", IFERROR(INDEX('Weekly 쨈 raw'!$A:$AAQ, MATCH(T$3, 'Weekly 쨈 raw'!$A:$A, 0), MATCH($A22, 'Weekly 쨈 raw'!$1:$1, 0)), 0))} | U22: {=IF(IFERROR(INDEX('Weekly 쨈 raw'!$A:$AAQ, MATCH(U$3, 'Weekly 쨈 raw'!$A:$A, 0), MATCH($A22, 'Weekly 쨈 raw'!$1:$1, 0)), 0)=0, "", IFERROR(INDEX('Weekly 쨈 raw'!$A:$AAQ, MATCH(U$3, 'Weekly 쨈 raw'!$A:$A, 0), MATCH($A22, 'Weekly 쨈 raw'!$1:$1, 0)), 0))}
A23: Purchase_Done_Count | B23: Purchase Done Count | C23: {=LET(val, IFERROR(INDEX('Weekly 쨈 raw'!$A:$AAQ, MATCH(C$3, 'Weekly 쨈 raw'!$A:$A, 0), MATCH($A23, 'Weekly 쨈 raw'!$1:$1, 0)), ""), IF(val=0, "", val))} -> 475 | D23: {=LET(val, IFERROR(INDEX('Weekly 쨈 raw'!$A:$AAQ, MATCH(D$3, 'Weekly 쨈 raw'!$A:$A, 0), MATCH($A23, 'Weekly 쨈 raw'!$1:$1, 0)), ""), IF(val=0, "", val))} -> 618 | E23: {=LET(val, IFERROR(INDEX('Weekly 쨈 raw'!$A:$AAQ, MATCH(E$3, 'Weekly 쨈 raw'!$A:$A, 0), MATCH($A23, 'Weekly 쨈 raw'!$1:$1, 0)), ""), IF(val=0, "", val))} -> 474 | F23: {=LET(val, IFERROR(INDEX('Weekly 쨈 raw'!$A:$AAQ, MATCH(F$3, 'Weekly 쨈 raw'!$A:$A, 0), MATCH($A23, 'Weekly 쨈 raw'!$1:$1, 0)), ""), IF(val=0, "", val))} -> 402 | G23: {=LET(val, IFERROR(INDEX('Weekly 쨈 raw'!$A:$AAQ, MATCH(G$3, 'Weekly 쨈 raw'!$A:$A, 0), MATCH($A23, 'Weekly 쨈 raw'!$1:$1, 0)), ""), IF(val=0, "", val))} -> 1071 | H23: {=LET(val, IFERROR(INDEX('Weekly 쨈 raw'!$A:$AAQ, MATCH(H$3, 'Weekly 쨈 raw'!$A:$A, 0), MATCH($A23, 'Weekly 쨈 raw'!$1:$1, 0)), ""), IF(val=0, "", val))} -> 696 | I23: {=LET(val, IFERROR(INDEX('Weekly 쨈 raw'!$A:$AAQ, MATCH(I$3, 'Weekly 쨈 raw'!$A:$A, 0), MATCH($A23, 'Weekly 쨈 raw'!$1:$1, 0)), ""), IF(val=0, "", val))} -> 431 | J23: {=LET(val, IFERROR(INDEX('Weekly 쨈 raw'!$A:$AAQ, MATCH(J$3, 'Weekly 쨈 raw'!$A:$A, 0), MATCH($A23, 'Weekly 쨈 raw'!$1:$1, 0)), ""), IF(val=0, "", val))} -> 493 | ... P23: {=LET(val, IFERROR(INDEX('Weekly 쨈 raw'!$A:$AAQ, MATCH(P$3, 'Weekly 쨈 raw'!$A:$A, 0), MATCH($A23, 'Weekly 쨈 raw'!$1:$1, 0)), ""), IF(val=0, "", val))} -> 26 | Q23: {=IF(IFERROR(INDEX('Weekly 쨈 raw'!$A:$AAQ, MATCH(Q$3, 'Weekly 쨈 raw'!$A:$A, 0), MATCH($A23, 'Weekly 쨈 raw'!$1:$1, 0)), 0)=0, "", IFERROR(INDEX('Weekly 쨈 raw'!$A:$AAQ, MATCH(Q$3, 'Weekly 쨈 raw'!$A:$A, 0), MATCH($A23, 'Weekly 쨈 raw'!$1:$1, 0)), 0))} | R23: {=IF(IFERROR(INDEX('Weekly 쨈 raw'!$A:$AAQ, MATCH(R$3, 'Weekly 쨈 raw'!$A:$A, 0), MATCH($A23, 'Weekly 쨈 raw'!$1:$1, 0)), 0)=0, "", IFERROR(INDEX('Weekly 쨈 raw'!$A:$AAQ, MATCH(R$3, 'Weekly 쨈 raw'!$A:$A, 0), MATCH($A23, 'Weekly 쨈 raw'!$1:$1, 0)), 0))} | S23: {=IF(IFERROR(INDEX('Weekly 쨈 raw'!$A:$AAQ, MATCH(S$3, 'Weekly 쨈 raw'!$A:$A, 0), MATCH($A23, 'Weekly 쨈 raw'!$1:$1, 0)), 0)=0, "", IFERROR(INDEX('Weekly 쨈 raw'!$A:$AAQ, MATCH(S$3, 'Weekly 쨈 raw'!$A:$A, 0), MATCH($A23, 'Weekly 쨈 raw'!$1:$1, 0)), 0))} | T23: {=IF(IFERROR(INDEX('Weekly 쨈 raw'!$A:$AAQ, MATCH(T$3, 'Weekly 쨈 raw'!$A:$A, 0), MATCH($A23, 'Weekly 쨈 raw'!$1:$1, 0)), 0)=0, "", IFERROR(INDEX('Weekly 쨈 raw'!$A:$AAQ, MATCH(T$3, 'Weekly 쨈 raw'!$A:$A, 0), MATCH($A23, 'Weekly 쨈 raw'!$1:$1, 0)), 0))} | U23: {=IF(IFERROR(INDEX('Weekly 쨈 raw'!$A:$AAQ, MATCH(U$3, 'Weekly 쨈 raw'!$A:$A, 0), MATCH($A23, 'Weekly 쨈 raw'!$1:$1, 0)), 0)=0, "", IFERROR(INDEX('Weekly 쨈 raw'!$A:$AAQ, MATCH(U$3, 'Weekly 쨈 raw'!$A:$A, 0), MATCH($A23, 'Weekly 쨈 raw'!$1:$1, 0)), 0))}
A24: Margin_Rate | B24: 마진율 | C24: {=LET(val, IFERROR(INDEX('Weekly 쨈 raw'!$A:$AAQ, MATCH(C$3, 'Weekly 쨈 raw'!$A:$A, 0), MATCH($A24, 'Weekly 쨈 raw'!$1:$1, 0)), ""), IF(val=0, "", val))} -> -0.41625132 | D24: {=LET(val, IFERROR(INDEX('Weekly 쨈 raw'!$A:$AAQ, MATCH(D$3, 'Weekly 쨈 raw'!$A:$A, 0), MATCH($A24, 'Weekly 쨈 raw'!$1:$1, 0)), ""), IF(val=0, "", val))} -> 0.23331145 | E24: {=LET(val, IFERROR(INDEX('Weekly 쨈 raw'!$A:$AAQ, MATCH(E$3, 'Weekly 쨈 raw'!$A:$A, 0), MATCH($A24, 'Weekly 쨈 raw'!$1:$1, 0)), ""), IF(val=0, "", val))} -> 0.098940113 | F24: {=LET(val, IFERROR(INDEX('Weekly 쨈 raw'!$A:$AAQ, MATCH(F$3, 'Weekly 쨈 raw'!$A:$A, 0), MATCH($A24, 'Weekly 쨈 raw'!$1:$1, 0)), ""), IF(val=0, "", val))} -> 0.1674427 | G24: {=LET(val, IFERROR(INDEX('Weekly 쨈 raw'!$A:$AAQ, MATCH(G$3, 'Weekly 쨈 raw'!$A:$A, 0), MATCH($A24, 'Weekly 쨈 raw'!$1:$1, 0)), ""), IF(val=0, "", val))} -> 0.19495299 | H24: {=LET(val, IFERROR(INDEX('Weekly 쨈 raw'!$A:$AAQ, MATCH(H$3, 'Weekly 쨈 raw'!$A:$A, 0), MATCH($A24, 'Weekly 쨈 raw'!$1:$1, 0)), ""), IF(val=0, "", val))} -> 0.05234929 | I24: {=LET(val, IFERROR(INDEX('Weekly 쨈 raw'!$A:$AAQ, MATCH(I$3, 'Weekly 쨈 raw'!$A:$A, 0), MATCH($A24, 'Weekly 쨈 raw'!$1:$1, 0)), ""), IF(val=0, "", val))} -> -0.073613167 | J24: {=LET(val, IFERROR(INDEX('Weekly 쨈 raw'!$A:$AAQ, MATCH(J$3, 'Weekly 쨈 raw'!$A:$A, 0), MATCH($A24, 'Weekly 쨈 raw'!$1:$1, 0)), ""), IF(val=0, "", val))} -> 0.17819543 | ... P24: {=LET(val, IFERROR(INDEX('Weekly 쨈 raw'!$A:$AAQ, MATCH(P$3, 'Weekly 쨈 raw'!$A:$A, 0), MATCH($A24, 'Weekly 쨈 raw'!$1:$1, 0)), ""), IF(val=0, "", val))} -> -0.0039596413 | Q24: {=IF(IFERROR(INDEX('Weekly 쨈 raw'!$A:$AAQ, MATCH(Q$3, 'Weekly 쨈 raw'!$A:$A, 0), MATCH($A24, 'Weekly 쨈 raw'!$1:$1, 0)), 0)=0, "", IFERROR(INDEX('Weekly 쨈 raw'!$A:$AAQ, MATCH(Q$3, 'Weekly 쨈 raw'!$A:$A, 0), MATCH($A24, 'Weekly 쨈 raw'!$1:$1, 0)), 0))} | R24: {=IF(IFERROR(INDEX('Weekly 쨈 raw'!$A:$AAQ, MATCH(R$3, 'Weekly 쨈 raw'!$A:$A, 0), MATCH($A24, 'Weekly 쨈 raw'!$1:$1, 0)), 0)=0, "", IFERROR(INDEX('Weekly 쨈 raw'!$A:$AAQ, MATCH(R$3, 'Weekly 쨈 raw'!$A:$A, 0), MATCH($A24, 'Weekly 쨈 raw'!$1:$1, 0)), 0))} | S24: {=IF(IFERROR(INDEX('Weekly 쨈 raw'!$A:$AAQ, MATCH(S$3, 'Weekly 쨈 raw'!$A:$A, 0), MATCH($A24, 'Weekly 쨈 raw'!$1:$1, 0)), 0)=0, "", IFERROR(INDEX('Weekly 쨈 raw'!$A:$AAQ, MATCH(S$3, 'Weekly 쨈 raw'!$A:$A, 0), MATCH($A24, 'Weekly 쨈 raw'!$1:$1, 0)), 0))} | T24: {=IF(IFERROR(INDEX('Weekly 쨈 raw'!$A:$AAQ, MATCH(T$3, 'Weekly 쨈 raw'!$A:$A, 0), MATCH($A24, 'Weekly 쨈 raw'!$1:$1, 0)), 0)=0, "", IFERROR(INDEX('Weekly 쨈 raw'!$A:$AAQ, MATCH(T$3, 'Weekly 쨈 raw'!$A:$A, 0), MATCH($A24, 'Weekly 쨈 raw'!$1:$1, 0)), 0))} | U24: {=IF(IFERROR(INDEX('Weekly 쨈 raw'!$A:$AAQ, MATCH(U$3, 'Weekly 쨈 raw'!$A:$A, 0), MATCH($A24, 'Weekly 쨈 raw'!$1:$1, 0)), 0)=0, "", IFERROR(INDEX('Weekly 쨈 raw'!$A:$AAQ, MATCH(U$3, 'Weekly 쨈 raw'!$A:$A, 0), MATCH($A24, 'Weekly 쨈 raw'!$1:$1, 0)), 0))}
A25: Cost | B25: Cost | C25: {=LET(val, IFERROR(INDEX('Weekly 쨈 raw'!$A:$AAQ, MATCH(C$3, 'Weekly 쨈 raw'!$A:$A, 0), MATCH($A25, 'Weekly 쨈 raw'!$1:$1, 0)), ""), IF(val=0, "", val))} -> 3922732.9 | D25: {=LET(val, IFERROR(INDEX('Weekly 쨈 raw'!$A:$AAQ, MATCH(D$3, 'Weekly 쨈 raw'!$A:$A, 0), MATCH($A25, 'Weekly 쨈 raw'!$1:$1, 0)), ""), IF(val=0, "", val))} -> 2869101.9 | E25: {=LET(val, IFERROR(INDEX('Weekly 쨈 raw'!$A:$AAQ, MATCH(E$3, 'Weekly 쨈 raw'!$A:$A, 0), MATCH($A25, 'Weekly 쨈 raw'!$1:$1, 0)), ""), IF(val=0, "", val))} -> 2338160.3 | F25: {=LET(val, IFERROR(INDEX('Weekly 쨈 raw'!$A:$AAQ, MATCH(F$3, 'Weekly 쨈 raw'!$A:$A, 0), MATCH($A25, 'Weekly 쨈 raw'!$1:$1, 0)), ""), IF(val=0, "", val))} -> 1960755.7 | G25: {=LET(val, IFERROR(INDEX('Weekly 쨈 raw'!$A:$AAQ, MATCH(G$3, 'Weekly 쨈 raw'!$A:$A, 0), MATCH($A25, 'Weekly 쨈 raw'!$1:$1, 0)), ""), IF(val=0, "", val))} -> 5652476.6 | H25: {=LET(val, IFERROR(INDEX('Weekly 쨈 raw'!$A:$AAQ, MATCH(H$3, 'Weekly 쨈 raw'!$A:$A, 0), MATCH($A25, 'Weekly 쨈 raw'!$1:$1, 0)), ""), IF(val=0, "", val))} -> 4372934.2 | I25: {=LET(val, IFERROR(INDEX('Weekly 쨈 raw'!$A:$AAQ, MATCH(I$3, 'Weekly 쨈 raw'!$A:$A, 0), MATCH($A25, 'Weekly 쨈 raw'!$1:$1, 0)), ""), IF(val=0, "", val))} -> 3031561.5 | J25: {=LET(val, IFERROR(INDEX('Weekly 쨈 raw'!$A:$AAQ, MATCH(J$3, 'Weekly 쨈 raw'!$A:$A, 0), MATCH($A25, 'Weekly 쨈 raw'!$1:$1, 0)), ""), IF(val=0, "", val))} -> 2663139.9 | ... P25: {=LET(val, IFERROR(INDEX('Weekly 쨈 raw'!$A:$AAQ, MATCH(P$3, 'Weekly 쨈 raw'!$A:$A, 0), MATCH($A25, 'Weekly 쨈 raw'!$1:$1, 0)), ""), IF(val=0, "", val))} -> 313436.2 | Q25: {=IF(IFERROR(INDEX('Weekly 쨈 raw'!$A:$AAQ, MATCH(Q$3, 'Weekly 쨈 raw'!$A:$A, 0), MATCH($A25, 'Weekly 쨈 raw'!$1:$1, 0)), 0)=0, "", IFERROR(INDEX('Weekly 쨈 raw'!$A:$AAQ, MATCH(Q$3, 'Weekly 쨈 raw'!$A:$A, 0), MATCH($A25, 'Weekly 쨈 raw'!$1:$1, 0)), 0))} | R25: {=IF(IFERROR(INDEX('Weekly 쨈 raw'!$A:$AAQ, MATCH(R$3, 'Weekly 쨈 raw'!$A:$A, 0), MATCH($A25, 'Weekly 쨈 raw'!$1:$1, 0)), 0)=0, "", IFERROR(INDEX('Weekly 쨈 raw'!$A:$AAQ, MATCH(R$3, 'Weekly 쨈 raw'!$A:$A, 0), MATCH($A25, 'Weekly 쨈 raw'!$1:$1, 0)), 0))} | S25: {=IF(IFERROR(INDEX('Weekly 쨈 raw'!$A:$AAQ, MATCH(S$3, 'Weekly 쨈 raw'!$A:$A, 0), MATCH($A25, 'Weekly 쨈 raw'!$1:$1, 0)), 0)=0, "", IFERROR(INDEX('Weekly 쨈 raw'!$A:$AAQ, MATCH(S$3, 'Weekly 쨈 raw'!$A:$A, 0), MATCH($A25, 'Weekly 쨈 raw'!$1:$1, 0)), 0))} | T25: {=IF(IFERROR(INDEX('Weekly 쨈 raw'!$A:$AAQ, MATCH(T$3, 'Weekly 쨈 raw'!$A:$A, 0), MATCH($A25, 'Weekly 쨈 raw'!$1:$1, 0)), 0)=0, "", IFERROR(INDEX('Weekly 쨈 raw'!$A:$AAQ, MATCH(T$3, 'Weekly 쨈 raw'!$A:$A, 0), MATCH($A25, 'Weekly 쨈 raw'!$1:$1, 0)), 0))} | U25: {=IF(IFERROR(INDEX('Weekly 쨈 raw'!$A:$AAQ, MATCH(U$3, 'Weekly 쨈 raw'!$A:$A, 0), MATCH($A25, 'Weekly 쨈 raw'!$1:$1, 0)), 0)=0, "", IFERROR(INDEX('Weekly 쨈 raw'!$A:$AAQ, MATCH(U$3, 'Weekly 쨈 raw'!$A:$A, 0), MATCH($A25, 'Weekly 쨈 raw'!$1:$1, 0)), 0))}
A26: Revenue_ | B26: Revenue | C26: {=LET(val, IFERROR(INDEX('Weekly 쨈 raw'!$A:$AAQ, MATCH(C$3, 'Weekly 쨈 raw'!$A:$A, 0), MATCH($A26, 'Weekly 쨈 raw'!$1:$1, 0)), ""), IF(val=0, "", val))} -> 2769800 | D26: {=LET(val, IFERROR(INDEX('Weekly 쨈 raw'!$A:$AAQ, MATCH(D$3, 'Weekly 쨈 raw'!$A:$A, 0), MATCH($A26, 'Weekly 쨈 raw'!$1:$1, 0)), ""), IF(val=0, "", val))} -> 3742200 | E26: {=LET(val, IFERROR(INDEX('Weekly 쨈 raw'!$A:$AAQ, MATCH(E$3, 'Weekly 쨈 raw'!$A:$A, 0), MATCH($A26, 'Weekly 쨈 raw'!$1:$1, 0)), ""), IF(val=0, "", val))} -> 2594900 | F26: {=LET(val, IFERROR(INDEX('Weekly 쨈 raw'!$A:$AAQ, MATCH(F$3, 'Weekly 쨈 raw'!$A:$A, 0), MATCH($A26, 'Weekly 쨈 raw'!$1:$1, 0)), ""), IF(val=0, "", val))} -> 2355100 | G26: {=LET(val, IFERROR(INDEX('Weekly 쨈 raw'!$A:$AAQ, MATCH(G$3, 'Weekly 쨈 raw'!$A:$A, 0), MATCH($A26, 'Weekly 쨈 raw'!$1:$1, 0)), ""), IF(val=0, "", val))} -> 7021300 | H26: {=LET(val, IFERROR(INDEX('Weekly 쨈 raw'!$A:$AAQ, MATCH(H$3, 'Weekly 쨈 raw'!$A:$A, 0), MATCH($A26, 'Weekly 쨈 raw'!$1:$1, 0)), ""), IF(val=0, "", val))} -> 4614500 | I26: {=LET(val, IFERROR(INDEX('Weekly 쨈 raw'!$A:$AAQ, MATCH(I$3, 'Weekly 쨈 raw'!$A:$A, 0), MATCH($A26, 'Weekly 쨈 raw'!$1:$1, 0)), ""), IF(val=0, "", val))} -> 2823700 | J26: {=LET(val, IFERROR(INDEX('Weekly 쨈 raw'!$A:$AAQ, MATCH(J$3, 'Weekly 쨈 raw'!$A:$A, 0), MATCH($A26, 'Weekly 쨈 raw'!$1:$1, 0)), ""), IF(val=0, "", val))} -> 3240600 | ... P26: {=LET(val, IFERROR(INDEX('Weekly 쨈 raw'!$A:$AAQ, MATCH(P$3, 'Weekly 쨈 raw'!$A:$A, 0), MATCH($A26, 'Weekly 쨈 raw'!$1:$1, 0)), ""), IF(val=0, "", val))} -> 312200 | Q26: {=IF(IFERROR(INDEX('Weekly 쨈 raw'!$A:$AAQ, MATCH(Q$3, 'Weekly 쨈 raw'!$A:$A, 0), MATCH($A26, 'Weekly 쨈 raw'!$1:$1, 0)), 0)=0, "", IFERROR(INDEX('Weekly 쨈 raw'!$A:$AAQ, MATCH(Q$3, 'Weekly 쨈 raw'!$A:$A, 0), MATCH($A26, 'Weekly 쨈 raw'!$1:$1, 0)), 0))} | R26: {=IF(IFERROR(INDEX('Weekly 쨈 raw'!$A:$AAQ, MATCH(R$3, 'Weekly 쨈 raw'!$A:$A, 0), MATCH($A26, 'Weekly 쨈 raw'!$1:$1, 0)), 0)=0, "", IFERROR(INDEX('Weekly 쨈 raw'!$A:$AAQ, MATCH(R$3, 'Weekly 쨈 raw'!$A:$A, 0), MATCH($A26, 'Weekly 쨈 raw'!$1:$1, 0)), 0))} | S26: {=IF(IFERROR(INDEX('Weekly 쨈 raw'!$A:$AAQ, MATCH(S$3, 'Weekly 쨈 raw'!$A:$A, 0), MATCH($A26, 'Weekly 쨈 raw'!$1:$1, 0)), 0)=0, "", IFERROR(INDEX('Weekly 쨈 raw'!$A:$AAQ, MATCH(S$3, 'Weekly 쨈 raw'!$A:$A, 0), MATCH($A26, 'Weekly 쨈 raw'!$1:$1, 0)), 0))} | T26: {=IF(IFERROR(INDEX('Weekly 쨈 raw'!$A:$AAQ, MATCH(T$3, 'Weekly 쨈 raw'!$A:$A, 0), MATCH($A26, 'Weekly 쨈 raw'!$1:$1, 0)), 0)=0, "", IFERROR(INDEX('Weekly 쨈 raw'!$A:$AAQ, MATCH(T$3, 'Weekly 쨈 raw'!$A:$A, 0), MATCH($A26, 'Weekly 쨈 raw'!$1:$1, 0)), 0))} | U26: {=IF(IFERROR(INDEX('Weekly 쨈 raw'!$A:$AAQ, MATCH(U$3, 'Weekly 쨈 raw'!$A:$A, 0), MATCH($A26, 'Weekly 쨈 raw'!$1:$1, 0)), 0)=0, "", IFERROR(INDEX('Weekly 쨈 raw'!$A:$AAQ, MATCH(U$3, 'Weekly 쨈 raw'!$A:$A, 0), MATCH($A26, 'Weekly 쨈 raw'!$1:$1, 0)), 0))}
B27: PMF 서베이 중, '이 서비스가 없으면 매우 실망할 것 같아요' 비중 | C27: {=LET(val, IFERROR(INDEX('Weekly 쨈 raw'!$A:$AAQ, MATCH(C$3, 'Weekly 쨈 raw'!$A:$A, 0), MATCH($A27, 'Weekly 쨈 raw'!$1:$1, 0)), ""), IF(val=0, "", val))} | D27: {=LET(val, IFERROR(INDEX('Weekly 쨈 raw'!$A:$AAQ, MATCH(D$3, 'Weekly 쨈 raw'!$A:$A, 0), MATCH($A27, 'Weekly 쨈 raw'!$1:$1, 0)), ""), IF(val=0, "", val))} | E27: {=LET(val, IFERROR(INDEX('Weekly 쨈 raw'!$A:$AAQ, MATCH(E$3, 'Weekly 쨈 raw'!$A:$A, 0), MATCH($A27, 'Weekly 쨈 raw'!$1:$1, 0)), ""), IF(val=0, "", val))} | F27: {=LET(val, IFERROR(INDEX('Weekly 쨈 raw'!$A:$AAQ, MATCH(F$3, 'Weekly 쨈 raw'!$A:$A, 0), MATCH($A27, 'Weekly 쨈 raw'!$1:$1, 0)), ""), IF(val=0, "", val))} | G27: {=LET(val, IFERROR(INDEX('Weekly 쨈 raw'!$A:$AAQ, MATCH(G$3, 'Weekly 쨈 raw'!$A:$A, 0), MATCH($A27, 'Weekly 쨈 raw'!$1:$1, 0)), ""), IF(val=0, "", val))} | H27: {=LET(val, IFERROR(INDEX('Weekly 쨈 raw'!$A:$AAQ, MATCH(H$3, 'Weekly 쨈 raw'!$A:$A, 0), MATCH($A27, 'Weekly 쨈 raw'!$1:$1, 0)), ""), IF(val=0, "", val))} | I27: {=LET(val, IFERROR(INDEX('Weekly 쨈 raw'!$A:$AAQ, MATCH(I$3, 'Weekly 쨈 raw'!$A:$A, 0), MATCH($A27, 'Weekly 쨈 raw'!$1:$1, 0)), ""), IF(val=0, "", val))} | J27: {=LET(val, IFERROR(INDEX('Weekly 쨈 raw'!$A:$AAQ, MATCH(J$3, 'Weekly 쨈 raw'!$A:$A, 0), MATCH($A27, 'Weekly 쨈 raw'!$1:$1, 0)), ""), IF(val=0, "", val))} | ... P27: {=LET(val, IFERROR(INDEX('Weekly 쨈 raw'!$A:$AAQ, MATCH(P$3, 'Weekly 쨈 raw'!$A:$A, 0), MATCH($A27, 'Weekly 쨈 raw'!$1:$1, 0)), ""), IF(val=0, "", val))} | Q27: {=IF(IFERROR(INDEX('Weekly 쨈 raw'!$A:$AAQ, MATCH(Q$3, 'Weekly 쨈 raw'!$A:$A, 0), MATCH($A27, 'Weekly 쨈 raw'!$1:$1, 0)), 0)=0, "", IFERROR(INDEX('Weekly 쨈 raw'!$A:$AAQ, MATCH(Q$3, 'Weekly 쨈 raw'!$A:$A, 0), MATCH($A27, 'Weekly 쨈 raw'!$1:$1, 0)), 0))} | R27: {=IF(IFERROR(INDEX('Weekly 쨈 raw'!$A:$AAQ, MATCH(R$3, 'Weekly 쨈 raw'!$A:$A, 0), MATCH($A27, 'Weekly 쨈 raw'!$1:$1, 0)), 0)=0, "", IFERROR(INDEX('Weekly 쨈 raw'!$A:$AAQ, MATCH(R$3, 'Weekly 쨈 raw'!$A:$A, 0), MATCH($A27, 'Weekly 쨈 raw'!$1:$1, 0)), 0))} | S27: {=IF(IFERROR(INDEX('Weekly 쨈 raw'!$A:$AAQ, MATCH(S$3, 'Weekly 쨈 raw'!$A:$A, 0), MATCH($A27, 'Weekly 쨈 raw'!$1:$1, 0)), 0)=0, "", IFERROR(INDEX('Weekly 쨈 raw'!$A:$AAQ, MATCH(S$3, 'Weekly 쨈 raw'!$A:$A, 0), MATCH($A27, 'Weekly 쨈 raw'!$1:$1, 0)), 0))} | T27: {=IF(IFERROR(INDEX('Weekly 쨈 raw'!$A:$AAQ, MATCH(T$3, 'Weekly 쨈 raw'!$A:$A, 0), MATCH($A27, 'Weekly 쨈 raw'!$1:$1, 0)), 0)=0, "", IFERROR(INDEX('Weekly 쨈 raw'!$A:$AAQ, MATCH(T$3, 'Weekly 쨈 raw'!$A:$A, 0), MATCH($A27, 'Weekly 쨈 raw'!$1:$1, 0)), 0))} | U27: {=IF(IFERROR(INDEX('Weekly 쨈 raw'!$A:$AAQ, MATCH(U$3, 'Weekly 쨈 raw'!$A:$A, 0), MATCH($A27, 'Weekly 쨈 raw'!$1:$1, 0)), 0)=0, "", IFERROR(INDEX('Weekly 쨈 raw'!$A:$AAQ, MATCH(U$3, 'Weekly 쨈 raw'!$A:$A, 0), MATCH($A27, 'Weekly 쨈 raw'!$1:$1, 0)), 0))}
B28: ㄴ VD User | C28: {=LET(val, IFERROR(INDEX('Weekly 쨈 raw'!$A:$AAQ, MATCH(C$3, 'Weekly 쨈 raw'!$A:$A, 0), MATCH($A28, 'Weekly 쨈 raw'!$1:$1, 0)), ""), IF(val=0, "", val))} | D28: {=LET(val, IFERROR(INDEX('Weekly 쨈 raw'!$A:$AAQ, MATCH(D$3, 'Weekly 쨈 raw'!$A:$A, 0), MATCH($A28, 'Weekly 쨈 raw'!$1:$1, 0)), ""), IF(val=0, "", val))} | E28: {=LET(val, IFERROR(INDEX('Weekly 쨈 raw'!$A:$AAQ, MATCH(E$3, 'Weekly 쨈 raw'!$A:$A, 0), MATCH($A28, 'Weekly 쨈 raw'!$1:$1, 0)), ""), IF(val=0, "", val))} | F28: {=LET(val, IFERROR(INDEX('Weekly 쨈 raw'!$A:$AAQ, MATCH(F$3, 'Weekly 쨈 raw'!$A:$A, 0), MATCH($A28, 'Weekly 쨈 raw'!$1:$1, 0)), ""), IF(val=0, "", val))} | G28: {=LET(val, IFERROR(INDEX('Weekly 쨈 raw'!$A:$AAQ, MATCH(G$3, 'Weekly 쨈 raw'!$A:$A, 0), MATCH($A28, 'Weekly 쨈 raw'!$1:$1, 0)), ""), IF(val=0, "", val))} | H28: {=LET(val, IFERROR(INDEX('Weekly 쨈 raw'!$A:$AAQ, MATCH(H$3, 'Weekly 쨈 raw'!$A:$A, 0), MATCH($A28, 'Weekly 쨈 raw'!$1:$1, 0)), ""), IF(val=0, "", val))} | I28: {=LET(val, IFERROR(INDEX('Weekly 쨈 raw'!$A:$AAQ, MATCH(I$3, 'Weekly 쨈 raw'!$A:$A, 0), MATCH($A28, 'Weekly 쨈 raw'!$1:$1, 0)), ""), IF(val=0, "", val))} | J28: {=LET(val, IFERROR(INDEX('Weekly 쨈 raw'!$A:$AAQ, MATCH(J$3, 'Weekly 쨈 raw'!$A:$A, 0), MATCH($A28, 'Weekly 쨈 raw'!$1:$1, 0)), ""), IF(val=0, "", val))} | ... P28: {=LET(val, IFERROR(INDEX('Weekly 쨈 raw'!$A:$AAQ, MATCH(P$3, 'Weekly 쨈 raw'!$A:$A, 0), MATCH($A28, 'Weekly 쨈 raw'!$1:$1, 0)), ""), IF(val=0, "", val))} | Q28: {=IF(IFERROR(INDEX('Weekly 쨈 raw'!$A:$AAQ, MATCH(Q$3, 'Weekly 쨈 raw'!$A:$A, 0), MATCH($A28, 'Weekly 쨈 raw'!$1:$1, 0)), 0)=0, "", IFERROR(INDEX('Weekly 쨈 raw'!$A:$AAQ, MATCH(Q$3, 'Weekly 쨈 raw'!$A:$A, 0), MATCH($A28, 'Weekly 쨈 raw'!$1:$1, 0)), 0))} | R28: {=IF(IFERROR(INDEX('Weekly 쨈 raw'!$A:$AAQ, MATCH(R$3, 'Weekly 쨈 raw'!$A:$A, 0), MATCH($A28, 'Weekly 쨈 raw'!$1:$1, 0)), 0)=0, "", IFERROR(INDEX('Weekly 쨈 raw'!$A:$AAQ, MATCH(R$3, 'Weekly 쨈 raw'!$A:$A, 0), MATCH($A28, 'Weekly 쨈 raw'!$1:$1, 0)), 0))} | S28: {=IF(IFERROR(INDEX('Weekly 쨈 raw'!$A:$AAQ, MATCH(S$3, 'Weekly 쨈 raw'!$A:$A, 0), MATCH($A28, 'Weekly 쨈 raw'!$1:$1, 0)), 0)=0, "", IFERROR(INDEX('Weekly 쨈 raw'!$A:$AAQ, MATCH(S$3, 'Weekly 쨈 raw'!$A:$A, 0), MATCH($A28, 'Weekly 쨈 raw'!$1:$1, 0)), 0))} | T28: {=IF(IFERROR(INDEX('Weekly 쨈 raw'!$A:$AAQ, MATCH(T$3, 'Weekly 쨈 raw'!$A:$A, 0), MATCH($A28, 'Weekly 쨈 raw'!$1:$1, 0)), 0)=0, "", IFERROR(INDEX('Weekly 쨈 raw'!$A:$AAQ, MATCH(T$3, 'Weekly 쨈 raw'!$A:$A, 0), MATCH($A28, 'Weekly 쨈 raw'!$1:$1, 0)), 0))} | U28: {=IF(IFERROR(INDEX('Weekly 쨈 raw'!$A:$AAQ, MATCH(U$3, 'Weekly 쨈 raw'!$A:$A, 0), MATCH($A28, 'Weekly 쨈 raw'!$1:$1, 0)), 0)=0, "", IFERROR(INDEX('Weekly 쨈 raw'!$A:$AAQ, MATCH(U$3, 'Weekly 쨈 raw'!$A:$A, 0), MATCH($A28, 'Weekly 쨈 raw'!$1:$1, 0)), 0))}
B29: ㄴ SD User | C29: {=LET(val, IFERROR(INDEX('Weekly 쨈 raw'!$A:$AAQ, MATCH(C$3, 'Weekly 쨈 raw'!$A:$A, 0), MATCH($A29, 'Weekly 쨈 raw'!$1:$1, 0)), ""), IF(val=0, "", val))} | D29: {=LET(val, IFERROR(INDEX('Weekly 쨈 raw'!$A:$AAQ, MATCH(D$3, 'Weekly 쨈 raw'!$A:$A, 0), MATCH($A29, 'Weekly 쨈 raw'!$1:$1, 0)), ""), IF(val=0, "", val))} | E29: {=LET(val, IFERROR(INDEX('Weekly 쨈 raw'!$A:$AAQ, MATCH(E$3, 'Weekly 쨈 raw'!$A:$A, 0), MATCH($A29, 'Weekly 쨈 raw'!$1:$1, 0)), ""), IF(val=0, "", val))} | F29: {=LET(val, IFERROR(INDEX('Weekly 쨈 raw'!$A:$AAQ, MATCH(F$3, 'Weekly 쨈 raw'!$A:$A, 0), MATCH($A29, 'Weekly 쨈 raw'!$1:$1, 0)), ""), IF(val=0, "", val))} | G29: {=LET(val, IFERROR(INDEX('Weekly 쨈 raw'!$A:$AAQ, MATCH(G$3, 'Weekly 쨈 raw'!$A:$A, 0), MATCH($A29, 'Weekly 쨈 raw'!$1:$1, 0)), ""), IF(val=0, "", val))} | H29: {=LET(val, IFERROR(INDEX('Weekly 쨈 raw'!$A:$AAQ, MATCH(H$3, 'Weekly 쨈 raw'!$A:$A, 0), MATCH($A29, 'Weekly 쨈 raw'!$1:$1, 0)), ""), IF(val=0, "", val))} | I29: {=LET(val, IFERROR(INDEX('Weekly 쨈 raw'!$A:$AAQ, MATCH(I$3, 'Weekly 쨈 raw'!$A:$A, 0), MATCH($A29, 'Weekly 쨈 raw'!$1:$1, 0)), ""), IF(val=0, "", val))} | J29: {=LET(val, IFERROR(INDEX('Weekly 쨈 raw'!$A:$AAQ, MATCH(J$3, 'Weekly 쨈 raw'!$A:$A, 0), MATCH($A29, 'Weekly 쨈 raw'!$1:$1, 0)), ""), IF(val=0, "", val))} | ... P29: {=LET(val, IFERROR(INDEX('Weekly 쨈 raw'!$A:$AAQ, MATCH(P$3, 'Weekly 쨈 raw'!$A:$A, 0), MATCH($A29, 'Weekly 쨈 raw'!$1:$1, 0)), ""), IF(val=0, "", val))} | Q29: {=IF(IFERROR(INDEX('Weekly 쨈 raw'!$A:$AAQ, MATCH(Q$3, 'Weekly 쨈 raw'!$A:$A, 0), MATCH($A29, 'Weekly 쨈 raw'!$1:$1, 0)), 0)=0, "", IFERROR(INDEX('Weekly 쨈 raw'!$A:$AAQ, MATCH(Q$3, 'Weekly 쨈 raw'!$A:$A, 0), MATCH($A29, 'Weekly 쨈 raw'!$1:$1, 0)), 0))} | R29: {=IF(IFERROR(INDEX('Weekly 쨈 raw'!$A:$AAQ, MATCH(R$3, 'Weekly 쨈 raw'!$A:$A, 0), MATCH($A29, 'Weekly 쨈 raw'!$1:$1, 0)), 0)=0, "", IFERROR(INDEX('Weekly 쨈 raw'!$A:$AAQ, MATCH(R$3, 'Weekly 쨈 raw'!$A:$A, 0), MATCH($A29, 'Weekly 쨈 raw'!$1:$1, 0)), 0))} | S29: {=IF(IFERROR(INDEX('Weekly 쨈 raw'!$A:$AAQ, MATCH(S$3, 'Weekly 쨈 raw'!$A:$A, 0), MATCH($A29, 'Weekly 쨈 raw'!$1:$1, 0)), 0)=0, "", IFERROR(INDEX('Weekly 쨈 raw'!$A:$AAQ, MATCH(S$3, 'Weekly 쨈 raw'!$A:$A, 0), MATCH($A29, 'Weekly 쨈 raw'!$1:$1, 0)), 0))} | T29: {=IF(IFERROR(INDEX('Weekly 쨈 raw'!$A:$AAQ, MATCH(T$3, 'Weekly 쨈 raw'!$A:$A, 0), MATCH($A29, 'Weekly 쨈 raw'!$1:$1, 0)), 0)=0, "", IFERROR(INDEX('Weekly 쨈 raw'!$A:$AAQ, MATCH(T$3, 'Weekly 쨈 raw'!$A:$A, 0), MATCH($A29, 'Weekly 쨈 raw'!$1:$1, 0)), 0))} | U29: {=IF(IFERROR(INDEX('Weekly 쨈 raw'!$A:$AAQ, MATCH(U$3, 'Weekly 쨈 raw'!$A:$A, 0), MATCH($A29, 'Weekly 쨈 raw'!$1:$1, 0)), 0)=0, "", IFERROR(INDEX('Weekly 쨈 raw'!$A:$AAQ, MATCH(U$3, 'Weekly 쨈 raw'!$A:$A, 0), MATCH($A29, 'Weekly 쨈 raw'!$1:$1, 0)), 0))}
B30: ㄴ ND User | C30: {=LET(val, IFERROR(INDEX('Weekly 쨈 raw'!$A:$AAQ, MATCH(C$3, 'Weekly 쨈 raw'!$A:$A, 0), MATCH($A30, 'Weekly 쨈 raw'!$1:$1, 0)), ""), IF(val=0, "", val))} | D30: {=LET(val, IFERROR(INDEX('Weekly 쨈 raw'!$A:$AAQ, MATCH(D$3, 'Weekly 쨈 raw'!$A:$A, 0), MATCH($A30, 'Weekly 쨈 raw'!$1:$1, 0)), ""), IF(val=0, "", val))} | E30: {=LET(val, IFERROR(INDEX('Weekly 쨈 raw'!$A:$AAQ, MATCH(E$3, 'Weekly 쨈 raw'!$A:$A, 0), MATCH($A30, 'Weekly 쨈 raw'!$1:$1, 0)), ""), IF(val=0, "", val))} | F30: {=LET(val, IFERROR(INDEX('Weekly 쨈 raw'!$A:$AAQ, MATCH(F$3, 'Weekly 쨈 raw'!$A:$A, 0), MATCH($A30, 'Weekly 쨈 raw'!$1:$1, 0)), ""), IF(val=0, "", val))} | G30: {=LET(val, IFERROR(INDEX('Weekly 쨈 raw'!$A:$AAQ, MATCH(G$3, 'Weekly 쨈 raw'!$A:$A, 0), MATCH($A30, 'Weekly 쨈 raw'!$1:$1, 0)), ""), IF(val=0, "", val))} | H30: {=LET(val, IFERROR(INDEX('Weekly 쨈 raw'!$A:$AAQ, MATCH(H$3, 'Weekly 쨈 raw'!$A:$A, 0), MATCH($A30, 'Weekly 쨈 raw'!$1:$1, 0)), ""), IF(val=0, "", val))} | I30: {=LET(val, IFERROR(INDEX('Weekly 쨈 raw'!$A:$AAQ, MATCH(I$3, 'Weekly 쨈 raw'!$A:$A, 0), MATCH($A30, 'Weekly 쨈 raw'!$1:$1, 0)), ""), IF(val=0, "", val))} | J30: {=LET(val, IFERROR(INDEX('Weekly 쨈 raw'!$A:$AAQ, MATCH(J$3, 'Weekly 쨈 raw'!$A:$A, 0), MATCH($A30, 'Weekly 쨈 raw'!$1:$1, 0)), ""), IF(val=0, "", val))} | ... P30: {=LET(val, IFERROR(INDEX('Weekly 쨈 raw'!$A:$AAQ, MATCH(P$3, 'Weekly 쨈 raw'!$A:$A, 0), MATCH($A30, 'Weekly 쨈 raw'!$1:$1, 0)), ""), IF(val=0, "", val))} | Q30: {=IF(IFERROR(INDEX('Weekly 쨈 raw'!$A:$AAQ, MATCH(Q$3, 'Weekly 쨈 raw'!$A:$A, 0), MATCH($A30, 'Weekly 쨈 raw'!$1:$1, 0)), 0)=0, "", IFERROR(INDEX('Weekly 쨈 raw'!$A:$AAQ, MATCH(Q$3, 'Weekly 쨈 raw'!$A:$A, 0), MATCH($A30, 'Weekly 쨈 raw'!$1:$1, 0)), 0))} | R30: {=IF(IFERROR(INDEX('Weekly 쨈 raw'!$A:$AAQ, MATCH(R$3, 'Weekly 쨈 raw'!$A:$A, 0), MATCH($A30, 'Weekly 쨈 raw'!$1:$1, 0)), 0)=0, "", IFERROR(INDEX('Weekly 쨈 raw'!$A:$AAQ, MATCH(R$3, 'Weekly 쨈 raw'!$A:$A, 0), MATCH($A30, 'Weekly 쨈 raw'!$1:$1, 0)), 0))} | S30: {=IF(IFERROR(INDEX('Weekly 쨈 raw'!$A:$AAQ, MATCH(S$3, 'Weekly 쨈 raw'!$A:$A, 0), MATCH($A30, 'Weekly 쨈 raw'!$1:$1, 0)), 0)=0, "", IFERROR(INDEX('Weekly 쨈 raw'!$A:$AAQ, MATCH(S$3, 'Weekly 쨈 raw'!$A:$A, 0), MATCH($A30, 'Weekly 쨈 raw'!$1:$1, 0)), 0))} | T30: {=IF(IFERROR(INDEX('Weekly 쨈 raw'!$A:$AAQ, MATCH(T$3, 'Weekly 쨈 raw'!$A:$A, 0), MATCH($A30, 'Weekly 쨈 raw'!$1:$1, 0)), 0)=0, "", IFERROR(INDEX('Weekly 쨈 raw'!$A:$AAQ, MATCH(T$3, 'Weekly 쨈 raw'!$A:$A, 0), MATCH($A30, 'Weekly 쨈 raw'!$1:$1, 0)), 0))} | U30: {=IF(IFERROR(INDEX('Weekly 쨈 raw'!$A:$AAQ, MATCH(U$3, 'Weekly 쨈 raw'!$A:$A, 0), MATCH($A30, 'Weekly 쨈 raw'!$1:$1, 0)), 0)=0, "", IFERROR(INDEX('Weekly 쨈 raw'!$A:$AAQ, MATCH(U$3, 'Weekly 쨈 raw'!$A:$A, 0), MATCH($A30, 'Weekly 쨈 raw'!$1:$1, 0)), 0))}
